[{"t":"CXAction","p":"documentation/CallKit/CXAction","r":"Class","a":"An abstract class that declares a programmatic interface for objects that represent a telephony action.","v":{"iOS":"10.0","iPadOS":"10.0","Mac Catalyst":"10.0","visionOS":"1.0","watchOS":"9.0"}},{"t":"CXAnswerCallAction","p":"documentation/CallKit/CXAnswerCallAction","r":"Class","a":"An encapsulation of the act of answering an incoming call.","v":{"iOS":"10.0","iPadOS":"10.0","Mac Catalyst":"10.0","visionOS":"1.0","watchOS":"9.0"}},{"t":"CXCall","p":"documentation/CallKit/CXCall","r":"Class","a":"A telephony call.","v":{"iOS":"10.0","iPadOS":"10.0","Mac Catalyst":"10.0","visionOS":"1.0","watchOS":"9.0"}},{"t":"CXCallAction","p":"documentation/CallKit/CXCallAction","r":"Class","a":"A programmatic interface for objects that represent a telephony action associated with a call object.","v":{"iOS":"10.0","iPadOS":"10.0","Mac Catalyst":"10.0","visionOS":"1.0","watchOS":"9.0"}},{"t":"CXCallController","p":"documentation/CallKit/CXCallController","r":"Class","a":"A programmatic interface for interacting with and observing calls.","v":{"iOS":"10.0","iPadOS":"10.0","Mac Catalyst":"10.0","visionOS":"1.0","watchOS":"9.0"}},{"t":"CXCallDirectoryExtensionContext","p":"documentation/CallKit/CXCallDirectoryExtensionContext","r":"Class","a":"A programmatic interface for adding identification and blocking entries to a Call Directory app extension.","v":{"iOS":"10.0","iPadOS":"10.0","Mac Catalyst":"10.0","visionOS":"1.0"}},{"t":"CXCallDirectoryExtensionContextDelegate","p":"documentation/CallKit/CXCallDirectoryExtensionContextDelegate","r":"Protocol","a":"A collection of methods a Call Directory extension context object calls when a request fails.","v":{"iOS":"10.0","iPadOS":"10.0","Mac Catalyst":"10.0","visionOS":"1.0"}},{"t":"CXCallDirectoryManager","p":"documentation/CallKit/CXCallDirectoryManager","r":"Class","a":"The programmatic interface to an object that manages a Call Directory app extension.","v":{"iOS":"10.0","iPadOS":"10.0","Mac Catalyst":"10.0","visionOS":"1.0"}},{"t":"CXCallDirectoryManager.EnabledStatus","p":"documentation/CallKit/CXCallDirectoryManager/EnabledStatus","r":"Enumeration","a":"The enabled status of a Call Directory app extension, as reported by the [getEnabledStatusForExtension(withIdentifier:completionHandler:)](/documentation/callkit/cxcalldirectorymanager/getenabledstatusforextension(withidentifier:completionhandler:)) method.","v":{"iOS":"10.0","iPadOS":"10.0","Mac Catalyst":"10.0","visionOS":"1.0"}},{"t":"CXCallDirectoryManager.EnabledStatus.disabled","p":"documentation/CallKit/CXCallDirectoryManager/EnabledStatus/disabled","r":"Case","a":"Indicates that the extension is disabled.","v":{"iOS":"10.0","iPadOS":"10.0","Mac Catalyst":"10.0","visionOS":"1.0"}},{"t":"CXCallDirectoryManager.EnabledStatus.enabled","p":"documentation/CallKit/CXCallDirectoryManager/EnabledStatus/enabled","r":"Case","a":"Indicates that the extension is enabled.","v":{"iOS":"10.0","iPadOS":"10.0","Mac Catalyst":"10.0","visionOS":"1.0"}},{"t":"CXCallDirectoryManager.EnabledStatus.unknown","p":"documentation/CallKit/CXCallDirectoryManager/EnabledStatus/unknown","r":"Case","a":"Indicates that the enabled status for the extension is unknown.","v":{"iOS":"10.0","iPadOS":"10.0","Mac Catalyst":"10.0","visionOS":"1.0"}},{"t":"CXCallDirectoryPhoneNumber","p":"documentation/CallKit/CXCallDirectoryPhoneNumber","r":"Type Alias","a":"A value that represents a phone number consisting of a country calling code followed by a sequence of digits.","v":{"iOS":"10.0","iPadOS":"10.0","Mac Catalyst":"13.0","macOS":"13.0","visionOS":"1.0","watchOS":"9.0"}},{"t":"CXCallDirectoryPhoneNumberMax","p":"documentation/CallKit/CXCallDirectoryPhoneNumberMax","r":"Global Variable","a":"The maximum allowable value for a phone number.","v":{"iOS":"10.0","iPadOS":"10.0","Mac Catalyst":"13.0","macOS":"13.0","visionOS":"1.0","watchOS":"9.0"}},{"t":"CXCallDirectoryProvider","p":"documentation/CallKit/CXCallDirectoryProvider","r":"Class","a":"The principal object for a Call Directory app extension for a host app.","v":{"iOS":"10.0","iPadOS":"10.0","Mac Catalyst":"10.0","visionOS":"1.0"}},{"t":"CXCallEndedReason","p":"documentation/CallKit/CXCallEndedReason","r":"Enumeration","a":"The reason that a call ended.","v":{"iOS":"10.0","iPadOS":"10.0","Mac Catalyst":"10.0","visionOS":"1.0","watchOS":"9.0"}},{"t":"CXCallEndedReason.answeredElsewhere","p":"documentation/CallKit/CXCallEndedReason/answeredElsewhere","r":"Case","a":"Another device answered the call.","v":{"iOS":"10.0","iPadOS":"10.0","Mac Catalyst":"10.0","visionOS":"1.0","watchOS":"9.0"}},{"t":"CXCallEndedReason.declinedElsewhere","p":"documentation/CallKit/CXCallEndedReason/declinedElsewhere","r":"Case","a":"Another device declined the call.","v":{"iOS":"10.0","iPadOS":"10.0","Mac Catalyst":"10.0","visionOS":"1.0","watchOS":"9.0"}},{"t":"CXCallEndedReason.failed","p":"documentation/CallKit/CXCallEndedReason/failed","r":"Case","a":"An error occurred while attempting to service the call.","v":{"iOS":"10.0","iPadOS":"10.0","Mac Catalyst":"10.0","visionOS":"1.0","watchOS":"9.0"}},{"t":"CXCallEndedReason.remoteEnded","p":"documentation/CallKit/CXCallEndedReason/remoteEnded","r":"Case","a":"The remote party explicitly ended the call.","v":{"iOS":"10.0","iPadOS":"10.0","Mac Catalyst":"10.0","visionOS":"1.0","watchOS":"9.0"}},{"t":"CXCallEndedReason.unanswered","p":"documentation/CallKit/CXCallEndedReason/unanswered","r":"Case","a":"The call never started connecting and was never explicitly ended, such as when an outgoing or incoming call times out.","v":{"iOS":"10.0","iPadOS":"10.0","Mac Catalyst":"10.0","visionOS":"1.0","watchOS":"9.0"}},{"t":"CXCallObserver","p":"documentation/CallKit/CXCallObserver","r":"Class","a":"A programmatic interface for an object that manages a list of active calls and observes call changes.","v":{"iOS":"10.0","iPadOS":"10.0","Mac Catalyst":"10.0","visionOS":"1.0","watchOS":"9.0"}},{"t":"CXCallObserverDelegate","p":"documentation/CallKit/CXCallObserverDelegate","r":"Protocol","a":"A collection of methods the system calls when a call changes state.","v":{"iOS":"10.0","iPadOS":"10.0","Mac Catalyst":"10.0","visionOS":"1.0","watchOS":"9.0"}},{"t":"CXCallUpdate","p":"documentation/CallKit/CXCallUpdate","r":"Class","a":"An encapsulation of new and changed information about a call.","v":{"iOS":"10.0","iPadOS":"10.0","Mac Catalyst":"10.0","visionOS":"1.0","watchOS":"9.0"}},{"t":"CXEndCallAction","p":"documentation/CallKit/CXEndCallAction","r":"Class","a":"An encapsulation of the act of ending a call.","v":{"iOS":"10.0","iPadOS":"10.0","Mac Catalyst":"10.0","visionOS":"1.0","watchOS":"9.0"}},{"t":"CXError","p":"documentation/CallKit/CXError","r":"Structure","a":"Error codes for the CallKit errors.","v":{"iOS":"10.0","iPadOS":"10.0","Mac Catalyst":"10.0","visionOS":"1.0","watchOS":"9.0"}},{"t":"CXError.Code","p":"documentation/CallKit/CXError/Code","r":"Enumeration","a":"Error codes for the CallKit errors.","v":{"iOS":"10.0","iPadOS":"10.0","Mac Catalyst":"10.0","visionOS":"1.0","watchOS":"9.0"}},{"t":"CXError.Code.invalidArgument","p":"documentation/CallKit/CXError/Code/invalidArgument","r":"Case","a":"The argument is invalid.","v":{"iOS":"13.2","iPadOS":"13.2","Mac Catalyst":"13.2","visionOS":"1.0","watchOS":"9.0"}},{"t":"CXError.Code.missingVoIPBackgroundMode","p":"documentation/CallKit/CXError/Code/missingVoIPBackgroundMode","r":"Case","v":{"iOS":"14.5","iPadOS":"14.5","Mac Catalyst":"14.5","visionOS":"1.0","watchOS":"9.0"}},{"t":"CXError.Code.unentitled","p":"documentation/CallKit/CXError/Code/unentitled","r":"Case","a":"The caller doesn\u2019t have the correct entitlement.","v":{"iOS":"13.2","iPadOS":"13.2","Mac Catalyst":"13.2","visionOS":"1.0","watchOS":"9.0"}},{"t":"CXError.Code.unknownError","p":"documentation/CallKit/CXError/Code/unknownError","r":"Case","a":"An unknown error occurred.","v":{"iOS":"10.0","iPadOS":"10.0","Mac Catalyst":"10.0","visionOS":"1.0","watchOS":"9.0"}},{"t":"CXErrorCodeCallDirectoryManagerError","p":"documentation/CallKit/CXErrorCodeCallDirectoryManagerError-swift.struct","r":"Structure","a":"Errors when interacting with a call directory manager.","v":{"iOS":"10.0","iPadOS":"10.0","Mac Catalyst":"10.0","visionOS":"1.0","watchOS":"9.0"}},{"t":"CXErrorCodeCallDirectoryManagerError.Code","p":"documentation/CallKit/CXErrorCodeCallDirectoryManagerError-swift.struct/Code","r":"Enumeration","a":"Error codes the CallKit framework returns.","v":{"iOS":"10.0","iPadOS":"10.0","Mac Catalyst":"10.0","visionOS":"1.0","watchOS":"9.0"}},{"t":"CXErrorCodeCallDirectoryManagerError.Code.currentlyLoading","p":"documentation/CallKit/CXErrorCodeCallDirectoryManagerError-swift.struct/Code/currentlyLoading","r":"Case","a":"The call directory manager is loading the app extension.","v":{"iOS":"10.3","iPadOS":"10.3","Mac Catalyst":"10.3","visionOS":"1.0","watchOS":"3.2"}},{"t":"CXErrorCodeCallDirectoryManagerError.Code.duplicateEntries","p":"documentation/CallKit/CXErrorCodeCallDirectoryManagerError-swift.struct/Code/duplicateEntries","r":"Case","a":"There are duplicate entries in the call directory.","v":{"iOS":"10.0","iPadOS":"10.0","Mac Catalyst":"10.0","visionOS":"1.0","watchOS":"9.0"}},{"t":"CXErrorCodeCallDirectoryManagerError.Code.entriesOutOfOrder","p":"documentation/CallKit/CXErrorCodeCallDirectoryManagerError-swift.struct/Code/entriesOutOfOrder","r":"Case","a":"The entries in the call directory are out of order.","v":{"iOS":"10.0","iPadOS":"10.0","Mac Catalyst":"10.0","visionOS":"1.0","watchOS":"9.0"}},{"t":"CXErrorCodeCallDirectoryManagerError.Code.extensionDisabled","p":"documentation/CallKit/CXErrorCodeCallDirectoryManagerError-swift.struct/Code/extensionDisabled","r":"Case","a":"The call directory extension isn\u2019t enabled by the system.","v":{"iOS":"10.0","iPadOS":"10.0","Mac Catalyst":"10.0","visionOS":"1.0","watchOS":"9.0"}},{"t":"CXErrorCodeCallDirectoryManagerError.Code.loadingInterrupted","p":"documentation/CallKit/CXErrorCodeCallDirectoryManagerError-swift.struct/Code/loadingInterrupted","r":"Case","a":"The call directory manager was interrupted while loading the app extension.","v":{"iOS":"10.0","iPadOS":"10.0","Mac Catalyst":"10.0","visionOS":"1.0","watchOS":"9.0"}},{"t":"CXErrorCodeCallDirectoryManagerError.Code.maximumEntriesExceeded","p":"documentation/CallKit/CXErrorCodeCallDirectoryManagerError-swift.struct/Code/maximumEntriesExceeded","r":"Case","a":"There are too many entries in the call directory.","v":{"iOS":"10.0","iPadOS":"10.0","Mac Catalyst":"10.0","visionOS":"1.0","watchOS":"9.0"}},{"t":"CXErrorCodeCallDirectoryManagerError.Code.noExtensionFound","p":"documentation/CallKit/CXErrorCodeCallDirectoryManagerError-swift.struct/Code/noExtensionFound","r":"Case","a":"The call directory manager could not find a corresponding app extension.","v":{"iOS":"10.0","iPadOS":"10.0","Mac Catalyst":"10.0","visionOS":"1.0","watchOS":"9.0"}},{"t":"CXErrorCodeCallDirectoryManagerError.Code.unexpectedIncrementalRemoval","p":"documentation/CallKit/CXErrorCodeCallDirectoryManagerError-swift.struct/Code/unexpectedIncrementalRemoval","r":"Case","a":"A request occurred before confirming incremental loading.","v":{"iOS":"11.0","iPadOS":"11.0","Mac Catalyst":"11.0","visionOS":"1.0","watchOS":"4.0"}},{"t":"CXErrorCodeCallDirectoryManagerError.Code.unknown","p":"documentation/CallKit/CXErrorCodeCallDirectoryManagerError-swift.struct/Code/unknown","r":"Case","a":"An unknown error occurred.","v":{"iOS":"10.0","iPadOS":"10.0","Mac Catalyst":"10.0","visionOS":"1.0","watchOS":"9.0"}},{"t":"CXErrorCodeIncomingCallError","p":"documentation/CallKit/CXErrorCodeIncomingCallError-swift.struct","r":"Structure","a":"Codes for errors that occur during incoming calls.","v":{"iOS":"10.0","iPadOS":"10.0","Mac Catalyst":"10.0","visionOS":"1.0","watchOS":"9.0"}},{"t":"CXErrorCodeIncomingCallError.Code","p":"documentation/CallKit/CXErrorCodeIncomingCallError-swift.struct/Code","r":"Enumeration","a":"Codes for errors that occur during incoming calls.","v":{"iOS":"10.0","iPadOS":"10.0","Mac Catalyst":"10.0","visionOS":"1.0","watchOS":"9.0"}},{"t":"CXErrorCodeIncomingCallError.Code.callIsProtected","p":"documentation/CallKit/CXErrorCodeIncomingCallError-swift.struct/Code/callIsProtected","r":"Case","v":{"iOS":"10.0","iPadOS":"10.0","Mac Catalyst":"10.0","visionOS":"1.0","watchOS":"9.0"}},{"t":"CXErrorCodeIncomingCallError.Code.callUUIDAlreadyExists","p":"documentation/CallKit/CXErrorCodeIncomingCallError-swift.struct/Code/callUUIDAlreadyExists","r":"Case","a":"The incoming call UUID already exists.","v":{"iOS":"10.0","iPadOS":"10.0","Mac Catalyst":"10.0","visionOS":"1.0","watchOS":"9.0"}},{"t":"CXErrorCodeIncomingCallError.Code.filteredByBlockList","p":"documentation/CallKit/CXErrorCodeIncomingCallError-swift.struct/Code/filteredByBlockList","r":"Case","a":"The incoming call is filtered because the incoming caller has been blocked by the user.","v":{"iOS":"10.0","iPadOS":"10.0","Mac Catalyst":"10.0","visionOS":"1.0","watchOS":"9.0"}},{"t":"CXErrorCodeIncomingCallError.Code.filteredByDoNotDisturb","p":"documentation/CallKit/CXErrorCodeIncomingCallError-swift.struct/Code/filteredByDoNotDisturb","r":"Case","a":"The incoming call is filtered because Do Not Disturb is active and the incoming caller is not a VIP.","v":{"iOS":"10.0","iPadOS":"10.0","Mac Catalyst":"10.0","visionOS":"1.0","watchOS":"9.0"}},{"t":"CXErrorCodeIncomingCallError.Code.filteredBySensitiveParticipants","p":"documentation/CallKit/CXErrorCodeIncomingCallError-swift.struct/Code/filteredBySensitiveParticipants","r":"Case","v":{"iOS":"10.0","iPadOS":"10.0","Mac Catalyst":"10.0","visionOS":"1.0","watchOS":"9.0"}},{"t":"CXErrorCodeIncomingCallError.Code.filteredDuringRestrictedSharingMode","p":"documentation/CallKit/CXErrorCodeIncomingCallError-swift.struct/Code/filteredDuringRestrictedSharingMode","r":"Case","v":{"iOS":"10.0","iPadOS":"10.0","Mac Catalyst":"10.0","visionOS":"1.0","watchOS":"9.0"}},{"t":"CXErrorCodeIncomingCallError.Code.unentitled","p":"documentation/CallKit/CXErrorCodeIncomingCallError-swift.struct/Code/unentitled","r":"Case","a":"The app isn\u2019t entitled to receive incoming calls.","v":{"iOS":"10.0","iPadOS":"10.0","Mac Catalyst":"10.0","visionOS":"1.0","watchOS":"9.0"}},{"t":"CXErrorCodeIncomingCallError.Code.unknown","p":"documentation/CallKit/CXErrorCodeIncomingCallError-swift.struct/Code/unknown","r":"Case","a":"An unknown error occurred.","v":{"iOS":"10.0","iPadOS":"10.0","Mac Catalyst":"10.0","visionOS":"1.0","watchOS":"9.0"}},{"t":"CXErrorCodeNotificationServiceExtensionError","p":"documentation/CallKit/CXErrorCodeNotificationServiceExtensionError-swift.struct","r":"Structure","a":"Errors that can occur when reporting new, incoming VoIP calls.","v":{"iOS":"14.5","iPadOS":"14.5","Mac Catalyst":"14.5","visionOS":"1.0","watchOS":"9.0"}},{"t":"CXErrorCodeNotificationServiceExtensionError.Code","p":"documentation/CallKit/CXErrorCodeNotificationServiceExtensionError-swift.struct/Code","r":"Enumeration","a":"Constants for errors returned when reporting new, incoming VoIP calls.","v":{"iOS":"14.5","iPadOS":"14.5","Mac Catalyst":"14.5","visionOS":"1.0","watchOS":"9.0"}},{"t":"CXErrorCodeNotificationServiceExtensionError.Code.invalidClientProcess","p":"documentation/CallKit/CXErrorCodeNotificationServiceExtensionError-swift.struct/Code/invalidClientProcess","r":"Case","a":"An error indicating that an invalid client process reported the incoming call.","v":{"iOS":"14.5","iPadOS":"14.5","Mac Catalyst":"14.5","visionOS":"1.0","watchOS":"9.0"}},{"t":"CXErrorCodeNotificationServiceExtensionError.Code.missingNotificationFilteringEntitlement","p":"documentation/CallKit/CXErrorCodeNotificationServiceExtensionError-swift.struct/Code/missingNotificationFilteringEntitlement","r":"Case","a":"An error indicating that the notification service extension is missing the required filtering entitlement.","v":{"iOS":"14.5","iPadOS":"14.5","Mac Catalyst":"14.5","visionOS":"1.0","watchOS":"9.0"}},{"t":"CXErrorCodeNotificationServiceExtensionError.Code.unknown","p":"documentation/CallKit/CXErrorCodeNotificationServiceExtensionError-swift.struct/Code/unknown","r":"Case","a":"An error that occurs when there is an unknown problem.","v":{"iOS":"14.5","iPadOS":"14.5","Mac Catalyst":"14.5","visionOS":"1.0","watchOS":"9.0"}},{"t":"CXErrorCodeRequestTransactionError","p":"documentation/CallKit/CXErrorCodeRequestTransactionError-swift.struct","r":"Structure","v":{"iOS":"10.0","iPadOS":"10.0","Mac Catalyst":"10.0","visionOS":"1.0","watchOS":"9.0"}},{"t":"CXErrorCodeRequestTransactionError.Code","p":"documentation/CallKit/CXErrorCodeRequestTransactionError-swift.struct/Code","r":"Enumeration","a":"Error codes for the CallKit error domain.","v":{"iOS":"10.0","iPadOS":"10.0","Mac Catalyst":"10.0","visionOS":"1.0","watchOS":"9.0"}},{"t":"CXErrorCodeRequestTransactionError.Code.callIsProtected","p":"documentation/CallKit/CXErrorCodeRequestTransactionError-swift.struct/Code/callIsProtected","r":"Case","v":{"iOS":"10.0","iPadOS":"10.0","Mac Catalyst":"10.0","visionOS":"1.0","watchOS":"9.0"}},{"t":"CXErrorCodeRequestTransactionError.Code.callUUIDAlreadyExists","p":"documentation/CallKit/CXErrorCodeRequestTransactionError-swift.struct/Code/callUUIDAlreadyExists","r":"Case","a":"The requested transaction contains call actions that reference a UUID that already exists.","v":{"iOS":"10.0","iPadOS":"10.0","Mac Catalyst":"10.0","visionOS":"1.0","watchOS":"9.0"}},{"t":"CXErrorCodeRequestTransactionError.Code.emptyTransaction","p":"documentation/CallKit/CXErrorCodeRequestTransactionError-swift.struct/Code/emptyTransaction","r":"Case","a":"The requested transaction contains no actions.","v":{"iOS":"10.0","iPadOS":"10.0","Mac Catalyst":"10.0","visionOS":"1.0","watchOS":"9.0"}},{"t":"CXErrorCodeRequestTransactionError.Code.invalidAction","p":"documentation/CallKit/CXErrorCodeRequestTransactionError-swift.struct/Code/invalidAction","r":"Case","a":"The requested transaction contains an invalid action.","v":{"iOS":"10.0","iPadOS":"10.0","Mac Catalyst":"10.0","visionOS":"1.0","watchOS":"9.0"}},{"t":"CXErrorCodeRequestTransactionError.Code.maximumCallGroupsReached","p":"documentation/CallKit/CXErrorCodeRequestTransactionError-swift.struct/Code/maximumCallGroupsReached","r":"Case","a":"The requested transaction contains actions that, if performed, would exceed the maximum number of call groups for the provider.","v":{"iOS":"10.0","iPadOS":"10.0","Mac Catalyst":"10.0","visionOS":"1.0","watchOS":"9.0"}},{"t":"CXErrorCodeRequestTransactionError.Code.unentitled","p":"documentation/CallKit/CXErrorCodeRequestTransactionError-swift.struct/Code/unentitled","r":"Case","a":"The app isn\u2019t entitled to perform the actions in the requested transaction.","v":{"iOS":"10.0","iPadOS":"10.0","Mac Catalyst":"10.0","visionOS":"1.0","watchOS":"9.0"}},{"t":"CXErrorCodeRequestTransactionError.Code.unknown","p":"documentation/CallKit/CXErrorCodeRequestTransactionError-swift.struct/Code/unknown","r":"Case","a":"An unknown error occurred.","v":{"iOS":"10.0","iPadOS":"10.0","Mac Catalyst":"10.0","visionOS":"1.0","watchOS":"9.0"}},{"t":"CXErrorCodeRequestTransactionError.Code.unknownCallProvider","p":"documentation/CallKit/CXErrorCodeRequestTransactionError-swift.struct/Code/unknownCallProvider","r":"Case","a":"The controller couldn\u2019t find a call provider to perform the actions in the requested transaction.","v":{"iOS":"10.0","iPadOS":"10.0","Mac Catalyst":"10.0","visionOS":"1.0","watchOS":"9.0"}},{"t":"CXErrorCodeRequestTransactionError.Code.unknownCallUUID","p":"documentation/CallKit/CXErrorCodeRequestTransactionError-swift.struct/Code/unknownCallUUID","r":"Case","a":"The requested transaction contains call actions that reference an unknown UUID.","v":{"iOS":"10.0","iPadOS":"10.0","Mac Catalyst":"10.0","visionOS":"1.0","watchOS":"9.0"}},{"t":"CXErrorDomain","p":"documentation/CallKit/CXErrorDomain","r":"Global Variable","a":"The domain for CallKit errors.","v":{"iOS":"10.0","iPadOS":"10.0","Mac Catalyst":"10.0","visionOS":"1.0","watchOS":"9.0"}},{"t":"CXErrorDomainCallDirectoryManager","p":"documentation/CallKit/CXErrorDomainCallDirectoryManager","r":"Global Variable","a":"Domain for errors when interacting with a call directory manager.","v":{"iOS":"10.0","iPadOS":"10.0","Mac Catalyst":"10.0","visionOS":"1.0","watchOS":"9.0"}},{"t":"CXErrorDomainIncomingCall","p":"documentation/CallKit/CXErrorDomainIncomingCall","r":"Global Variable","a":"The domain for errors that occur during incoming calls.","v":{"iOS":"10.0","iPadOS":"10.0","Mac Catalyst":"10.0","visionOS":"1.0","watchOS":"9.0"}},{"t":"CXErrorDomainNotificationServiceExtension","p":"documentation/CallKit/CXErrorDomainNotificationServiceExtension","r":"Global Variable","v":{"iOS":"14.5","iPadOS":"14.5","Mac Catalyst":"14.5","visionOS":"1.0","watchOS":"9.0"}},{"t":"CXErrorDomainRequestTransaction","p":"documentation/CallKit/CXErrorDomainRequestTransaction","r":"Global Variable","a":"Domain for errors when requesting a transaction from a call controller.","v":{"iOS":"10.0","iPadOS":"10.0","Mac Catalyst":"10.0","visionOS":"1.0","watchOS":"9.0"}},{"t":"CXHandle","p":"documentation/CallKit/CXHandle","r":"Class","a":"A way to reach a call recipient, such as a phone number or email address.","v":{"iOS":"10.0","iPadOS":"10.0","Mac Catalyst":"10.0","visionOS":"1.0","watchOS":"9.0"}},{"t":"CXHandle.HandleType","p":"documentation/CallKit/CXHandle/HandleType","r":"Enumeration","a":"The possible types of handles.","v":{"iOS":"10.0","iPadOS":"10.0","Mac Catalyst":"10.0","visionOS":"1.0","watchOS":"9.0"}},{"t":"CXHandle.HandleType.emailAddress","p":"documentation/CallKit/CXHandle/HandleType/emailAddress","r":"Case","a":"An email address.","v":{"iOS":"10.0","iPadOS":"10.0","Mac Catalyst":"10.0","visionOS":"1.0","watchOS":"9.0"}},{"t":"CXHandle.HandleType.generic","p":"documentation/CallKit/CXHandle/HandleType/generic","r":"Case","a":"An unspecified type of handle.","v":{"iOS":"10.0","iPadOS":"10.0","Mac Catalyst":"10.0","visionOS":"1.0","watchOS":"9.0"}},{"t":"CXHandle.HandleType.phoneNumber","p":"documentation/CallKit/CXHandle/HandleType/phoneNumber","r":"Case","a":"A phone number.","v":{"iOS":"10.0","iPadOS":"10.0","Mac Catalyst":"10.0","visionOS":"1.0","watchOS":"9.0"}},{"t":"CXPlayDTMFCallAction","p":"documentation/CallKit/CXPlayDTMFCallAction","r":"Class","a":"An encapsulation of the act of playing a dual tone multifrequency (DTMF) sequence.","v":{"iOS":"10.0","iPadOS":"10.0","Mac Catalyst":"10.0","visionOS":"1.0","watchOS":"9.0"}},{"t":"CXPlayDTMFCallAction.ActionType","p":"documentation/CallKit/CXPlayDTMFCallAction/ActionType","r":"Enumeration","a":"The types of events that generate dial tones.","v":{"iOS":"10.0","iPadOS":"10.0","Mac Catalyst":"10.0","visionOS":"1.0","watchOS":"9.0"}},{"t":"CXPlayDTMFCallAction.ActionType.hardPause","p":"documentation/CallKit/CXPlayDTMFCallAction/ActionType/hardPause","r":"Case","a":"Indicates that the user included digits after a hard pause in their dial string. A hard pause is indicated by a semicolon (`;`) and waits for further user interaction before dialing the additional digits.","v":{"iOS":"10.0","iPadOS":"10.0","Mac Catalyst":"10.0","visionOS":"1.0","watchOS":"9.0"}},{"t":"CXPlayDTMFCallAction.ActionType.singleTone","p":"documentation/CallKit/CXPlayDTMFCallAction/ActionType/singleTone","r":"Case","a":"Indicates that the user tapped a digit on the in-call keypad.","v":{"iOS":"10.0","iPadOS":"10.0","Mac Catalyst":"10.0","visionOS":"1.0","watchOS":"9.0"}},{"t":"CXPlayDTMFCallAction.ActionType.softPause","p":"documentation/CallKit/CXPlayDTMFCallAction/ActionType/softPause","r":"Case","a":"Indicates that the user included digits after a soft pause in their dial string. A soft pause is indicated by a comma (`,`) and waits a few seconds before dialing the additional digits.","v":{"iOS":"10.0","iPadOS":"10.0","Mac Catalyst":"10.0","visionOS":"1.0","watchOS":"9.0"}},{"t":"CXProvider","p":"documentation/CallKit/CXProvider","r":"Class","a":"An object that represents a telephony provider.","v":{"iOS":"10.0","iPadOS":"10.0","Mac Catalyst":"10.0","visionOS":"1.0","watchOS":"9.0"}},{"t":"CXProviderConfiguration","p":"documentation/CallKit/CXProviderConfiguration","r":"Class","a":"An encapsulation of the configuration of a provider object.","v":{"iOS":"10.0","iPadOS":"10.0","Mac Catalyst":"10.0","macOS":"11.0","visionOS":"1.0","watchOS":"9.0"}},{"t":"CXProviderDelegate","p":"documentation/CallKit/CXProviderDelegate","r":"Protocol","a":"A collection of methods that a telephony provider object calls.","v":{"iOS":"10.0","iPadOS":"10.0","Mac Catalyst":"10.0","visionOS":"1.0","watchOS":"9.0"}},{"t":"CXSetGroupCallAction","p":"documentation/CallKit/CXSetGroupCallAction","r":"Class","a":"An encapsulation of the act of grouping or ungrouping calls.","v":{"iOS":"10.0","iPadOS":"10.0","Mac Catalyst":"10.0","visionOS":"1.0","watchOS":"9.0"}},{"t":"CXSetHeldCallAction","p":"documentation/CallKit/CXSetHeldCallAction","r":"Class","a":"An encapsulation of the act of placing a call on hold or removing a call from hold.","v":{"iOS":"10.0","iPadOS":"10.0","Mac Catalyst":"10.0","visionOS":"1.0","watchOS":"9.0"}},{"t":"CXSetMutedCallAction","p":"documentation/CallKit/CXSetMutedCallAction","r":"Class","a":"An encapsulation of the act of muting or unmuting a call.","v":{"iOS":"10.0","iPadOS":"10.0","Mac Catalyst":"10.0","visionOS":"1.0","watchOS":"9.0"}},{"t":"CXSetTranslatingCallAction","p":"documentation/CallKit/CXSetTranslatingCallAction","r":"Class","a":"An encapsulation of the act of translating a call.","v":{"iOS":"26.0","iPadOS":"26.0","Mac Catalyst":"26.0"}},{"t":"CXStartCallAction","p":"documentation/CallKit/CXStartCallAction","r":"Class","a":"An encapsulation of the act of initiating an outgoing call.","v":{"iOS":"10.0","iPadOS":"10.0","Mac Catalyst":"10.0","visionOS":"1.0","watchOS":"9.0"}},{"t":"CXTransaction","p":"documentation/CallKit/CXTransaction","r":"Class","a":"An object that contains zero or more action objects for a call controller to perform.","v":{"iOS":"10.0","iPadOS":"10.0","Mac Catalyst":"10.0","visionOS":"1.0","watchOS":"9.0"}},{"t":"CXTranslationEngine","p":"documentation/CallKit/CXTranslationEngine","r":"Enumeration","a":"Values that describe the translation engine that provided a translation.","v":{"iOS":"10.0","iPadOS":"10.0","Mac Catalyst":"10.0"}},{"t":"CXTranslationEngine.custom","p":"documentation/CallKit/CXTranslationEngine/custom","r":"Case","v":{"iOS":"10.0","iPadOS":"10.0","Mac Catalyst":"10.0"}},{"t":"CXTranslationEngine.default","p":"documentation/CallKit/CXTranslationEngine/default","r":"Case","a":"The translation was provided by the system\u2019s default translation engine.","v":{"iOS":"10.0","iPadOS":"10.0","Mac Catalyst":"10.0"}},{"t":"CX_CLASS_AVAILABLE","p":"documentation/CallKit/CX_CLASS_AVAILABLE","r":"Macro","v":{"iOS":"10.0","iPadOS":"10.0","Mac Catalyst":"13.0","macOS":"13.0","visionOS":"1.0","watchOS":"9.0"}},{"t":"CX_EXTERN","p":"documentation/CallKit/CX_EXTERN","r":"Macro","v":{"iOS":"10.0","iPadOS":"10.0","Mac Catalyst":"13.0","macOS":"13.0","visionOS":"1.0","watchOS":"9.0"}},{"t":"CallKit","p":"documentation/CallKit","r":"Framework","a":"Display the system-calling UI for your app\u2019s VoIP services, and coordinate your calling services with other apps and the system.","v":{"iOS":"10.0","iPadOS":"10.0","Mac Catalyst":"13.0","macOS":"13.0","visionOS":"1.0","watchOS":"9.0"}},{"t":"CallKit Constants","p":"documentation/CallKit/callkit-constants","r":"API Collection"},{"t":"CallKit Enumerations","p":"documentation/CallKit/callkit-enumerations","r":"API Collection"},{"t":"Identifying and blocking calls","p":"documentation/CallKit/identifying-and-blocking-calls","r":"Article","a":"Create a Call Directory app extension to identify and block incoming callers by their phone number."},{"t":"Making and receiving VoIP calls","p":"documentation/CallKit/making-and-receiving-voip-calls","r":"Article","a":"Initiate outgoing calls with VoIP and configure your app to receive incoming calls."},{"t":"Preparing your app to be the default calling app","p":"documentation/CallKit/Preparing-your-app-to-be-the-default-calling-app","r":"Article","a":"Configure your CallKit or LiveCommunicationKit app so people can set it as the default calling app on their device."},{"t":"Sending End-to-End Encrypted VoIP Calls","p":"documentation/CallKit/sending-end-to-end-encrypted-voip-calls","r":"Article","a":"Initiate VoIP calls when your server can\u2019t determine whether an outgoing notification is a request for a VoIP call due to metadata encryption."},{"t":"VoIP calling with CallKit","p":"documentation/CallKit/voip-calling-with-callkit","r":"Sample Code","a":"Use the CallKit framework to integrate native VoIP calling.","v":{"iOS":"13.0","iPadOS":"13.0","Mac Catalyst":"13.0","watchOS":"9.0","Xcode":"14.0"}},{"t":"actions","p":"documentation/CallKit/CXTransaction/actions","r":"Instance Property","a":"The actions added to a transaction.","v":{"iOS":"10.0","iPadOS":"10.0","Mac Catalyst":"10.0","visionOS":"1.0","watchOS":"9.0"}},{"t":"addAction(_:)","p":"documentation/CallKit/CXTransaction/addAction(_:)","r":"Instance Method","a":"Adds the specified action to the transaction."},{"t":"addBlockingEntry(withNextSequentialPhoneNumber:)","p":"documentation/CallKit/CXCallDirectoryExtensionContext/addBlockingEntry(withNextSequentialPhoneNumber:)","r":"Instance Method","a":"Adds a blocking entry with the specified phone number."},{"t":"addIdentificationEntry(withNextSequentialPhoneNumber:label:)","p":"documentation/CallKit/CXCallDirectoryExtensionContext/addIdentificationEntry(withNextSequentialPhoneNumber:label:)","r":"Instance Method","a":"Adds an identification entry with the specified phone number and label."},{"t":"beginRequest(with:)","p":"documentation/CallKit/CXCallDirectoryProvider/beginRequest(with:)","r":"Instance Method","a":"Tells the extension to prepare for a host app\u2019s request."},{"t":"callIsProtected","p":"documentation/CallKit/CXErrorCodeIncomingCallError-swift.struct/callIsProtected","r":"Type Property","v":{"iOS":"10.0","iPadOS":"10.0","Mac Catalyst":"10.0","visionOS":"1.0","watchOS":"9.0"}},{"t":"callIsProtected","p":"documentation/CallKit/CXErrorCodeRequestTransactionError-swift.struct/callIsProtected","r":"Type Property","v":{"iOS":"10.0","iPadOS":"10.0","Mac Catalyst":"10.0","visionOS":"1.0","watchOS":"9.0"}},{"t":"callObserver","p":"documentation/CallKit/CXCallController/callObserver","r":"Instance Property","a":"Returns an observer for active calls.","v":{"iOS":"10.0","iPadOS":"10.0","Mac Catalyst":"10.0","visionOS":"1.0","watchOS":"9.0"}},{"t":"callObserver(_:callChanged:)","p":"documentation/CallKit/CXCallObserverDelegate/callObserver(_:callChanged:)","r":"Instance Method","a":"Called when a call is changed."},{"t":"callUUID","p":"documentation/CallKit/CXCallAction/callUUID","r":"Instance Property","a":"The unique identifier for the call associated with the action.","v":{"iOS":"10.0","iPadOS":"10.0","Mac Catalyst":"10.0","visionOS":"1.0","watchOS":"9.0"}},{"t":"callUUIDAlreadyExists","p":"documentation/CallKit/CXErrorCodeIncomingCallError-swift.struct/callUUIDAlreadyExists","r":"Type Property","a":"The incoming call UUID already exists.","v":{"iOS":"10.0","iPadOS":"10.0","Mac Catalyst":"10.0","visionOS":"1.0","watchOS":"9.0"}},{"t":"callUUIDAlreadyExists","p":"documentation/CallKit/CXErrorCodeRequestTransactionError-swift.struct/callUUIDAlreadyExists","r":"Type Property","a":"The requested transaction contains call actions that reference a UUID that already exists.","v":{"iOS":"10.0","iPadOS":"10.0","Mac Catalyst":"10.0","visionOS":"1.0","watchOS":"9.0"}},{"t":"callUUIDToGroupWith","p":"documentation/CallKit/CXSetGroupCallAction/callUUIDToGroupWith","r":"Instance Property","a":"The unique identifier of the call to be grouped with the call associated with the receiver.","v":{"iOS":"10.0","iPadOS":"10.0","Mac Catalyst":"10.0","visionOS":"1.0","watchOS":"9.0"}},{"t":"calls","p":"documentation/CallKit/CXCallObserver/calls","r":"Instance Property","a":"Returns the active calls of the telephony provider.","v":{"iOS":"10.0","iPadOS":"10.0","Mac Catalyst":"10.0","visionOS":"1.0","watchOS":"9.0"}},{"t":"completeRequest(completionHandler:)","p":"documentation/CallKit/CXCallDirectoryExtensionContext/completeRequest(completionHandler:)","r":"Instance Method","a":"Completes the request to the extension context."},{"t":"configuration","p":"documentation/CallKit/CXProvider/configuration","r":"Instance Property","a":"The configuration of the provider.","v":{"iOS":"10.0","iPadOS":"10.0","Mac Catalyst":"10.0","visionOS":"1.0","watchOS":"9.0"}},{"t":"contactIdentifier","p":"documentation/CallKit/CXStartCallAction/contactIdentifier","r":"Instance Property","a":"The identifier for the call recipient.","v":{"iOS":"10.0","iPadOS":"10.0","Mac Catalyst":"10.0","visionOS":"1.0","watchOS":"9.0"}},{"t":"currentlyLoading","p":"documentation/CallKit/CXErrorCodeCallDirectoryManagerError-swift.struct/currentlyLoading","r":"Type Property","a":"The call directory manager is loading the app extension.","v":{"iOS":"10.3","iPadOS":"10.3","Mac Catalyst":"10.3","visionOS":"1.0","watchOS":"3.2"}},{"t":"delegate","p":"documentation/CallKit/CXCallDirectoryExtensionContext/delegate","r":"Instance Property","a":"Sets a delegate that can handle request failures for the Call Directory extension context object.","v":{"iOS":"10.0","iPadOS":"10.0","Mac Catalyst":"10.0","visionOS":"1.0"}},{"t":"digits","p":"documentation/CallKit/CXPlayDTMFCallAction/digits","r":"Instance Property","a":"The digits tapped by the user into the in-call keypad or included in the dial string.","v":{"iOS":"10.0","iPadOS":"10.0","Mac Catalyst":"10.0","visionOS":"1.0","watchOS":"9.0"}},{"t":"duplicateEntries","p":"documentation/CallKit/CXErrorCodeCallDirectoryManagerError-swift.struct/duplicateEntries","r":"Type Property","a":"There are duplicate entries in the call directory.","v":{"iOS":"10.0","iPadOS":"10.0","Mac Catalyst":"10.0","visionOS":"1.0","watchOS":"9.0"}},{"t":"emptyTransaction","p":"documentation/CallKit/CXErrorCodeRequestTransactionError-swift.struct/emptyTransaction","r":"Type Property","a":"The requested transaction doesn\u2019t contain any actions.","v":{"iOS":"10.0","iPadOS":"10.0","Mac Catalyst":"10.0","visionOS":"1.0","watchOS":"9.0"}},{"t":"entriesOutOfOrder","p":"documentation/CallKit/CXErrorCodeCallDirectoryManagerError-swift.struct/entriesOutOfOrder","r":"Type Property","a":"The entries in the call directory are out of order.","v":{"iOS":"10.0","iPadOS":"10.0","Mac Catalyst":"10.0","visionOS":"1.0","watchOS":"9.0"}},{"t":"errorDomain","p":"documentation/CallKit/CXErrorCodeCallDirectoryManagerError-swift.struct/errorDomain","r":"Type Property","v":{"iOS":"10.0","iPadOS":"10.0","Mac Catalyst":"10.0","visionOS":"1.0","watchOS":"9.0"}},{"t":"errorDomain","p":"documentation/CallKit/CXErrorCodeIncomingCallError-swift.struct/errorDomain","r":"Type Property","v":{"iOS":"10.0","iPadOS":"10.0","Mac Catalyst":"10.0","visionOS":"1.0","watchOS":"9.0"}},{"t":"errorDomain","p":"documentation/CallKit/CXErrorCodeNotificationServiceExtensionError-swift.struct/errorDomain","r":"Type Property","v":{"iOS":"14.5","iPadOS":"14.5","Mac Catalyst":"14.5","visionOS":"1.0","watchOS":"9.0"}},{"t":"errorDomain","p":"documentation/CallKit/CXError/errorDomain","r":"Type Property","v":{"iOS":"10.0","iPadOS":"10.0","Mac Catalyst":"10.0","visionOS":"1.0","watchOS":"9.0"}},{"t":"errorDomain","p":"documentation/CallKit/CXErrorCodeRequestTransactionError-swift.struct/errorDomain","r":"Type Property","v":{"iOS":"10.0","iPadOS":"10.0","Mac Catalyst":"10.0","visionOS":"1.0","watchOS":"9.0"}},{"t":"extensionDisabled","p":"documentation/CallKit/CXErrorCodeCallDirectoryManagerError-swift.struct/extensionDisabled","r":"Type Property","a":"The call directory extension isn\u2019t in an enabled state.","v":{"iOS":"10.0","iPadOS":"10.0","Mac Catalyst":"10.0","visionOS":"1.0","watchOS":"9.0"}},{"t":"fail()","p":"documentation/CallKit/CXAction/fail()","r":"Instance Method","a":"Reports the failed execution of the action.","v":{"iOS":"10.0","iPadOS":"10.0","Mac Catalyst":"10.0","visionOS":"1.0","watchOS":"9.0"}},{"t":"filteredByBlockList","p":"documentation/CallKit/CXErrorCodeIncomingCallError-swift.struct/filteredByBlockList","r":"Type Property","a":"The system is filtering the incoming call because the user is blocking it.","v":{"iOS":"10.0","iPadOS":"10.0","Mac Catalyst":"10.0","visionOS":"1.0","watchOS":"9.0"}},{"t":"filteredByDoNotDisturb","p":"documentation/CallKit/CXErrorCodeIncomingCallError-swift.struct/filteredByDoNotDisturb","r":"Type Property","a":"The system is filtering the incoming call because Do Not Disturb is active and the incoming caller isn\u2019t a VIP.","v":{"iOS":"10.0","iPadOS":"10.0","Mac Catalyst":"10.0","visionOS":"1.0","watchOS":"9.0"}},{"t":"filteredBySensitiveParticipants","p":"documentation/CallKit/CXErrorCodeIncomingCallError-swift.struct/filteredBySensitiveParticipants","r":"Type Property","v":{"iOS":"10.0","iPadOS":"10.0","Mac Catalyst":"10.0","visionOS":"1.0","watchOS":"9.0"}},{"t":"filteredDuringRestrictedSharingMode","p":"documentation/CallKit/CXErrorCodeIncomingCallError-swift.struct/filteredDuringRestrictedSharingMode","r":"Type Property","v":{"iOS":"10.0","iPadOS":"10.0","Mac Catalyst":"10.0","visionOS":"1.0","watchOS":"9.0"}},{"t":"fulfill()","p":"documentation/CallKit/CXAction/fulfill()","r":"Instance Method","a":"Reports the successful execution of the action.","v":{"iOS":"10.0","iPadOS":"10.0","Mac Catalyst":"10.0","visionOS":"1.0","watchOS":"9.0"}},{"t":"fulfill(using:)","p":"documentation/CallKit/CXSetTranslatingCallAction/fulfill(using:)","r":"Instance Method"},{"t":"fulfill(withDateConnected:)","p":"documentation/CallKit/CXAnswerCallAction/fulfill(withDateConnected:)","r":"Instance Method","a":"Reports the successful execution of the action at the specified time."},{"t":"fulfill(withDateEnded:)","p":"documentation/CallKit/CXEndCallAction/fulfill(withDateEnded:)","r":"Instance Method","a":"Reports the successful execution of the action at the specified time."},{"t":"fulfill(withDateStarted:)","p":"documentation/CallKit/CXStartCallAction/fulfill(withDateStarted:)","r":"Instance Method","a":"Reports the successful execution of the action at the specified time."},{"t":"getEnabledStatusForExtension(withIdentifier:completionHandler:)","p":"documentation/CallKit/CXCallDirectoryManager/getEnabledStatusForExtension(withIdentifier:completionHandler:)","r":"Instance Method","a":"Asynchronously returns the enabled status of the extension with the specified identifier."},{"t":"handle","p":"documentation/CallKit/CXStartCallAction/handle","r":"Instance Property","a":"The handle of the call recipient.","v":{"iOS":"10.0","iPadOS":"10.0","Mac Catalyst":"10.0","visionOS":"1.0","watchOS":"9.0"}},{"t":"hasConnected","p":"documentation/CallKit/CXCall/hasConnected","r":"Instance Property","a":"A Boolean value that indicates whether the call has connected.","v":{"iOS":"10.0","iPadOS":"10.0","Mac Catalyst":"10.0","visionOS":"1.0","watchOS":"9.0"}},{"t":"hasEnded","p":"documentation/CallKit/CXCall/hasEnded","r":"Instance Property","a":"A Boolean value that indicates whether the call has ended.","v":{"iOS":"10.0","iPadOS":"10.0","Mac Catalyst":"10.0","visionOS":"1.0","watchOS":"9.0"}},{"t":"hasVideo","p":"documentation/CallKit/CXCallUpdate/hasVideo","r":"Instance Property","a":"A Boolean value that indicates whether the call includes video in addition to audio.","v":{"iOS":"10.0","iPadOS":"10.0","Mac Catalyst":"10.0","visionOS":"1.0","watchOS":"9.0"}},{"t":"iconTemplateImageData","p":"documentation/CallKit/CXProviderConfiguration/iconTemplateImageData","r":"Instance Property","a":"The PNG data for the icon image to be displayed for the provider.","v":{"iOS":"10.0","iPadOS":"10.0","Mac Catalyst":"10.0","macOS":"11.0","visionOS":"1.0","watchOS":"9.0"}},{"t":"includesCallsInRecents","p":"documentation/CallKit/CXProviderConfiguration/includesCallsInRecents","r":"Instance Property","a":"A Boolean value that indicates whether the provider includes a call in the system\u2019s Recents list after the call ends.","v":{"iOS":"11.0","iPadOS":"11.0","Mac Catalyst":"11.0","macOS":"11.0","visionOS":"1.0","watchOS":"9.0"}},{"t":"init()","p":"documentation/CallKit/CXCallController/init()","r":"Initializer","a":"Initializes a new call controller with a private, serial queue, which is used for calling completion blocks.","v":{"iOS":"10.0","iPadOS":"10.0","Mac Catalyst":"10.0","visionOS":"1.0","watchOS":"9.0"}},{"t":"init()","p":"documentation/CallKit/CXAction/init()","r":"Initializer","a":"Initializes a new telephony action.","v":{"iOS":"10.0","iPadOS":"10.0","Mac Catalyst":"10.0","visionOS":"1.0","watchOS":"9.0"}},{"t":"init()","p":"documentation/CallKit/CXProviderConfiguration/init()","r":"Initializer","a":"Creates the configuration of a provider object.","v":{"iOS":"14.0","iPadOS":"14.0","Mac Catalyst":"14.0","macOS":"11.0","visionOS":"1.0","watchOS":"9.0"}},{"t":"init(action:)","p":"documentation/CallKit/CXTransaction/init(action:)","r":"Initializer","a":"Initializes a new transaction with the specified action."},{"t":"init(actions:)","p":"documentation/CallKit/CXTransaction/init(actions:)","r":"Initializer","a":"Initializes a new transaction with the specified actions."},{"t":"init(call:)","p":"documentation/CallKit/CXCallAction/init(call:)","r":"Initializer","a":"Initializes a new action for a call identified by a given UUID."},{"t":"init(call:callUUIDToGroupWith:)","p":"documentation/CallKit/CXSetGroupCallAction/init(call:callUUIDToGroupWith:)","r":"Initializer","a":"Initializes a new action for a call identified by a given UUID, as well as a call to group with identified by another UUID."},{"t":"init(call:digits:type:)","p":"documentation/CallKit/CXPlayDTMFCallAction/init(call:digits:type:)","r":"Initializer","a":"Initializes a new action for a call identified by a given UUID, as well as a specified type and sequence of digits."},{"t":"init(call:handle:)","p":"documentation/CallKit/CXStartCallAction/init(call:handle:)","r":"Initializer","a":"Initializes a new action to start a call with the specified UUID to a recipient with the specified handle."},{"t":"init(call:isTranslating:localLanguage:remoteLanguage:)","p":"documentation/CallKit/CXSetTranslatingCallAction/init(call:isTranslating:localLanguage:remoteLanguage:)","r":"Initializer"},{"t":"init(call:muted:)","p":"documentation/CallKit/CXSetMutedCallAction/init(call:muted:)","r":"Initializer","a":"Initializes a new action for a call identified by a given UUID, as well as whether the call is muted."},{"t":"init(call:onHold:)","p":"documentation/CallKit/CXSetHeldCallAction/init(call:onHold:)","r":"Initializer","a":"Initializes a new action for a call identified by a given UUID, as well as whether the call is on hold."},{"t":"init(callUUID:)","p":"documentation/CallKit/CXCallAction/init(callUUID:)","r":"Initializer"},{"t":"init(callUUID:callUUIDToGroupWith:)","p":"documentation/CallKit/CXSetGroupCallAction/init(callUUID:callUUIDToGroupWith:)","r":"Initializer"},{"t":"init(callUUID:digits:type:)","p":"documentation/CallKit/CXPlayDTMFCallAction/init(callUUID:digits:type:)","r":"Initializer"},{"t":"init(callUUID:handle:)","p":"documentation/CallKit/CXStartCallAction/init(callUUID:handle:)","r":"Initializer"},{"t":"init(callUUID:isTranslating:localLanguage:remoteLanguage:)","p":"documentation/CallKit/CXSetTranslatingCallAction/init(callUUID:isTranslating:localLanguage:remoteLanguage:)","r":"Initializer"},{"t":"init(callUUID:muted:)","p":"documentation/CallKit/CXSetMutedCallAction/init(callUUID:muted:)","r":"Initializer"},{"t":"init(callUUID:onHold:)","p":"documentation/CallKit/CXSetHeldCallAction/init(callUUID:onHold:)","r":"Initializer"},{"t":"init(coder:)","p":"documentation/CallKit/CXSetHeldCallAction/init(coder:)","r":"Initializer","a":"Creates a new action to place a call on hold with data in an unarchiver."},{"t":"init(coder:)","p":"documentation/CallKit/CXHandle/init(coder:)","r":"Initializer"},{"t":"init(coder:)","p":"documentation/CallKit/CXTransaction/init(coder:)","r":"Initializer"},{"t":"init(coder:)","p":"documentation/CallKit/CXStartCallAction/init(coder:)","r":"Initializer","a":"Creates a new action to start a call with data in an unarchiver."},{"t":"init(coder:)","p":"documentation/CallKit/CXCallAction/init(coder:)","r":"Initializer","a":"Creates a new action for a call with data in an unarchiver."},{"t":"init(coder:)","p":"documentation/CallKit/CXSetTranslatingCallAction/init(coder:)","r":"Initializer","a":"Creates a new action to start or stop translating a call with the provided data."},{"t":"init(coder:)","p":"documentation/CallKit/CXSetMutedCallAction/init(coder:)","r":"Initializer","a":"Creates a new action for a call with data in an unarchiver."},{"t":"init(coder:)","p":"documentation/CallKit/CXAction/init(coder:)","r":"Initializer","a":"Creates a new telephony action with data in an unarchiver."},{"t":"init(coder:)","p":"documentation/CallKit/CXPlayDTMFCallAction/init(coder:)","r":"Initializer","a":"Creates a new action to play dual-tone multifrequency (DTMF) tones with data in an unarchiver."},{"t":"init(coder:)","p":"documentation/CallKit/CXSetGroupCallAction/init(coder:)","r":"Initializer","a":"Creates a new action to group calls with data in an unarchiver."},{"t":"init(configuration:)","p":"documentation/CallKit/CXProvider/init(configuration:)","r":"Initializer","a":"Initializes a new provider with the specified configuration."},{"t":"init(localizedName:)","p":"documentation/CallKit/CXProviderConfiguration/init(localizedName:)","r":"Initializer","a":"Initializes a configuration with the specified localized name."},{"t":"init(queue:)","p":"documentation/CallKit/CXCallController/init(queue:)","r":"Initializer","a":"Initializes a new call controller with a specified queue, which is used for calling completion blocks."},{"t":"init(rawValue:)","p":"documentation/CallKit/CXCallDirectoryManager/EnabledStatus/init(rawValue:)","r":"Initializer"},{"t":"init(rawValue:)","p":"documentation/CallKit/CXErrorCodeCallDirectoryManagerError-swift.struct/Code/init(rawValue:)","r":"Initializer"},{"t":"init(rawValue:)","p":"documentation/CallKit/CXError/Code/init(rawValue:)","r":"Initializer"},{"t":"init(rawValue:)","p":"documentation/CallKit/CXCallEndedReason/init(rawValue:)","r":"Initializer"},{"t":"init(rawValue:)","p":"documentation/CallKit/CXErrorCodeIncomingCallError-swift.struct/Code/init(rawValue:)","r":"Initializer"},{"t":"init(rawValue:)","p":"documentation/CallKit/CXHandle/HandleType/init(rawValue:)","r":"Initializer"},{"t":"init(rawValue:)","p":"documentation/CallKit/CXErrorCodeRequestTransactionError-swift.struct/Code/init(rawValue:)","r":"Initializer"},{"t":"init(rawValue:)","p":"documentation/CallKit/CXErrorCodeNotificationServiceExtensionError-swift.struct/Code/init(rawValue:)","r":"Initializer"},{"t":"init(rawValue:)","p":"documentation/CallKit/CXTranslationEngine/init(rawValue:)","r":"Initializer"},{"t":"init(rawValue:)","p":"documentation/CallKit/CXPlayDTMFCallAction/ActionType/init(rawValue:)","r":"Initializer"},{"t":"init(type:value:)","p":"documentation/CallKit/CXHandle/init(type:value:)","r":"Initializer","a":"Initializes a new handle of a given type with the specified value."},{"t":"invalidAction","p":"documentation/CallKit/CXErrorCodeRequestTransactionError-swift.struct/invalidAction","r":"Type Property","a":"The requested transaction contains an invalid action.","v":{"iOS":"10.0","iPadOS":"10.0","Mac Catalyst":"10.0","visionOS":"1.0","watchOS":"9.0"}},{"t":"invalidArgument","p":"documentation/CallKit/CXError/invalidArgument","r":"Type Property","a":"The argument is invalid.","v":{"iOS":"13.2","iPadOS":"13.2","Mac Catalyst":"13.2","visionOS":"1.0","watchOS":"9.0"}},{"t":"invalidClientProcess","p":"documentation/CallKit/CXErrorCodeNotificationServiceExtensionError-swift.struct/invalidClientProcess","r":"Type Property","a":"An error indicating that an invalid client process reported the incoming call.","v":{"iOS":"14.5","iPadOS":"14.5","Mac Catalyst":"14.5","visionOS":"1.0","watchOS":"9.0"}},{"t":"invalidate()","p":"documentation/CallKit/CXProvider/invalidate()","r":"Instance Method","a":"Invalidates the provider and completes all active calls with an error.","v":{"iOS":"10.0","iPadOS":"10.0","Mac Catalyst":"10.0","visionOS":"1.0","watchOS":"9.0"}},{"t":"isComplete","p":"documentation/CallKit/CXTransaction/isComplete","r":"Instance Property","a":"A Boolean value that indicates whether the transaction has been completed.","v":{"iOS":"10.0","iPadOS":"10.0","Mac Catalyst":"10.0","visionOS":"1.0","watchOS":"9.0"}},{"t":"isComplete","p":"documentation/CallKit/CXAction/isComplete","r":"Instance Property","a":"A Boolean value that indicates whether the action has been performed by the provider.","v":{"iOS":"10.0","iPadOS":"10.0","Mac Catalyst":"10.0","visionOS":"1.0","watchOS":"9.0"}},{"t":"isEqualToCall:","p":"documentation/CallKit/CXCall/isEqualToCall:","r":"Instance Method","a":"Returns a Boolean value that indicates whether a given call is equal to the receiver."},{"t":"isEqualToHandle:","p":"documentation/CallKit/CXHandle/isEqualToHandle:","r":"Instance Method","a":"Returns a Boolean value that indicates whether a given handle is equal to the receiver."},{"t":"isIncremental","p":"documentation/CallKit/CXCallDirectoryExtensionContext/isIncremental","r":"Instance Property","a":"A Boolean value that indicates whether the request provides data incrementally.","v":{"iOS":"11.0","iPadOS":"11.0","Mac Catalyst":"11.0","visionOS":"1.0"}},{"t":"isMuted","p":"documentation/CallKit/CXSetMutedCallAction/isMuted","r":"Instance Property","a":"A Boolean value that indicates whether the call is muted.","v":{"iOS":"10.0","iPadOS":"10.0","Mac Catalyst":"10.0","visionOS":"1.0","watchOS":"9.0"}},{"t":"isOnHold","p":"documentation/CallKit/CXSetHeldCallAction/isOnHold","r":"Instance Property","a":"A Boolean value that indicates whether the call is placed on hold.","v":{"iOS":"10.0","iPadOS":"10.0","Mac Catalyst":"10.0","visionOS":"1.0","watchOS":"9.0"}},{"t":"isOnHold","p":"documentation/CallKit/CXCall/isOnHold","r":"Instance Property","a":"A Boolean value that indicates whether the call is on hold.","v":{"iOS":"10.0","iPadOS":"10.0","Mac Catalyst":"10.0","visionOS":"1.0","watchOS":"9.0"}},{"t":"isOutgoing","p":"documentation/CallKit/CXCall/isOutgoing","r":"Instance Property","a":"A Boolean value that indicates whether the call is outgoing.","v":{"iOS":"10.0","iPadOS":"10.0","Mac Catalyst":"10.0","visionOS":"1.0","watchOS":"9.0"}},{"t":"isTranslating","p":"documentation/CallKit/CXSetTranslatingCallAction/isTranslating","r":"Instance Property","a":"A value that indicates whether translation is active for a call.","v":{"iOS":"26.0","iPadOS":"26.0","Mac Catalyst":"26.0"}},{"t":"isVideo","p":"documentation/CallKit/CXStartCallAction/isVideo","r":"Instance Property","a":"A Boolean value that indicates whether the call is a video call.","v":{"iOS":"10.0","iPadOS":"10.0","Mac Catalyst":"10.0","visionOS":"1.0","watchOS":"9.0"}},{"t":"loadingInterrupted","p":"documentation/CallKit/CXErrorCodeCallDirectoryManagerError-swift.struct/loadingInterrupted","r":"Type Property","a":"The system interrupted the call directory manager while loading the app extension.","v":{"iOS":"10.0","iPadOS":"10.0","Mac Catalyst":"10.0","visionOS":"1.0","watchOS":"9.0"}},{"t":"localLanguage","p":"documentation/CallKit/CXSetTranslatingCallAction/localLanguage","r":"Instance Property","v":{"iOS":"26.0","iPadOS":"26.0","Mac Catalyst":"26.0"}},{"t":"localizedCallerName","p":"documentation/CallKit/CXCallUpdate/localizedCallerName","r":"Instance Property","a":"The localized name of the caller.","v":{"iOS":"10.0","iPadOS":"10.0","Mac Catalyst":"10.0","visionOS":"1.0","watchOS":"9.0"}},{"t":"localizedName","p":"documentation/CallKit/CXProviderConfiguration/localizedName","r":"Instance Property","a":"The localized name of the provider.","v":{"iOS":"10.0","iPadOS":"10.0","Mac Catalyst":"10.0","macOS":"11.0","visionOS":"1.0"}},{"t":"maximumCallGroups","p":"documentation/CallKit/CXProviderConfiguration/maximumCallGroups","r":"Instance Property","a":"The maximum number of call groups.","v":{"iOS":"10.0","iPadOS":"10.0","Mac Catalyst":"10.0","macOS":"11.0","visionOS":"1.0","watchOS":"9.0"}},{"t":"maximumCallGroupsReached","p":"documentation/CallKit/CXErrorCodeRequestTransactionError-swift.struct/maximumCallGroupsReached","r":"Type Property","a":"Performing the requested transaction exceeds the maximum number of call groups for the provider.","v":{"iOS":"10.0","iPadOS":"10.0","Mac Catalyst":"10.0","visionOS":"1.0","watchOS":"9.0"}},{"t":"maximumCallsPerCallGroup","p":"documentation/CallKit/CXProviderConfiguration/maximumCallsPerCallGroup","r":"Instance Property","a":"The maximum number of calls per call group.","v":{"iOS":"10.0","iPadOS":"10.0","Mac Catalyst":"10.0","macOS":"11.0","visionOS":"1.0","watchOS":"9.0"}},{"t":"maximumEntriesExceeded","p":"documentation/CallKit/CXErrorCodeCallDirectoryManagerError-swift.struct/maximumEntriesExceeded","r":"Type Property","a":"There are too many entries in the call directory.","v":{"iOS":"10.0","iPadOS":"10.0","Mac Catalyst":"10.0","visionOS":"1.0","watchOS":"9.0"}},{"t":"missingNotificationFilteringEntitlement","p":"documentation/CallKit/CXErrorCodeNotificationServiceExtensionError-swift.struct/missingNotificationFilteringEntitlement","r":"Type Property","a":"An error indicating that the notification service extension is missing the required filtering entitlement.","v":{"iOS":"14.5","iPadOS":"14.5","Mac Catalyst":"14.5","visionOS":"1.0","watchOS":"9.0"}},{"t":"missingVoIPBackgroundMode","p":"documentation/CallKit/CXError/missingVoIPBackgroundMode","r":"Type Property","v":{"iOS":"14.5","iPadOS":"14.5","Mac Catalyst":"14.5","visionOS":"1.0","watchOS":"9.0"}},{"t":"noExtensionFound","p":"documentation/CallKit/CXErrorCodeCallDirectoryManagerError-swift.struct/noExtensionFound","r":"Type Property","a":"The call directory manager can\u2019t find a corresponding app extension.","v":{"iOS":"10.0","iPadOS":"10.0","Mac Catalyst":"10.0","visionOS":"1.0","watchOS":"9.0"}},{"t":"openSettings(completionHandler:)","p":"documentation/CallKit/CXCallDirectoryManager/openSettings(completionHandler:)","r":"Instance Method","a":"Opens the iOS Settings app and shows the Call Blocking & Identification settings."},{"t":"pendingCallActions(of:withCall:)","p":"documentation/CallKit/CXProvider/pendingCallActions(of:withCall:)","r":"Instance Method","a":"Returns all call actions in any pending transactions of the specified class for the specified call identifier that are incomplete."},{"t":"pendingTransactions","p":"documentation/CallKit/CXProvider/pendingTransactions","r":"Instance Property","a":"Incomplete transactions.","v":{"iOS":"10.0","iPadOS":"10.0","Mac Catalyst":"10.0","visionOS":"1.0","watchOS":"9.0"}},{"t":"provider(_:didActivate:)","p":"documentation/CallKit/CXProviderDelegate/provider(_:didActivate:)","r":"Instance Method","a":"Called when the provider\u2019s audio session is activated."},{"t":"provider(_:didDeactivate:)","p":"documentation/CallKit/CXProviderDelegate/provider(_:didDeactivate:)","r":"Instance Method","a":"Called when the provider\u2019s audio session is deactivated."},{"t":"provider(_:execute:)","p":"documentation/CallKit/CXProviderDelegate/provider(_:execute:)","r":"Instance Method","a":"Called when a transaction is executed by a call controller."},{"t":"provider(_:perform:)","p":"documentation/CallKit/CXProviderDelegate/provider(_:perform:)-h4in","r":"Instance Method","a":"Called when the provider performs the specified answer call action."},{"t":"provider(_:perform:)","p":"documentation/CallKit/CXProviderDelegate/provider(_:perform:)-947b1","r":"Instance Method","a":"Called when the provider performs the specified set held call action."},{"t":"provider(_:perform:)","p":"documentation/CallKit/CXProviderDelegate/provider(_:perform:)-9masw","r":"Instance Method","a":"Called when the provider performs the specified set group call action."},{"t":"provider(_:perform:)","p":"documentation/CallKit/CXProviderDelegate/provider(_:perform:)-2lem5","r":"Instance Method","a":"Called when the provider performs the specified start call action."},{"t":"provider(_:perform:)","p":"documentation/CallKit/CXProviderDelegate/provider(_:perform:)-43atg","r":"Instance Method","a":"Called when the provider performs the specified set translation action."},{"t":"provider(_:perform:)","p":"documentation/CallKit/CXProviderDelegate/provider(_:perform:)-9a0m","r":"Instance Method","a":"Called when the provider performs the specified end call action."},{"t":"provider(_:perform:)","p":"documentation/CallKit/CXProviderDelegate/provider(_:perform:)-4htxt","r":"Instance Method","a":"Called when the provider performs the specified play DTMF (dual tone multifrequency) call action."},{"t":"provider(_:perform:)","p":"documentation/CallKit/CXProviderDelegate/provider(_:perform:)-4u3yu","r":"Instance Method","a":"Called when the provider performs the specified set muted call action."},{"t":"provider(_:timedOutPerforming:)","p":"documentation/CallKit/CXProviderDelegate/provider(_:timedOutPerforming:)","r":"Instance Method","a":"Called when the provider performs the specified action times out."},{"t":"providerDidBegin(_:)","p":"documentation/CallKit/CXProviderDelegate/providerDidBegin(_:)","r":"Instance Method","a":"Called when the provider begins."},{"t":"providerDidReset(_:)","p":"documentation/CallKit/CXProviderDelegate/providerDidReset(_:)","r":"Instance Method","a":"Called when the provider is reset."},{"t":"reloadExtension(withIdentifier:completionHandler:)","p":"documentation/CallKit/CXCallDirectoryManager/reloadExtension(withIdentifier:completionHandler:)","r":"Instance Method","a":"Asynchronously reloads the extension with the specified identifier."},{"t":"remoteHandle","p":"documentation/CallKit/CXCallUpdate/remoteHandle","r":"Instance Property","a":"The handle for the remote party (for an incoming call, this is the caller; for an outgoing call, this is the callee).","v":{"iOS":"10.0","iPadOS":"10.0","Mac Catalyst":"10.0","visionOS":"1.0","watchOS":"9.0"}},{"t":"remoteLanguage","p":"documentation/CallKit/CXSetTranslatingCallAction/remoteLanguage","r":"Instance Property","v":{"iOS":"26.0","iPadOS":"26.0","Mac Catalyst":"26.0"}},{"t":"removeAllBlockingEntries()","p":"documentation/CallKit/CXCallDirectoryExtensionContext/removeAllBlockingEntries()","r":"Instance Method","a":"Removes all stored blocking entries.","v":{"iOS":"11.0","iPadOS":"11.0","Mac Catalyst":"11.0","visionOS":"1.0"}},{"t":"removeAllIdentificationEntries()","p":"documentation/CallKit/CXCallDirectoryExtensionContext/removeAllIdentificationEntries()","r":"Instance Method","a":"Removes all stored identification entries.","v":{"iOS":"11.0","iPadOS":"11.0","Mac Catalyst":"11.0","visionOS":"1.0"}},{"t":"removeBlockingEntry(withPhoneNumber:)","p":"documentation/CallKit/CXCallDirectoryExtensionContext/removeBlockingEntry(withPhoneNumber:)","r":"Instance Method","a":"Removes a blocking entry that contains the specified phone number."},{"t":"removeIdentificationEntry(withPhoneNumber:)","p":"documentation/CallKit/CXCallDirectoryExtensionContext/removeIdentificationEntry(withPhoneNumber:)","r":"Instance Method","a":"Removes an identification entry that contains the specified phone number."},{"t":"reportCall(with:endedAt:reason:)","p":"documentation/CallKit/CXProvider/reportCall(with:endedAt:reason:)","r":"Instance Method","a":"Reports to the provider that a call with the specified identifier ended at a given date for a particular reason."},{"t":"reportCall(with:updated:)","p":"documentation/CallKit/CXProvider/reportCall(with:updated:)","r":"Instance Method","a":"Reports to the provider that an active call updated its information."},{"t":"reportNewIncomingCall(with:update:completion:)","p":"documentation/CallKit/CXProvider/reportNewIncomingCall(with:update:completion:)","r":"Instance Method","a":"Reports a new incoming call with the specified unique identifier to the provider."},{"t":"reportNewIncomingVoIPPushPayload(_:completion:)","p":"documentation/CallKit/CXProvider/reportNewIncomingVoIPPushPayload(_:completion:)","r":"Type Method","a":"Reports a new incoming call after your notification service extension decrypts a VoIP call request."},{"t":"reportOutgoingCall(with:connectedAt:)","p":"documentation/CallKit/CXProvider/reportOutgoingCall(with:connectedAt:)","r":"Instance Method","a":"Reports to the provider that an outgoing call with the specified unique identifier finished connecting at a particular time."},{"t":"reportOutgoingCall(with:startedConnectingAt:)","p":"documentation/CallKit/CXProvider/reportOutgoingCall(with:startedConnectingAt:)","r":"Instance Method","a":"Reports to the provider that an outgoing call with the specified unique identifier started connecting at a particular time."},{"t":"request(_:completion:)","p":"documentation/CallKit/CXCallController/request(_:completion:)","r":"Instance Method","a":"Requests that the actions in the specified transaction be asynchronously performed by the telephony provider."},{"t":"requestFailed(for:withError:)","p":"documentation/CallKit/CXCallDirectoryExtensionContextDelegate/requestFailed(for:withError:)","r":"Instance Method","a":"Called when a Call Directory app extension request fails."},{"t":"requestTransaction(with:completion:)","p":"documentation/CallKit/CXCallController/requestTransaction(with:completion:)-ffme","r":"Instance Method","a":"Requests that the transaction that contains the specified action be asynchronously performed by the telephony provider."},{"t":"requestTransaction(with:completion:)","p":"documentation/CallKit/CXCallController/requestTransaction(with:completion:)-4o1m4","r":"Instance Method","a":"Requests that the transaction that contains the specified actions be asynchronously performed by the telephony provider."},{"t":"ringtoneSound","p":"documentation/CallKit/CXProviderConfiguration/ringtoneSound","r":"Instance Property","a":"The name of the sound resource in the app bundle to be used for the provider ringtone.","v":{"iOS":"10.0","iPadOS":"10.0","Mac Catalyst":"10.0","macOS":"11.0","visionOS":"1.0","watchOS":"9.0"}},{"t":"setDelegate(_:queue:)","p":"documentation/CallKit/CXProvider/setDelegate(_:queue:)","r":"Instance Method","a":"Sets a provider delegate, specifying an optional queue on which to execute delegate methods."},{"t":"setDelegate(_:queue:)","p":"documentation/CallKit/CXCallObserver/setDelegate(_:queue:)","r":"Instance Method","a":"Sets a call observer delegate, specifying an optional queue on which to execute delegate methods."},{"t":"sharedInstance","p":"documentation/CallKit/CXCallDirectoryManager/sharedInstance","r":"Type Property","a":"Returns the shared call directory manager instance for the app.","v":{"iOS":"10.0","iPadOS":"10.0","Mac Catalyst":"10.0","visionOS":"1.0"}},{"t":"supportedHandleTypes","p":"documentation/CallKit/CXProviderConfiguration/supportedHandleTypes-995uh","r":"Instance Property","a":"The supported handle types.","v":{"iOS":"10.0","iPadOS":"10.0","Mac Catalyst":"13.0","macOS":"11.0","visionOS":"1.0","watchOS":"9.0"}},{"t":"supportedHandleTypes","p":"documentation/CallKit/CXProviderConfiguration/supportedHandleTypes-kd6i","r":"Instance Property","a":"The supported handle types.","v":{"iOS":"10.0","iPadOS":"10.0","Mac Catalyst":"10.0","visionOS":"1.0","watchOS":"9.0"}},{"t":"supportsAudioTranslation","p":"documentation/CallKit/CXProviderConfiguration/supportsAudioTranslation","r":"Instance Property","v":{"iOS":"26.0","iPadOS":"26.0","Mac Catalyst":"26.0","macOS":"11.0","visionOS":"26.0","watchOS":"26.0"}},{"t":"supportsDTMF","p":"documentation/CallKit/CXCallUpdate/supportsDTMF","r":"Instance Property","a":"A Boolean value that indicates whether the call can send DTMF (dual tone multifrequency) tones via hard pause digits or in-call keypad entries.","v":{"iOS":"10.0","iPadOS":"10.0","Mac Catalyst":"10.0","visionOS":"1.0","watchOS":"9.0"}},{"t":"supportsGrouping","p":"documentation/CallKit/CXCallUpdate/supportsGrouping","r":"Instance Property","a":"A Boolean value that indicates whether the call can be grouped with other calls.","v":{"iOS":"10.0","iPadOS":"10.0","Mac Catalyst":"10.0","visionOS":"1.0","watchOS":"9.0"}},{"t":"supportsHolding","p":"documentation/CallKit/CXCallUpdate/supportsHolding","r":"Instance Property","a":"A Boolean value that indicates whether the call can be placed on hold or removed from hold.","v":{"iOS":"10.0","iPadOS":"10.0","Mac Catalyst":"10.0","visionOS":"1.0","watchOS":"9.0"}},{"t":"supportsUngrouping","p":"documentation/CallKit/CXCallUpdate/supportsUngrouping","r":"Instance Property","a":"A Boolean value that indicates whether the call can be ungrouped from other calls.","v":{"iOS":"10.0","iPadOS":"10.0","Mac Catalyst":"10.0","visionOS":"1.0","watchOS":"9.0"}},{"t":"supportsVideo","p":"documentation/CallKit/CXProviderConfiguration/supportsVideo","r":"Instance Property","a":"A Boolean value that indicates whether the provider supports video in addition to audio.","v":{"iOS":"10.0","iPadOS":"10.0","Mac Catalyst":"10.0","macOS":"11.0","visionOS":"1.0","watchOS":"9.0"}},{"t":"timeoutDate","p":"documentation/CallKit/CXAction/timeoutDate","r":"Instance Property","a":"The time after which the action cannot be completed.","v":{"iOS":"10.0","iPadOS":"10.0","Mac Catalyst":"10.0","visionOS":"1.0","watchOS":"9.0"}},{"t":"type","p":"documentation/CallKit/CXHandle/type","r":"Instance Property","a":"The type of the handle.","v":{"iOS":"10.0","iPadOS":"10.0","Mac Catalyst":"10.0","visionOS":"1.0","watchOS":"9.0"}},{"t":"type","p":"documentation/CallKit/CXPlayDTMFCallAction/type","r":"Instance Property","a":"The type of the call action.","v":{"iOS":"10.0","iPadOS":"10.0","Mac Catalyst":"10.0","visionOS":"1.0","watchOS":"9.0"}},{"t":"unentitled","p":"documentation/CallKit/CXErrorCodeIncomingCallError-swift.struct/unentitled","r":"Type Property","a":"The app doesn\u2019t have the entitlement to receive incoming calls.","v":{"iOS":"10.0","iPadOS":"10.0","Mac Catalyst":"10.0","visionOS":"1.0","watchOS":"9.0"}},{"t":"unentitled","p":"documentation/CallKit/CXError/unentitled","r":"Type Property","a":"The caller doesn\u2019t have the correct entitlement.","v":{"iOS":"13.2","iPadOS":"13.2","Mac Catalyst":"13.2","visionOS":"1.0","watchOS":"9.0"}},{"t":"unentitled","p":"documentation/CallKit/CXErrorCodeRequestTransactionError-swift.struct/unentitled","r":"Type Property","a":"The app doesn\u2019t have the entitlement to perform the actions in the requested transaction.","v":{"iOS":"10.0","iPadOS":"10.0","Mac Catalyst":"10.0","visionOS":"1.0","watchOS":"9.0"}},{"t":"unexpectedIncrementalRemoval","p":"documentation/CallKit/CXErrorCodeCallDirectoryManagerError-swift.struct/unexpectedIncrementalRemoval","r":"Type Property","a":"A request occurred before confirming incremental loading.","v":{"iOS":"11.0","iPadOS":"11.0","Mac Catalyst":"11.0","visionOS":"1.0","watchOS":"4.0"}},{"t":"unknown","p":"documentation/CallKit/CXErrorCodeCallDirectoryManagerError-swift.struct/unknown","r":"Type Property","a":"An unknown error occurred.","v":{"iOS":"10.0","iPadOS":"10.0","Mac Catalyst":"10.0","visionOS":"1.0","watchOS":"9.0"}},{"t":"unknown","p":"documentation/CallKit/CXErrorCodeIncomingCallError-swift.struct/unknown","r":"Type Property","a":"An unknown error occurred.","v":{"iOS":"10.0","iPadOS":"10.0","Mac Catalyst":"10.0","visionOS":"1.0","watchOS":"9.0"}},{"t":"unknown","p":"documentation/CallKit/CXErrorCodeNotificationServiceExtensionError-swift.struct/unknown","r":"Type Property","a":"An error that occurs when there is an unknown problem.","v":{"iOS":"14.5","iPadOS":"14.5","Mac Catalyst":"14.5","visionOS":"1.0","watchOS":"9.0"}},{"t":"unknown","p":"documentation/CallKit/CXErrorCodeRequestTransactionError-swift.struct/unknown","r":"Type Property","a":"An unknown error occurred.","v":{"iOS":"10.0","iPadOS":"10.0","Mac Catalyst":"10.0","visionOS":"1.0","watchOS":"9.0"}},{"t":"unknownCallProvider","p":"documentation/CallKit/CXErrorCodeRequestTransactionError-swift.struct/unknownCallProvider","r":"Type Property","a":"The controller can\u2019t find a call provider to perform the actions in the requested transaction.","v":{"iOS":"10.0","iPadOS":"10.0","Mac Catalyst":"10.0","visionOS":"1.0","watchOS":"9.0"}},{"t":"unknownCallUUID","p":"documentation/CallKit/CXErrorCodeRequestTransactionError-swift.struct/unknownCallUUID","r":"Type Property","a":"The requested transaction contains call actions that reference an unknown UUID.","v":{"iOS":"10.0","iPadOS":"10.0","Mac Catalyst":"10.0","visionOS":"1.0","watchOS":"9.0"}},{"t":"unknownError","p":"documentation/CallKit/CXError/unknownError","r":"Type Property","a":"An unknown error occurred.","v":{"iOS":"10.0","iPadOS":"10.0","Mac Catalyst":"10.0","visionOS":"1.0","watchOS":"9.0"}},{"t":"uuid","p":"documentation/CallKit/CXCall/uuid","r":"Instance Property","a":"The unique identifier for the call.","v":{"iOS":"10.0","iPadOS":"10.0","Mac Catalyst":"10.0","visionOS":"1.0","watchOS":"9.0"}},{"t":"uuid","p":"documentation/CallKit/CXTransaction/uuid","r":"Instance Property","a":"The unique identifier of the transaction.","v":{"iOS":"10.0","iPadOS":"10.0","Mac Catalyst":"10.0","visionOS":"1.0","watchOS":"9.0"}},{"t":"uuid","p":"documentation/CallKit/CXAction/uuid","r":"Instance Property","a":"The unique identifier for the action.","v":{"iOS":"10.0","iPadOS":"10.0","Mac Catalyst":"10.0","visionOS":"1.0","watchOS":"9.0"}},{"t":"value","p":"documentation/CallKit/CXHandle/value","r":"Instance Property","a":"The value of the handle.","v":{"iOS":"10.0","iPadOS":"10.0","Mac Catalyst":"10.0","visionOS":"1.0","watchOS":"9.0"}}]