[{"t":"CodeDirectoryHash","p":"documentation/LightweightCodeRequirements/CodeDirectoryHash","r":"Structure","a":"A constraint that matches the hash of a code directory of a code file or of a running or launching process.","v":{"iOS":"17.4","iPadOS":"17.4","Mac Catalyst":"17.4","macOS":"14.4","tvOS":"17.4","visionOS":"1.1","watchOS":"10.4"}},{"t":"CodeDirectoryHash.DataType","p":"documentation/LightweightCodeRequirements/CodeDirectoryHash/DataType","r":"Type Alias","a":"The basic input data type for this constraint: Data","v":{"iOS":"17.4","iPadOS":"17.4","Mac Catalyst":"17.4","macOS":"14.4","tvOS":"17.4","visionOS":"1.1","watchOS":"10.4"}},{"t":"CodeDirectoryHash.OutType","p":"documentation/LightweightCodeRequirements/CodeDirectoryHash/OutType","r":"Type Alias","a":"The type of this constraint: [CodeDirectoryHash](/documentation/lightweightcoderequirements/codedirectoryhash)","v":{"iOS":"17.4","iPadOS":"17.4","Mac Catalyst":"17.4","macOS":"14.4","tvOS":"17.4","visionOS":"1.1","watchOS":"10.4"}},{"t":"ConstraintError","p":"documentation/LightweightCodeRequirements/ConstraintError","r":"Enumeration","a":"Error types that can be thrown from lightweight code requirement routines.","v":{"iOS":"17.4","iPadOS":"17.4","Mac Catalyst":"17.4","macOS":"14.4","tvOS":"17.4","visionOS":"1.1","watchOS":"10.4"}},{"t":"ConstraintError.duplicateKey","p":"documentation/LightweightCodeRequirements/ConstraintError/duplicateKey","r":"Case","a":"Two constraints of the same type were found in the same logical group.","v":{"iOS":"17.4","iPadOS":"17.4","Mac Catalyst":"17.4","macOS":"14.4","tvOS":"17.4","visionOS":"1.1","watchOS":"10.4"}},{"t":"ConstraintError.malformedConstraint","p":"documentation/LightweightCodeRequirements/ConstraintError/malformedConstraint","r":"Case","a":"An unexpected type was found when trying to encode or decode a constraint.","v":{"iOS":"17.4","iPadOS":"17.4","Mac Catalyst":"17.4","macOS":"14.4","tvOS":"17.4","visionOS":"1.1","watchOS":"10.4"}},{"t":"ConstraintError.taskIsNoLongerValid","p":"documentation/LightweightCodeRequirements/ConstraintError/taskIsNoLongerValid","r":"Case","a":"A SecTask operation failed because the task is no longer valid","v":{"iOS":"17.4","iPadOS":"17.4","Mac Catalyst":"17.4","macOS":"14.4","tvOS":"17.4","visionOS":"1.1","watchOS":"10.4"}},{"t":"ConstraintError.unsupportedConstraintForRequirementType","p":"documentation/LightweightCodeRequirements/ConstraintError/unsupportedConstraintForRequirementType","r":"Case","a":"Converting one code requirement type to another failed because the original requirement included a constraint that is not supported by the target requirement type.","v":{"iOS":"17.4","iPadOS":"17.4","Mac Catalyst":"17.4","macOS":"14.4","tvOS":"17.4","visionOS":"1.1","watchOS":"10.4"}},{"t":"EntitlementsQuery","p":"documentation/LightweightCodeRequirements/EntitlementsQuery","r":"Class","a":"A constraint that tests values in the entitlements dictionary associated with a process or code file.","v":{"iOS":"17.4","iPadOS":"17.4","Mac Catalyst":"17.4","macOS":"14.4","tvOS":"17.4","visionOS":"1.1","watchOS":"10.4"}},{"t":"EntitlementsQuery.DataType","p":"documentation/LightweightCodeRequirements/EntitlementsQuery/DataType","r":"Enumeration","a":"The types of elements allowed in entitlements dictionaries.","v":{"iOS":"17.4","iPadOS":"17.4","Mac Catalyst":"17.4","macOS":"14.4","tvOS":"17.4","visionOS":"1.1","watchOS":"10.4"}},{"t":"EntitlementsQuery.DataType.array","p":"documentation/LightweightCodeRequirements/EntitlementsQuery/DataType/array","r":"Case","v":{"iOS":"17.4","iPadOS":"17.4","Mac Catalyst":"17.4","macOS":"14.4","tvOS":"17.4","visionOS":"1.1","watchOS":"10.4"}},{"t":"EntitlementsQuery.DataType.boolean","p":"documentation/LightweightCodeRequirements/EntitlementsQuery/DataType/boolean","r":"Case","v":{"iOS":"17.4","iPadOS":"17.4","Mac Catalyst":"17.4","macOS":"14.4","tvOS":"17.4","visionOS":"1.1","watchOS":"10.4"}},{"t":"EntitlementsQuery.DataType.dictionary","p":"documentation/LightweightCodeRequirements/EntitlementsQuery/DataType/dictionary","r":"Case","v":{"iOS":"17.4","iPadOS":"17.4","Mac Catalyst":"17.4","macOS":"14.4","tvOS":"17.4","visionOS":"1.1","watchOS":"10.4"}},{"t":"EntitlementsQuery.DataType.integer","p":"documentation/LightweightCodeRequirements/EntitlementsQuery/DataType/integer","r":"Case","v":{"iOS":"17.4","iPadOS":"17.4","Mac Catalyst":"17.4","macOS":"14.4","tvOS":"17.4","visionOS":"1.1","watchOS":"10.4"}},{"t":"EntitlementsQuery.DataType.string","p":"documentation/LightweightCodeRequirements/EntitlementsQuery/DataType/string","r":"Case","v":{"iOS":"17.4","iPadOS":"17.4","Mac Catalyst":"17.4","macOS":"14.4","tvOS":"17.4","visionOS":"1.1","watchOS":"10.4"}},{"t":"InfoPlistHash","p":"documentation/LightweightCodeRequirements/InfoPlistHash","r":"Structure","a":"A constraint that tests the specified hash against the Information property list hash stored in the code signature of the process or code file.","v":{"iOS":"17.4","iPadOS":"17.4","Mac Catalyst":"17.4","macOS":"14.4","tvOS":"17.4","visionOS":"1.1","watchOS":"10.4"}},{"t":"InfoPlistHash.DataType","p":"documentation/LightweightCodeRequirements/InfoPlistHash/DataType","r":"Type Alias","v":{"iOS":"17.4","iPadOS":"17.4","Mac Catalyst":"17.4","macOS":"14.4","tvOS":"17.4","visionOS":"1.1","watchOS":"10.4"}},{"t":"InfoPlistHash.OutType","p":"documentation/LightweightCodeRequirements/InfoPlistHash/OutType","r":"Type Alias","a":"The type of this constraint: [InfoPlistHash](/documentation/lightweightcoderequirements/infoplisthash).","v":{"iOS":"17.4","iPadOS":"17.4","Mac Catalyst":"17.4","macOS":"14.4","tvOS":"17.4","visionOS":"1.1","watchOS":"10.4"}},{"t":"IsInitProcess","p":"documentation/LightweightCodeRequirements/IsInitProcess","r":"Structure","a":"A constraint that tests whether a process is the operating system\u2019s initial process.","v":{"iOS":"17.4","iPadOS":"17.4","Mac Catalyst":"17.4","macOS":"14.4","tvOS":"17.4","visionOS":"1.1","watchOS":"10.4"}},{"t":"IsMainBinary","p":"documentation/LightweightCodeRequirements/IsMainBinary","r":"Structure","a":"A constraint that tests whether a code file is a main binary.","v":{"iOS":"17.4","iPadOS":"17.4","Mac Catalyst":"17.4","macOS":"14.4","tvOS":"17.4","visionOS":"1.1","watchOS":"10.4"}},{"t":"IsSIPProtected","p":"documentation/LightweightCodeRequirements/IsSIPProtected","r":"Structure","a":"A constraint that tests whether a code file or process is on a volume protected by System Integrity Protection (SIP).","v":{"iOS":"17.4","iPadOS":"17.4","Mac Catalyst":"17.4","macOS":"14.4","tvOS":"17.4","visionOS":"1.1","watchOS":"10.4"}},{"t":"LaunchCodeRequirement","p":"documentation/LightweightCodeRequirements/LaunchCodeRequirement","r":"Structure","a":"A lightweight code requirement that you use to evaluate the executable for a launching process.","v":{"iOS":"17.4","iPadOS":"17.4","Mac Catalyst":"17.4","macOS":"14.4","tvOS":"17.4","visionOS":"1.1","watchOS":"10.4"}},{"t":"LaunchConstraint","p":"documentation/LightweightCodeRequirements/LaunchConstraint","r":"Protocol","a":"A protocol to which a lightweight code requirement constraint conforms if you can use it in launch code requirements.","v":{"iOS":"17.4","iPadOS":"17.4","Mac Catalyst":"17.4","macOS":"14.4","tvOS":"17.4","visionOS":"1.1","watchOS":"10.4"}},{"t":"LaunchConstraintBuilder","p":"documentation/LightweightCodeRequirements/LaunchConstraintBuilder","r":"Structure","a":"A custom parameter attribute that constructs launch constraints from closures.","v":{"iOS":"17.4","iPadOS":"17.4","Mac Catalyst":"17.4","macOS":"14.4","tvOS":"17.4","visionOS":"1.1","watchOS":"10.4"}},{"t":"LightweightCodeRequirements","p":"documentation/LightweightCodeRequirements","r":"Framework","a":"Test the identity of executable code on disk and in running processes.","v":{"iOS":"17.4","iPadOS":"17.4","Mac Catalyst":"17.4","macOS":"14.4"}},{"t":"OnDiskCodeRequirement","p":"documentation/LightweightCodeRequirements/OnDiskCodeRequirement","r":"Structure","a":"A lightweight code requirement that you use to evaluate a code file on disk.","v":{"iOS":"17.4","iPadOS":"17.4","Mac Catalyst":"17.4","macOS":"14.4","tvOS":"17.4","visionOS":"1.1","watchOS":"10.4"}},{"t":"OnDiskCodeSigningFlags","p":"documentation/LightweightCodeRequirements/OnDiskCodeSigningFlags","r":"Structure","a":"A constraint that tests the code-signing flags of a code file on disk.","v":{"iOS":"17.4","iPadOS":"17.4","Mac Catalyst":"17.4","macOS":"14.4","tvOS":"17.4","visionOS":"1.1","watchOS":"10.4"}},{"t":"OnDiskCodeSigningFlags.DataType","p":"documentation/LightweightCodeRequirements/OnDiskCodeSigningFlags/DataType","r":"Type Alias","a":"The basic input data type for this constraint: `OnDiskCodeSigningFlags.ValueSet`","v":{"iOS":"17.4","iPadOS":"17.4","Mac Catalyst":"17.4","macOS":"14.4","tvOS":"17.4","visionOS":"1.1","watchOS":"10.4"}},{"t":"OnDiskCodeSigningFlags.OutType","p":"documentation/LightweightCodeRequirements/OnDiskCodeSigningFlags/OutType","r":"Type Alias","a":"The type of this constraint: [OnDiskCodeSigningFlags](/documentation/lightweightcoderequirements/ondiskcodesigningflags)","v":{"iOS":"17.4","iPadOS":"17.4","Mac Catalyst":"17.4","macOS":"14.4","tvOS":"17.4","visionOS":"1.1","watchOS":"10.4"}},{"t":"OnDiskCodeSigningFlags.ValueSet","p":"documentation/LightweightCodeRequirements/OnDiskCodeSigningFlags/ValueSet","r":"Structure","a":"Code signing flags that can be set on code on disk.","v":{"iOS":"17.4","iPadOS":"17.4","Mac Catalyst":"17.4","macOS":"14.4","tvOS":"17.4","visionOS":"1.1","watchOS":"10.4"}},{"t":"OnDiskConstraint","p":"documentation/LightweightCodeRequirements/OnDiskConstraint","r":"Protocol","a":"A protocol to which a lightweight code requirement constraint conforms if you can use it in on-disk code requirements.","v":{"iOS":"17.4","iPadOS":"17.4","Mac Catalyst":"17.4","macOS":"14.4","tvOS":"17.4","visionOS":"1.1","watchOS":"10.4"}},{"t":"OnDiskConstraintBuilder","p":"documentation/LightweightCodeRequirements/OnDiskConstraintBuilder","r":"Structure","a":"A custom parameter attribute that constructs on-disk constraints from closures.","v":{"iOS":"17.4","iPadOS":"17.4","Mac Catalyst":"17.4","macOS":"14.4","tvOS":"17.4","visionOS":"1.1","watchOS":"10.4"}},{"t":"PlatformType","p":"documentation/LightweightCodeRequirements/PlatformType","r":"Structure","a":"A constraint that tests whether a code file or running process targets a given platform.","v":{"iOS":"17.4","iPadOS":"17.4","Mac Catalyst":"17.4","macOS":"14.4","tvOS":"17.4","visionOS":"1.1","watchOS":"10.4"}},{"t":"PlatformType.DataType","p":"documentation/LightweightCodeRequirements/PlatformType/DataType","r":"Type Alias","a":"The basic input data type of this constraint: `PlatformType.Value`..","v":{"iOS":"17.4","iPadOS":"17.4","Mac Catalyst":"17.4","macOS":"14.4","tvOS":"17.4","visionOS":"1.1","watchOS":"10.4"}},{"t":"PlatformType.OutType","p":"documentation/LightweightCodeRequirements/PlatformType/OutType","r":"Type Alias","a":"The type of this constraint: [PlatformType](/documentation/lightweightcoderequirements/platformtype)","v":{"iOS":"17.4","iPadOS":"17.4","Mac Catalyst":"17.4","macOS":"14.4","tvOS":"17.4","visionOS":"1.1","watchOS":"10.4"}},{"t":"PlatformType.Value","p":"documentation/LightweightCodeRequirements/PlatformType/Value","r":"Structure","a":"Supported Platform Types for a process","v":{"iOS":"17.4","iPadOS":"17.4","Mac Catalyst":"17.4","macOS":"14.4","tvOS":"17.4","visionOS":"1.1","watchOS":"10.4"}},{"t":"ProcessCodeRequirement","p":"documentation/LightweightCodeRequirements/ProcessCodeRequirement","r":"Structure","a":"A lightweight code requirement that you use to evaluate a running process.","v":{"iOS":"17.4","iPadOS":"17.4","Mac Catalyst":"17.4","macOS":"14.4","tvOS":"17.4","visionOS":"1.1","watchOS":"10.4"}},{"t":"ProcessCodeSigningFlags","p":"documentation/LightweightCodeRequirements/ProcessCodeSigningFlags","r":"Structure","a":"A constraint that matches the current code-signing flags of a process.","v":{"iOS":"17.4","iPadOS":"17.4","Mac Catalyst":"17.4","macOS":"14.4","tvOS":"17.4","visionOS":"1.1","watchOS":"10.4"}},{"t":"ProcessCodeSigningFlags.DataType","p":"documentation/LightweightCodeRequirements/ProcessCodeSigningFlags/DataType","r":"Type Alias","a":"The basic input data type for this constraint: `ProcessCodeSigningFlags.ValueSet`","v":{"iOS":"17.4","iPadOS":"17.4","Mac Catalyst":"17.4","macOS":"14.4","tvOS":"17.4","visionOS":"1.1","watchOS":"10.4"}},{"t":"ProcessCodeSigningFlags.OutType","p":"documentation/LightweightCodeRequirements/ProcessCodeSigningFlags/OutType","r":"Type Alias","a":"The type of this constraint: [ProcessCodeSigningFlags](/documentation/lightweightcoderequirements/processcodesigningflags)","v":{"iOS":"17.4","iPadOS":"17.4","Mac Catalyst":"17.4","macOS":"14.4","tvOS":"17.4","visionOS":"1.1","watchOS":"10.4"}},{"t":"ProcessCodeSigningFlags.ValueSet","p":"documentation/LightweightCodeRequirements/ProcessCodeSigningFlags/ValueSet","r":"Structure","a":"Code signing flags that can be set on a process","v":{"iOS":"17.4","iPadOS":"17.4","Mac Catalyst":"17.4","macOS":"14.4","tvOS":"17.4","visionOS":"1.1","watchOS":"10.4"}},{"t":"ProcessConstraint","p":"documentation/LightweightCodeRequirements/ProcessConstraint","r":"Protocol","a":"A protocol to which a lightweight code requirement constraint conforms if you can use it in process code requirements.","v":{"iOS":"17.4","iPadOS":"17.4","Mac Catalyst":"17.4","macOS":"14.4","tvOS":"17.4","visionOS":"1.1","watchOS":"10.4"}},{"t":"ProcessConstraintBuilder","p":"documentation/LightweightCodeRequirements/ProcessConstraintBuilder","r":"Structure","a":"A custom parameter attribute that constructs process constraints from closures.","v":{"iOS":"17.4","iPadOS":"17.4","Mac Catalyst":"17.4","macOS":"14.4","tvOS":"17.4","visionOS":"1.1","watchOS":"10.4"}},{"t":"SecCodeCheckValidityWithOnDiskRequirement(code:flags:requirement:)","p":"documentation/LightweightCodeRequirements/SecCodeCheckValidityWithOnDiskRequirement(code:flags:requirement:)","r":"Function","a":"Checks whether code on disk satisfies a lightweight code requirement."},{"t":"SecCodeCheckValidityWithProcessRequirement(code:flags:requirement:)","p":"documentation/LightweightCodeRequirements/SecCodeCheckValidityWithProcessRequirement(code:flags:requirement:)","r":"Function","a":"Checks whether the code associated with a running process satisfies a lightweight code requirement."},{"t":"SecStaticCodeCheckValidityWithOnDiskRequirement(code:flags:requirement:)","p":"documentation/LightweightCodeRequirements/SecStaticCodeCheckValidityWithOnDiskRequirement(code:flags:requirement:)","r":"Function","a":"Checks whether static code on disk satisfies a lightweight code requirement."},{"t":"SecTaskValidateForRequirement(task:requirement:)","p":"documentation/LightweightCodeRequirements/SecTaskValidateForRequirement(task:requirement:)","r":"Function","a":"Tests whether a task\u2019s executable satisfies a lightweight code requirement."},{"t":"SigningIdentifier","p":"documentation/LightweightCodeRequirements/SigningIdentifier","r":"Structure","a":"A constraint that tests whether the provided signing identifier matches the signature attached to the code.","v":{"iOS":"17.4","iPadOS":"17.4","Mac Catalyst":"17.4","macOS":"14.4","tvOS":"17.4","visionOS":"1.1","watchOS":"10.4"}},{"t":"SigningIdentifier.DataType","p":"documentation/LightweightCodeRequirements/SigningIdentifier/DataType","r":"Type Alias","a":"The basic input data type for this constraint: String.","v":{"iOS":"17.4","iPadOS":"17.4","Mac Catalyst":"17.4","macOS":"14.4","tvOS":"17.4","visionOS":"1.1","watchOS":"10.4"}},{"t":"SigningIdentifier.OutType","p":"documentation/LightweightCodeRequirements/SigningIdentifier/OutType","r":"Type Alias","a":"The type of this constraint: [SigningIdentifier](/documentation/lightweightcoderequirements/signingidentifier).","v":{"iOS":"17.4","iPadOS":"17.4","Mac Catalyst":"17.4","macOS":"14.4","tvOS":"17.4","visionOS":"1.1","watchOS":"10.4"}},{"t":"TeamIdentifier","p":"documentation/LightweightCodeRequirements/TeamIdentifier","r":"Structure","a":"A constraint that tests whether the provided team identifier matches the team identified in the code signature.","v":{"iOS":"17.4","iPadOS":"17.4","Mac Catalyst":"17.4","macOS":"14.4","tvOS":"17.4","visionOS":"1.1","watchOS":"10.4"}},{"t":"TeamIdentifier.DataType","p":"documentation/LightweightCodeRequirements/TeamIdentifier/DataType","r":"Type Alias","a":"The basic input data type for this constraint: String.","v":{"iOS":"17.4","iPadOS":"17.4","Mac Catalyst":"17.4","macOS":"14.4","tvOS":"17.4","visionOS":"1.1","watchOS":"10.4"}},{"t":"TeamIdentifier.OutType","p":"documentation/LightweightCodeRequirements/TeamIdentifier/OutType","r":"Type Alias","a":"The type of this constraint: [TeamIdentifier](/documentation/lightweightcoderequirements/teamidentifier).","v":{"iOS":"17.4","iPadOS":"17.4","Mac Catalyst":"17.4","macOS":"14.4","tvOS":"17.4","visionOS":"1.1","watchOS":"10.4"}},{"t":"TeamIdentifierMatchesCurrentProcess","p":"documentation/LightweightCodeRequirements/TeamIdentifierMatchesCurrentProcess","r":"Structure","a":"A constraint that matches if a process has the same team identifier as the calling process.","v":{"iOS":"18.0","iPadOS":"18.0","Mac Catalyst":"18.0","macOS":"15.0","tvOS":"18.0","visionOS":"2.0","watchOS":"11.0"}},{"t":"ValidationCategory","p":"documentation/LightweightCodeRequirements/ValidationCategory","r":"Structure","a":"A constraint that tests whether a code file or running process is signed in a way that conforms to the specified validation category.","v":{"iOS":"17.4","iPadOS":"17.4","Mac Catalyst":"17.4","macOS":"14.4","tvOS":"17.4","visionOS":"1.1","watchOS":"10.4"}},{"t":"ValidationCategory.DataType","p":"documentation/LightweightCodeRequirements/ValidationCategory/DataType","r":"Type Alias","a":"The basic input data type for this constraint: `ValidationCategoryType`.","v":{"iOS":"17.4","iPadOS":"17.4","Mac Catalyst":"17.4","macOS":"14.4","tvOS":"17.4","visionOS":"1.1","watchOS":"10.4"}},{"t":"ValidationCategory.OutType","p":"documentation/LightweightCodeRequirements/ValidationCategory/OutType","r":"Type Alias","a":"The type of this constraint: [ValidationCategory](/documentation/lightweightcoderequirements/validationcategory).","v":{"iOS":"17.4","iPadOS":"17.4","Mac Catalyst":"17.4","macOS":"14.4","tvOS":"17.4","visionOS":"1.1","watchOS":"10.4"}},{"t":"ValidationCategory.Value","p":"documentation/LightweightCodeRequirements/ValidationCategory/Value","r":"Structure","a":"Supported Validation categories for signatures","v":{"iOS":"17.4","iPadOS":"17.4","Mac Catalyst":"17.4","macOS":"14.4","tvOS":"17.4","visionOS":"1.1","watchOS":"10.4"}},{"t":"ValidationResult","p":"documentation/LightweightCodeRequirements/ValidationResult","r":"Structure","a":"A structure that represents the result of testing a lightweight code requirement.","v":{"Mac Catalyst":"17.4","macOS":"14.4"}},{"t":"allOf(requirement:)","p":"documentation/LightweightCodeRequirements/allOf(requirement:)-2ocwl","r":"Function","a":"Creates a constraint that requires code on disk to satisfy all of the provided constraints."},{"t":"allOf(requirement:)","p":"documentation/LightweightCodeRequirements/allOf(requirement:)-4gf5f","r":"Function","a":"Creates a constraint that requires a launching process\u2019s executable to satisfy all of the provided constraints."},{"t":"allOf(requirement:)","p":"documentation/LightweightCodeRequirements/OnDiskCodeRequirement/allOf(requirement:)","r":"Type Method","a":"Create a [OnDiskCodeRequirement](/documentation/lightweightcoderequirements/ondiskcoderequirement) that requires matching all of the provided constraints."},{"t":"allOf(requirement:)","p":"documentation/LightweightCodeRequirements/allOf(requirement:)-4k3ay","r":"Function","a":"Creates a constraint that requires a running process\u2019s executable to satisfy all of the provided constraints."},{"t":"allOf(requirement:)","p":"documentation/LightweightCodeRequirements/LaunchCodeRequirement/allOf(requirement:)","r":"Type Method","a":"Create a [LaunchCodeRequirement](/documentation/lightweightcoderequirements/launchcoderequirement) that requires matching all of the provided constraints."},{"t":"allOf(requirement:)","p":"documentation/LightweightCodeRequirements/ProcessCodeRequirement/allOf(requirement:)","r":"Type Method","a":"Create a [ProcessCodeRequirement](/documentation/lightweightcoderequirements/processcoderequirement) that requires matching all of the provided constraints."},{"t":"anyOf(requirement:)","p":"documentation/LightweightCodeRequirements/OnDiskCodeRequirement/anyOf(requirement:)","r":"Type Method","a":"Create a [OnDiskCodeRequirement](/documentation/lightweightcoderequirements/ondiskcoderequirement) that requires matching any of the provided constraints."},{"t":"anyOf(requirement:)","p":"documentation/LightweightCodeRequirements/anyOf(requirement:)-vwhn","r":"Function","a":"Creates a constraint that requires a running process\u2019s executable to satisfy any of the provided constraints."},{"t":"anyOf(requirement:)","p":"documentation/LightweightCodeRequirements/anyOf(requirement:)-6nicx","r":"Function","a":"Creates a constraint that requires a launching process\u2019s executable to satisfy any of the provided constraints."},{"t":"anyOf(requirement:)","p":"documentation/LightweightCodeRequirements/anyOf(requirement:)-71pff","r":"Function","a":"Creates a constraint that requires code on disk to satisfy any of the provided constraints."},{"t":"anyOf(requirement:)","p":"documentation/LightweightCodeRequirements/LaunchCodeRequirement/anyOf(requirement:)","r":"Type Method","a":"Create a [LaunchCodeRequirement](/documentation/lightweightcoderequirements/launchcoderequirement) that requires matching any of the provided constraints."},{"t":"anyOf(requirement:)","p":"documentation/LightweightCodeRequirements/ProcessCodeRequirement/anyOf(requirement:)","r":"Type Method","a":"Create a [ProcessCodeRequirement](/documentation/lightweightcoderequirements/processcoderequirement) that requires matching any of the provided constraints."},{"t":"appStore","p":"documentation/LightweightCodeRequirements/ValidationCategory/Value/appStore","r":"Type Property","a":"Indicates that the code is signed by Apple\u2019s App Store","v":{"iOS":"17.4","iPadOS":"17.4","Mac Catalyst":"17.4","macOS":"14.4","tvOS":"17.4","visionOS":"1.1","watchOS":"10.4"}},{"t":"buildBlock(_:)","p":"documentation/LightweightCodeRequirements/ProcessConstraintBuilder/buildBlock(_:)","r":"Type Method","a":"Builds flat array from a variadic set of arrays"},{"t":"buildBlock(_:)","p":"documentation/LightweightCodeRequirements/LaunchConstraintBuilder/buildBlock(_:)","r":"Type Method","a":"Builds flat array from a variadic set of arrays"},{"t":"buildBlock(_:)","p":"documentation/LightweightCodeRequirements/OnDiskConstraintBuilder/buildBlock(_:)","r":"Type Method","a":"Builds flat array from a variadic set of arrays"},{"t":"buildEither(first:)","p":"documentation/LightweightCodeRequirements/ProcessConstraintBuilder/buildEither(first:)","r":"Type Method","a":"Produces content for a conditional statement in a multi-statement closure when the condition is true"},{"t":"buildEither(first:)","p":"documentation/LightweightCodeRequirements/LaunchConstraintBuilder/buildEither(first:)","r":"Type Method","a":"Produces content for a conditional statement in a multi-statement closure when the condition is true"},{"t":"buildEither(first:)","p":"documentation/LightweightCodeRequirements/OnDiskConstraintBuilder/buildEither(first:)","r":"Type Method","a":"Produces content for a conditional statement in a multi-statement closure when the condition is true"},{"t":"buildEither(second:)","p":"documentation/LightweightCodeRequirements/ProcessConstraintBuilder/buildEither(second:)","r":"Type Method","a":"Produces content for a conditional statement in a multi-statement closure when the condition is false"},{"t":"buildEither(second:)","p":"documentation/LightweightCodeRequirements/LaunchConstraintBuilder/buildEither(second:)","r":"Type Method","a":"Produces content for a conditional statement in a multi-statement closure when the condition is false"},{"t":"buildEither(second:)","p":"documentation/LightweightCodeRequirements/OnDiskConstraintBuilder/buildEither(second:)","r":"Type Method","a":"Produces content for a conditional statement in a multi-statement closure when the condition is false"},{"t":"buildExpression(_:)","p":"documentation/LightweightCodeRequirements/ProcessConstraintBuilder/buildExpression(_:)-7rglu","r":"Type Method","a":"Builds an expression within the builder"},{"t":"buildExpression(_:)","p":"documentation/LightweightCodeRequirements/ProcessConstraintBuilder/buildExpression(_:)-6zrmh","r":"Type Method","a":"Builds an expression within the builder"},{"t":"buildExpression(_:)","p":"documentation/LightweightCodeRequirements/LaunchConstraintBuilder/buildExpression(_:)-5tl61","r":"Type Method","a":"Builds an expression within the builder"},{"t":"buildExpression(_:)","p":"documentation/LightweightCodeRequirements/LaunchConstraintBuilder/buildExpression(_:)-6l0k6","r":"Type Method","a":"Builds an expression within the builder"},{"t":"buildExpression(_:)","p":"documentation/LightweightCodeRequirements/OnDiskConstraintBuilder/buildExpression(_:)-1qla","r":"Type Method","a":"Builds an expression within the builder"},{"t":"buildExpression(_:)","p":"documentation/LightweightCodeRequirements/OnDiskConstraintBuilder/buildExpression(_:)-3uyy8","r":"Type Method","a":"Builds an expression within the builder"},{"t":"buildOptional(_:)","p":"documentation/LightweightCodeRequirements/ProcessConstraintBuilder/buildOptional(_:)","r":"Type Method","a":"Produces content for a conditional statement in a multi-statement closure when the condition is true and has no else option."},{"t":"buildOptional(_:)","p":"documentation/LightweightCodeRequirements/OnDiskConstraintBuilder/buildOptional(_:)","r":"Type Method","a":"Produces content for a conditional statement in a multi-statement closure when the condition is true and has no else option"},{"t":"buildOptional(_:)","p":"documentation/LightweightCodeRequirements/LaunchConstraintBuilder/buildOptional(_:)","r":"Type Method","a":"Produces content for a conditional statement in a multi-statement closure when the condition is true and has no else option"},{"t":"developerID","p":"documentation/LightweightCodeRequirements/ValidationCategory/Value/developerID","r":"Type Property","a":"Indicates that the code is signed by an Apple issued Developer ID certificate.","v":{"iOS":"17.4","iPadOS":"17.4","Mac Catalyst":"17.4","macOS":"14.4","tvOS":"17.4","visionOS":"1.1","watchOS":"10.4"}},{"t":"development","p":"documentation/LightweightCodeRequirements/ValidationCategory/Value/development","r":"Type Property","a":"Indicates that the code is signed by an Apple issued development certificate.","v":{"iOS":"17.4","iPadOS":"17.4","Mac Catalyst":"17.4","macOS":"14.4","tvOS":"17.4","visionOS":"1.1","watchOS":"10.4"}},{"t":"driverKit","p":"documentation/LightweightCodeRequirements/PlatformType/Value/driverKit","r":"Type Property","a":"The platform type for a driverkit driver.","v":{"iOS":"17.4","iPadOS":"17.4","Mac Catalyst":"17.4","macOS":"14.4","tvOS":"17.4","visionOS":"1.1","watchOS":"10.4"}},{"t":"elementAtIndex(_:)","p":"documentation/LightweightCodeRequirements/EntitlementsQuery/elementAtIndex(_:)","r":"Instance Method","a":"Match against the specified index (0 based) in an array. Chain additional qualifiers to constrain the value of element."},{"t":"encode(to:)","p":"documentation/LightweightCodeRequirements/SigningIdentifier/encode(to:)","r":"Instance Method","a":"Encodes this value into the given encoder"},{"t":"encode(to:)","p":"documentation/LightweightCodeRequirements/CodeDirectoryHash/encode(to:)","r":"Instance Method","a":"Encodes this value into the given encoder"},{"t":"encode(to:)","p":"documentation/LightweightCodeRequirements/IsSIPProtected/encode(to:)","r":"Instance Method","a":"Encodes this value into the given encoder"},{"t":"encode(to:)","p":"documentation/LightweightCodeRequirements/IsInitProcess/encode(to:)","r":"Instance Method","a":"Encodes this value into the given encoder"},{"t":"encode(to:)","p":"documentation/LightweightCodeRequirements/TeamIdentifier/encode(to:)","r":"Instance Method","a":"Encodes this value into the given encoder"},{"t":"encode(to:)","p":"documentation/LightweightCodeRequirements/OnDiskCodeRequirement/encode(to:)","r":"Instance Method","a":"Encodes this value into the given encoder"},{"t":"encode(to:)","p":"documentation/LightweightCodeRequirements/ValidationCategory/encode(to:)","r":"Instance Method","a":"Encodes this value into the given encoder"},{"t":"encode(to:)","p":"documentation/LightweightCodeRequirements/InfoPlistHash/encode(to:)","r":"Instance Method","a":"Encodes this value into the given encoder"},{"t":"encode(to:)","p":"documentation/LightweightCodeRequirements/EntitlementsQuery/encode(to:)","r":"Instance Method","a":"Encodes this value into the given encoder"},{"t":"encode(to:)","p":"documentation/LightweightCodeRequirements/PlatformType/encode(to:)","r":"Instance Method","a":"Encodes this value into the given encoder"},{"t":"encode(to:)","p":"documentation/LightweightCodeRequirements/LaunchCodeRequirement/encode(to:)","r":"Instance Method","a":"Encodes this value into the given encoder"},{"t":"encode(to:)","p":"documentation/LightweightCodeRequirements/TeamIdentifierMatchesCurrentProcess/encode(to:)","r":"Instance Method","a":"Encodes this constraint into the given encoder."},{"t":"encode(to:)","p":"documentation/LightweightCodeRequirements/ProcessCodeRequirement/encode(to:)","r":"Instance Method","a":"Encodes this value into the given encoder"},{"t":"encode(to:)","p":"documentation/LightweightCodeRequirements/IsMainBinary/encode(to:)","r":"Instance Method","a":"Encodes this value into the given encoder"},{"t":"enterprise","p":"documentation/LightweightCodeRequirements/ValidationCategory/Value/enterprise","r":"Type Property","a":"Indicates that the code is signed by an Apple issued distribution certificate and allowed to run via Provisioning profile.","v":{"iOS":"17.4","iPadOS":"17.4","Mac Catalyst":"17.4","macOS":"14.4","tvOS":"17.4","visionOS":"1.1","watchOS":"10.4"}},{"t":"failureReason","p":"documentation/LightweightCodeRequirements/ValidationResult/failureReason","r":"Instance Property","v":{"Mac Catalyst":"18.0","macOS":"15.0"}},{"t":"iOS","p":"documentation/LightweightCodeRequirements/PlatformType/Value/iOS","r":"Type Property","a":"The platform type for iOS/iPadOS software running on iOS/ipadOS/macOS/visionOS","v":{"iOS":"17.4","iPadOS":"17.4","Mac Catalyst":"17.4","macOS":"14.4","tvOS":"17.4","visionOS":"1.1","watchOS":"10.4"}},{"t":"iOSSimulator","p":"documentation/LightweightCodeRequirements/PlatformType/Value/iOSSimulator","r":"Type Property","a":"The platform type for code running in the iOS Simulator.","v":{"iOS":"17.4","iPadOS":"17.4","Mac Catalyst":"17.4","macOS":"14.4","tvOS":"17.4","visionOS":"1.1","watchOS":"10.4"}},{"t":"in(_:)","p":"documentation/LightweightCodeRequirements/SigningIdentifier/in(_:)-57qq8","r":"Type Method","a":"Matches if the signing identifier of the code matches any of the provided signing identifiers."},{"t":"in(_:)","p":"documentation/LightweightCodeRequirements/SigningIdentifier/in(_:)-57h8m","r":"Type Method","a":"Matches if the signing identifier of the code matches any of the provided signing identifiers."},{"t":"in(_:)","p":"documentation/LightweightCodeRequirements/CodeDirectoryHash/in(_:)-912dv","r":"Type Method","a":"Match against any of the code directory hashes in the provided list."},{"t":"in(_:)","p":"documentation/LightweightCodeRequirements/CodeDirectoryHash/in(_:)-1kiuo","r":"Type Method","a":"Match against any of the code directory hashes in the provided list."},{"t":"in(_:)","p":"documentation/LightweightCodeRequirements/TeamIdentifier/in(_:)-9x3l9","r":"Type Method","a":"Matches if the team identifier of the code matches any of the provided team identifiers."},{"t":"in(_:)","p":"documentation/LightweightCodeRequirements/TeamIdentifier/in(_:)-1z4vz","r":"Type Method","a":"Matches if the team identifier of the code matches any of the provided team identifiers."},{"t":"in(_:)","p":"documentation/LightweightCodeRequirements/ValidationCategory/in(_:)-94p2z","r":"Type Method","a":"Matches if the file or process is signed in a way that conforms to any of the specified categories."},{"t":"in(_:)","p":"documentation/LightweightCodeRequirements/ValidationCategory/in(_:)-1skt4","r":"Type Method","a":"Matches if the file or process is signed in a way that conforms to any of the specified categories."},{"t":"in(_:)","p":"documentation/LightweightCodeRequirements/InfoPlistHash/in(_:)-18amo","r":"Type Method","a":"Match against any of the Info.plist hashes in the provided list."},{"t":"in(_:)","p":"documentation/LightweightCodeRequirements/InfoPlistHash/in(_:)-1rwy8","r":"Type Method","a":"Match against any of the Info.plist hashes in the provided list."},{"t":"in(_:)","p":"documentation/LightweightCodeRequirements/PlatformType/in(_:)-44pc3","r":"Type Method","a":"Matches if the process is running as any of the specified platform types or if the file supports any of the specified platform types."},{"t":"in(_:)","p":"documentation/LightweightCodeRequirements/PlatformType/in(_:)-1ndmu","r":"Type Method","a":"Matches if the process is running as any of the specified platform types or if the file supports any of the specified platform types."},{"t":"init()","p":"documentation/LightweightCodeRequirements/IsSIPProtected/init()","r":"Initializer","a":"Matches if the file is SIP protected.","v":{"iOS":"17.4","iPadOS":"17.4","Mac Catalyst":"17.4","macOS":"14.4","tvOS":"17.4","visionOS":"1.1","watchOS":"10.4"}},{"t":"init()","p":"documentation/LightweightCodeRequirements/IsInitProcess/init()","r":"Initializer","a":"Matches if the process is the init process.","v":{"iOS":"17.4","iPadOS":"17.4","Mac Catalyst":"17.4","macOS":"14.4","tvOS":"17.4","visionOS":"1.1","watchOS":"10.4"}},{"t":"init()","p":"documentation/LightweightCodeRequirements/TeamIdentifierMatchesCurrentProcess/init()","r":"Initializer","a":"Creates a constraint that matches the current process\u2019s team identifier.","v":{"iOS":"18.0","iPadOS":"18.0","Mac Catalyst":"18.0","macOS":"15.0","tvOS":"18.0","visionOS":"2.0","watchOS":"11.0"}},{"t":"init()","p":"documentation/LightweightCodeRequirements/IsMainBinary/init()","r":"Initializer","a":"Matches if the process or file is a main binary","v":{"iOS":"17.4","iPadOS":"17.4","Mac Catalyst":"17.4","macOS":"14.4","tvOS":"17.4","visionOS":"1.1","watchOS":"10.4"}},{"t":"init(_:)","p":"documentation/LightweightCodeRequirements/SigningIdentifier/init(_:)","r":"Initializer","a":"Matches if the provided string matches the signing identifier of the code."},{"t":"init(_:)","p":"documentation/LightweightCodeRequirements/CodeDirectoryHash/init(_:)","r":"Initializer","a":"Match against a single code directory hash."},{"t":"init(_:)","p":"documentation/LightweightCodeRequirements/IsSIPProtected/init(_:)","r":"Initializer","a":"Matches if the file is or isn\u2019t SIP protected depending on the specified value."},{"t":"init(_:)","p":"documentation/LightweightCodeRequirements/IsInitProcess/init(_:)","r":"Initializer","a":"Matches if the process is or is not the init process depending on the specified value."},{"t":"init(_:)","p":"documentation/LightweightCodeRequirements/TeamIdentifier/init(_:)","r":"Initializer","a":"Matches if the provided string matches the team identifier of the code."},{"t":"init(_:)","p":"documentation/LightweightCodeRequirements/OnDiskCodeRequirement/init(_:)-2lfey","r":"Initializer","a":"Convert a [LaunchCodeRequirement](/documentation/lightweightcoderequirements/launchcoderequirement) to an [OnDiskCodeRequirement](/documentation/lightweightcoderequirements/ondiskcoderequirement) if possible."},{"t":"init(_:)","p":"documentation/LightweightCodeRequirements/OnDiskCodeRequirement/init(_:)-9imtm","r":"Initializer","a":"Convert a [ProcessCodeRequirement](/documentation/lightweightcoderequirements/processcoderequirement) to an [OnDiskCodeRequirement](/documentation/lightweightcoderequirements/ondiskcoderequirement) if possible."},{"t":"init(_:)","p":"documentation/LightweightCodeRequirements/ValidationCategory/init(_:)","r":"Initializer","a":"Matches if the file or process is signed in a way that conforms to the specified category."},{"t":"init(_:)","p":"documentation/LightweightCodeRequirements/InfoPlistHash/init(_:)","r":"Initializer","a":"Match against a single Info.plist hash"},{"t":"init(_:)","p":"documentation/LightweightCodeRequirements/PlatformType/init(_:)","r":"Initializer","a":"Matches if the process is running as the specified platform type or if the file supports the specified platform type."},{"t":"init(_:)","p":"documentation/LightweightCodeRequirements/LaunchCodeRequirement/init(_:)-5fh0u","r":"Initializer","a":"Convert a [ProcessCodeRequirement](/documentation/lightweightcoderequirements/processcoderequirement) to a [LaunchCodeRequirement](/documentation/lightweightcoderequirements/launchcoderequirement) if possible."},{"t":"init(_:)","p":"documentation/LightweightCodeRequirements/LaunchCodeRequirement/init(_:)-6hixy","r":"Initializer","a":"Convert a [OnDiskCodeRequirement](/documentation/lightweightcoderequirements/ondiskcoderequirement) to a [LaunchCodeRequirement](/documentation/lightweightcoderequirements/launchcoderequirement) if possible."},{"t":"init(_:)","p":"documentation/LightweightCodeRequirements/TeamIdentifierMatchesCurrentProcess/init(_:)","r":"Initializer","a":"Creates a constraint that tests whether a process\u2019s team identifier matches the current process\u2019s team identifier."},{"t":"init(_:)","p":"documentation/LightweightCodeRequirements/ProcessCodeRequirement/init(_:)-4gkz2","r":"Initializer","a":"Convert a [LaunchCodeRequirement](/documentation/lightweightcoderequirements/launchcoderequirement) to a [ProcessCodeRequirement](/documentation/lightweightcoderequirements/processcoderequirement) if possible."},{"t":"init(_:)","p":"documentation/LightweightCodeRequirements/ProcessCodeRequirement/init(_:)-1va02","r":"Initializer","a":"Convert an [OnDiskCodeRequirement](/documentation/lightweightcoderequirements/ondiskcoderequirement) to a [ProcessCodeRequirement](/documentation/lightweightcoderequirements/processcoderequirement) if possible."},{"t":"init(_:)","p":"documentation/LightweightCodeRequirements/IsMainBinary/init(_:)","r":"Initializer","a":"Matches if the process or file is or isn\u2019t a main binary depending on the specified value."},{"t":"init(from:)","p":"documentation/LightweightCodeRequirements/SigningIdentifier/init(from:)","r":"Initializer","a":"Create a new instance by decoding from the given decoder"},{"t":"init(from:)","p":"documentation/LightweightCodeRequirements/CodeDirectoryHash/init(from:)","r":"Initializer","a":"Create a new instance by decoding from the given decoder"},{"t":"init(from:)","p":"documentation/LightweightCodeRequirements/IsInitProcess/init(from:)","r":"Initializer","a":"Create a new instance by decoding from the given decoder"},{"t":"init(from:)","p":"documentation/LightweightCodeRequirements/IsSIPProtected/init(from:)","r":"Initializer","a":"Create a new instance by decoding from the given decoder"},{"t":"init(from:)","p":"documentation/LightweightCodeRequirements/TeamIdentifier/init(from:)","r":"Initializer","a":"Create a new instance by decoding from the given decoder"},{"t":"init(from:)","p":"documentation/LightweightCodeRequirements/OnDiskCodeRequirement/init(from:)","r":"Initializer","a":"Create a new instance by decoding from the given decoder"},{"t":"init(from:)","p":"documentation/LightweightCodeRequirements/ValidationCategory/init(from:)","r":"Initializer","a":"Create a new instance by decoding from the given decoder"},{"t":"init(from:)","p":"documentation/LightweightCodeRequirements/InfoPlistHash/init(from:)","r":"Initializer","a":"Create a new instance by decoding from the given decoder"},{"t":"init(from:)","p":"documentation/LightweightCodeRequirements/EntitlementsQuery/init(from:)","r":"Initializer","a":"Create a new instance by decoding from the given decoder"},{"t":"init(from:)","p":"documentation/LightweightCodeRequirements/PlatformType/init(from:)","r":"Initializer","a":"Create a new instance by decoding from the given decoder"},{"t":"init(from:)","p":"documentation/LightweightCodeRequirements/LaunchCodeRequirement/init(from:)","r":"Initializer","a":"Create a new instance by decoding from the given decoder"},{"t":"init(from:)","p":"documentation/LightweightCodeRequirements/TeamIdentifierMatchesCurrentProcess/init(from:)","r":"Initializer","a":"Create a new constraint by decoding from the given decoder"},{"t":"init(from:)","p":"documentation/LightweightCodeRequirements/ProcessCodeRequirement/init(from:)","r":"Initializer","a":"Create a new instance by decoding from the given decoder"},{"t":"init(from:)","p":"documentation/LightweightCodeRequirements/IsMainBinary/init(from:)","r":"Initializer","a":"Create a new instance by decoding from the given decoder"},{"t":"init(rawValue:)","p":"documentation/LightweightCodeRequirements/ValidationCategory/Value/init(rawValue:)","r":"Initializer","a":"Creates a new instance with the specified raw value."},{"t":"init(rawValue:)","p":"documentation/LightweightCodeRequirements/PlatformType/Value/init(rawValue:)","r":"Initializer","a":"Creates a new instance with the specified raw value."},{"t":"isAdhocSigned","p":"documentation/LightweightCodeRequirements/ProcessCodeSigningFlags/ValueSet/isAdhocSigned","r":"Type Property","a":"The code is adhoc signed i.e. it contains a code directory and page hashes but no CMS signature.","v":{"iOS":"17.4","iPadOS":"17.4","Mac Catalyst":"17.4","macOS":"14.4","tvOS":"17.4","visionOS":"1.1","watchOS":"10.4"}},{"t":"isAdhocSigned","p":"documentation/LightweightCodeRequirements/OnDiskCodeSigningFlags/ValueSet/isAdhocSigned","r":"Type Property","a":"The code is adhoc signed i.e. it contains a code directory and page hashes but no CMS signature.","v":{"iOS":"17.4","iPadOS":"17.4","Mac Catalyst":"17.4","macOS":"14.4","tvOS":"17.4","visionOS":"1.1","watchOS":"10.4"}},{"t":"isCertificateExpirationEnforced","p":"documentation/LightweightCodeRequirements/ProcessCodeSigningFlags/ValueSet/isCertificateExpirationEnforced","r":"Type Property","a":"Flag indicating that the signature on this code should be treated as invalid if the certificate it was signed with expired.","v":{"iOS":"17.4","iPadOS":"17.4","Mac Catalyst":"17.4","macOS":"14.4","tvOS":"17.4","visionOS":"1.1","watchOS":"10.4"}},{"t":"isCertificateExpirationEnforced","p":"documentation/LightweightCodeRequirements/OnDiskCodeSigningFlags/ValueSet/isCertificateExpirationEnforced","r":"Type Property","a":"Flag indicating that the signature on this code should be treated as invalid if the certificate it was signed with expired.","v":{"iOS":"17.4","iPadOS":"17.4","Mac Catalyst":"17.4","macOS":"14.4","tvOS":"17.4","visionOS":"1.1","watchOS":"10.4"}},{"t":"isCodeSignatureRequiredForAllExecutableCode","p":"documentation/LightweightCodeRequirements/ProcessCodeSigningFlags/ValueSet/isCodeSignatureRequiredForAllExecutableCode","r":"Type Property","a":"Flag indicating that the process should not allow code to execute from memory if that memory is not associated with a code signature.","v":{"iOS":"17.4","iPadOS":"17.4","Mac Catalyst":"17.4","macOS":"14.4","tvOS":"17.4","visionOS":"1.1","watchOS":"10.4"}},{"t":"isCodeSignatureRequiredForAllExecutableCode","p":"documentation/LightweightCodeRequirements/OnDiskCodeSigningFlags/ValueSet/isCodeSignatureRequiredForAllExecutableCode","r":"Type Property","a":"Flag indicating that the process should not allow code to execute from memory if that memory is not associated with a code signature.","v":{"iOS":"17.4","iPadOS":"17.4","Mac Catalyst":"17.4","macOS":"14.4","tvOS":"17.4","visionOS":"1.1","watchOS":"10.4"}},{"t":"isDebuggable","p":"documentation/LightweightCodeRequirements/ProcessCodeSigningFlags/ValueSet/isDebuggable","r":"Type Property","a":"Flag indicating that the process is debuggable by authorized debuggers.","v":{"iOS":"17.4","iPadOS":"17.4","Mac Catalyst":"17.4","macOS":"14.4","tvOS":"17.4","visionOS":"1.1","watchOS":"10.4"}},{"t":"isDebugged","p":"documentation/LightweightCodeRequirements/ProcessCodeSigningFlags/ValueSet/isDebugged","r":"Type Property","a":"Flag indicating that the process has been attached by a debugger.","v":{"iOS":"17.4","iPadOS":"17.4","Mac Catalyst":"17.4","macOS":"14.4","tvOS":"17.4","visionOS":"1.1","watchOS":"10.4"}},{"t":"isDynamicLinkerPolicyHardened","p":"documentation/LightweightCodeRequirements/ProcessCodeSigningFlags/ValueSet/isDynamicLinkerPolicyHardened","r":"Type Property","a":"Flag indicating that the process should get hardened dynamic linker policies.","v":{"iOS":"17.4","iPadOS":"17.4","Mac Catalyst":"17.4","macOS":"14.4","tvOS":"17.4","visionOS":"1.1","watchOS":"10.4"}},{"t":"isDynamicLinkerPolicyHardened","p":"documentation/LightweightCodeRequirements/OnDiskCodeSigningFlags/ValueSet/isDynamicLinkerPolicyHardened","r":"Type Property","a":"Flag indicating that the process should get hardened dynamic linker policies.","v":{"iOS":"17.4","iPadOS":"17.4","Mac Catalyst":"17.4","macOS":"14.4","tvOS":"17.4","visionOS":"1.1","watchOS":"10.4"}},{"t":"isDynamicallyValid","p":"documentation/LightweightCodeRequirements/ProcessCodeSigningFlags/ValueSet/isDynamicallyValid","r":"Type Property","a":"Flag indicating that no code signing validation errors have been found for the process.","v":{"iOS":"17.4","iPadOS":"17.4","Mac Catalyst":"17.4","macOS":"14.4","tvOS":"17.4","visionOS":"1.1","watchOS":"10.4"}},{"t":"isHardenedRuntimeEnforced","p":"documentation/LightweightCodeRequirements/ProcessCodeSigningFlags/ValueSet/isHardenedRuntimeEnforced","r":"Type Property","a":"Flag indicating that the process has enabled the Hardened Runtime","v":{"iOS":"17.4","iPadOS":"17.4","Mac Catalyst":"17.4","macOS":"14.4","tvOS":"17.4","visionOS":"1.1","watchOS":"10.4"}},{"t":"isHardenedRuntimeEnforced","p":"documentation/LightweightCodeRequirements/OnDiskCodeSigningFlags/ValueSet/isHardenedRuntimeEnforced","r":"Type Property","a":"Flag indicating that the process has enabled the Hardened Runtime","v":{"iOS":"17.4","iPadOS":"17.4","Mac Catalyst":"17.4","macOS":"14.4","tvOS":"17.4","visionOS":"1.1","watchOS":"10.4"}},{"t":"isLibraryValidationRequired","p":"documentation/LightweightCodeRequirements/ProcessCodeSigningFlags/ValueSet/isLibraryValidationRequired","r":"Type Property","a":"Flag indicating that the process should enforce Library Validation.","v":{"iOS":"17.4","iPadOS":"17.4","Mac Catalyst":"17.4","macOS":"14.4","tvOS":"17.4","visionOS":"1.1","watchOS":"10.4"}},{"t":"isLibraryValidationRequired","p":"documentation/LightweightCodeRequirements/OnDiskCodeSigningFlags/ValueSet/isLibraryValidationRequired","r":"Type Property","a":"Flag indicating that the process should enforce Library Validation.","v":{"iOS":"17.4","iPadOS":"17.4","Mac Catalyst":"17.4","macOS":"14.4","tvOS":"17.4","visionOS":"1.1","watchOS":"10.4"}},{"t":"isPlatformSigned","p":"documentation/LightweightCodeRequirements/ProcessCodeSigningFlags/ValueSet/isPlatformSigned","r":"Type Property","a":"Flag indicating that the binary has been identified as a platform binary (Apple Signed).","v":{"iOS":"17.4","iPadOS":"17.4","Mac Catalyst":"17.4","macOS":"14.4","tvOS":"17.4","visionOS":"1.1","watchOS":"10.4"}},{"t":"isSigned","p":"documentation/LightweightCodeRequirements/ProcessCodeSigningFlags/ValueSet/isSigned","r":"Type Property","a":"Flag indicating that the process is signed.","v":{"iOS":"17.4","iPadOS":"17.4","Mac Catalyst":"17.4","macOS":"14.4","tvOS":"17.4","visionOS":"1.1","watchOS":"10.4"}},{"t":"isSignedByLinker","p":"documentation/LightweightCodeRequirements/ProcessCodeSigningFlags/ValueSet/isSignedByLinker","r":"Type Property","a":"Flag indicating that the code was signed by the linker and not an invocation of codesign.","v":{"iOS":"17.4","iPadOS":"17.4","Mac Catalyst":"17.4","macOS":"14.4","tvOS":"17.4","visionOS":"1.1","watchOS":"10.4"}},{"t":"isSignedByLinker","p":"documentation/LightweightCodeRequirements/OnDiskCodeSigningFlags/ValueSet/isSignedByLinker","r":"Type Property","a":"Flag indicating that the code was signed by the linker and not an invocation of codesign.","v":{"iOS":"17.4","iPadOS":"17.4","Mac Catalyst":"17.4","macOS":"14.4","tvOS":"17.4","visionOS":"1.1","watchOS":"10.4"}},{"t":"isSuperset(of:)","p":"documentation/LightweightCodeRequirements/OnDiskCodeSigningFlags/isSuperset(of:)","r":"Type Method","a":"Matches when the code signing flags on the file/slice are a superset of the specified flags."},{"t":"isSuperset(of:)","p":"documentation/LightweightCodeRequirements/ProcessCodeSigningFlags/isSuperset(of:)","r":"Type Method","a":"Matches when the code signing flags on the process are a superset of the specified flags."},{"t":"key(_:)","p":"documentation/LightweightCodeRequirements/EntitlementsQuery/key(_:)-swift.type.method","r":"Type Method","a":"Match against the specified key name at the root of the entitlements dictionary."},{"t":"key(_:)","p":"documentation/LightweightCodeRequirements/EntitlementsQuery/key(_:)-swift.method","r":"Instance Method","a":"Match the specified key in a nested dictionary"},{"t":"keyPrefix(_:)","p":"documentation/LightweightCodeRequirements/EntitlementsQuery/keyPrefix(_:)-swift.type.method","r":"Type Method","a":"Match the specified key prefix at the root of the entitlements dicitonary. Chain additional qualifiers to constrain the value of the key."},{"t":"keyPrefix(_:)","p":"documentation/LightweightCodeRequirements/EntitlementsQuery/keyPrefix(_:)-swift.method","r":"Instance Method","a":"Match the specified key prefix in a nested dictionary."},{"t":"macCatalyst","p":"documentation/LightweightCodeRequirements/PlatformType/Value/macCatalyst","r":"Type Property","a":"The platform type for macCatalyst software.","v":{"iOS":"17.4","iPadOS":"17.4","Mac Catalyst":"17.4","macOS":"14.4","tvOS":"17.4","visionOS":"1.1","watchOS":"10.4"}},{"t":"macOS","p":"documentation/LightweightCodeRequirements/PlatformType/Value/macOS","r":"Type Property","a":"The platform type for non-macCatalyst macOS software.","v":{"iOS":"17.4","iPadOS":"17.4","Mac Catalyst":"17.4","macOS":"14.4","tvOS":"17.4","visionOS":"1.1","watchOS":"10.4"}},{"t":"match(_:)","p":"documentation/LightweightCodeRequirements/EntitlementsQuery/match(_:)-6msza","r":"Instance Method","a":"Match the specified Int64 against an integer or array of integers."},{"t":"match(_:)","p":"documentation/LightweightCodeRequirements/EntitlementsQuery/match(_:)-5cw98","r":"Instance Method","a":"Match the specified bool value against a bool value."},{"t":"match(_:)","p":"documentation/LightweightCodeRequirements/EntitlementsQuery/match(_:)-5cqvy","r":"Instance Method","a":"Match the specified string value against a string or an array of strings."},{"t":"matchPrefix(_:)","p":"documentation/LightweightCodeRequirements/EntitlementsQuery/matchPrefix(_:)","r":"Instance Method","a":"Match the specified string prefix against a string value or array."},{"t":"matchPrefixSingle(_:)","p":"documentation/LightweightCodeRequirements/EntitlementsQuery/matchPrefixSingle(_:)","r":"Instance Method","a":"Match the specified string prefix value against a string value (not an array)."},{"t":"matchSingle(_:)","p":"documentation/LightweightCodeRequirements/EntitlementsQuery/matchSingle(_:)-49kv7","r":"Instance Method","a":"Match the specified Int64 value against an integer value (not an array)."},{"t":"matchSingle(_:)","p":"documentation/LightweightCodeRequirements/EntitlementsQuery/matchSingle(_:)-8ggh1","r":"Instance Method","a":"Match the specified string against a string value (not an array)."},{"t":"matchType(_:)","p":"documentation/LightweightCodeRequirements/EntitlementsQuery/matchType(_:)","r":"Instance Method","a":"Matches the specified type against the current element."},{"t":"none","p":"documentation/LightweightCodeRequirements/ValidationCategory/Value/none","r":"Type Property","a":"Indicates that the code is either adhoc signed or signed by an un-recognized certificate chain.","v":{"iOS":"17.4","iPadOS":"17.4","Mac Catalyst":"17.4","macOS":"14.4","tvOS":"17.4","visionOS":"1.1","watchOS":"10.4"}},{"t":"platform","p":"documentation/LightweightCodeRequirements/ValidationCategory/Value/platform","r":"Type Property","a":"Indicates that the code is signed by Apple or allowed by a loaded trustcache.","v":{"iOS":"17.4","iPadOS":"17.4","Mac Catalyst":"17.4","macOS":"14.4","tvOS":"17.4","visionOS":"1.1","watchOS":"10.4"}},{"t":"rawValue","p":"documentation/LightweightCodeRequirements/ValidationCategory/Value/rawValue","r":"Instance Property","a":"The corresponding value of the raw type.","v":{"iOS":"17.4","iPadOS":"17.4","Mac Catalyst":"17.4","macOS":"14.4","tvOS":"17.4","visionOS":"1.1","watchOS":"10.4"}},{"t":"rawValue","p":"documentation/LightweightCodeRequirements/PlatformType/Value/rawValue","r":"Instance Property","a":"The corresponding value of the raw type.","v":{"iOS":"17.4","iPadOS":"17.4","Mac Catalyst":"17.4","macOS":"14.4","tvOS":"17.4","visionOS":"1.1","watchOS":"10.4"}},{"t":"requirementMatched","p":"documentation/LightweightCodeRequirements/ValidationResult/requirementMatched","r":"Instance Property","v":{"Mac Catalyst":"18.0","macOS":"15.0"}},{"t":"signalsBusErrorOnCodeSigningFailure","p":"documentation/LightweightCodeRequirements/ProcessCodeSigningFlags/ValueSet/signalsBusErrorOnCodeSigningFailure","r":"Type Property","a":"Code signing failures on page-in should be rejected as SIGBUS errors.","v":{"iOS":"17.4","iPadOS":"17.4","Mac Catalyst":"17.4","macOS":"14.4","tvOS":"17.4","visionOS":"1.1","watchOS":"10.4"}},{"t":"signalsBusErrorOnCodeSigningFailure","p":"documentation/LightweightCodeRequirements/OnDiskCodeSigningFlags/ValueSet/signalsBusErrorOnCodeSigningFailure","r":"Type Property","a":"Code signing failures on page-in should be rejected as SIGBUS errors.","v":{"iOS":"17.4","iPadOS":"17.4","Mac Catalyst":"17.4","macOS":"14.4","tvOS":"17.4","visionOS":"1.1","watchOS":"10.4"}},{"t":"signatureIsValid","p":"documentation/LightweightCodeRequirements/ValidationResult/signatureIsValid","r":"Instance Property","v":{"Mac Catalyst":"18.0","macOS":"15.0"}},{"t":"terminatesOnCodeSigningFailure","p":"documentation/LightweightCodeRequirements/ProcessCodeSigningFlags/ValueSet/terminatesOnCodeSigningFailure","r":"Type Property","a":"Code signing failures on page in should cause the process to be terminated.","v":{"iOS":"17.4","iPadOS":"17.4","Mac Catalyst":"17.4","macOS":"14.4","tvOS":"17.4","visionOS":"1.1","watchOS":"10.4"}},{"t":"terminatesOnCodeSigningFailure","p":"documentation/LightweightCodeRequirements/OnDiskCodeSigningFlags/ValueSet/terminatesOnCodeSigningFailure","r":"Type Property","a":"Code signing failures on page in should cause the process to be terminated.","v":{"iOS":"17.4","iPadOS":"17.4","Mac Catalyst":"17.4","macOS":"14.4","tvOS":"17.4","visionOS":"1.1","watchOS":"10.4"}},{"t":"testflight","p":"documentation/LightweightCodeRequirements/ValidationCategory/Value/testflight","r":"Type Property","a":"Indicates that the code is signed by Apple\u2019s TestFlight certificate","v":{"iOS":"17.4","iPadOS":"17.4","Mac Catalyst":"17.4","macOS":"14.4","tvOS":"17.4","visionOS":"1.1","watchOS":"10.4"}},{"t":"tvOS","p":"documentation/LightweightCodeRequirements/PlatformType/Value/tvOS","r":"Type Property","a":"The platform type for native tvOS software.","v":{"iOS":"17.4","iPadOS":"17.4","Mac Catalyst":"17.4","macOS":"14.4","tvOS":"17.4","visionOS":"1.1","watchOS":"10.4"}},{"t":"tvOSSimulator","p":"documentation/LightweightCodeRequirements/PlatformType/Value/tvOSSimulator","r":"Type Property","a":"The platform type for code running in the tvOS Simulator.","v":{"iOS":"17.4","iPadOS":"17.4","Mac Catalyst":"17.4","macOS":"14.4","tvOS":"17.4","visionOS":"1.1","watchOS":"10.4"}},{"t":"visionOS","p":"documentation/LightweightCodeRequirements/PlatformType/Value/visionOS","r":"Type Property","a":"The platform type for native visionOS code.","v":{"iOS":"17.4","iPadOS":"17.4","Mac Catalyst":"17.4","macOS":"14.4","tvOS":"17.4","visionOS":"1.1","watchOS":"10.4"}},{"t":"visionOSSimulator","p":"documentation/LightweightCodeRequirements/PlatformType/Value/visionOSSimulator","r":"Type Property","a":"The platform type for code running in the visionOS Simulator.","v":{"iOS":"17.4","iPadOS":"17.4","Mac Catalyst":"17.4","macOS":"14.4","tvOS":"17.4","visionOS":"1.1","watchOS":"10.4"}},{"t":"watchOS","p":"documentation/LightweightCodeRequirements/PlatformType/Value/watchOS","r":"Type Property","a":"The platform type for native watchOS software.","v":{"iOS":"17.4","iPadOS":"17.4","Mac Catalyst":"17.4","macOS":"14.4","tvOS":"17.4","visionOS":"1.1","watchOS":"10.4"}},{"t":"watchOSSimulator","p":"documentation/LightweightCodeRequirements/PlatformType/Value/watchOSSimulator","r":"Type Property","a":"The platform type for code running in the watchOS Simulator.","v":{"iOS":"17.4","iPadOS":"17.4","Mac Catalyst":"17.4","macOS":"14.4","tvOS":"17.4","visionOS":"1.1","watchOS":"10.4"}}]