[{"t":"Capturing screen content in macOS","p":"documentation/ScreenCaptureKit/capturing-screen-content-in-macos","r":"Sample Code","a":"Stream desktop content like displays, apps, and windows by adopting screen capture in your app.","v":{"macOS":"15.0","Xcode":"16.0"}},{"t":"Error Constants","p":"documentation/ScreenCaptureKit/error-constants","r":"API Collection","a":"Error code constants for framework operations."},{"t":"SCCaptureDynamicRange","p":"documentation/ScreenCaptureKit/SCCaptureDynamicRange","r":"Enumeration","a":"Specifies whether the captured screen output is standard or high dynamic range.","v":{"iOS":"27.0","iPadOS":"27.0","Mac Catalyst":"18.2","macOS":"15.0"},"beta":true},{"t":"SCCaptureDynamicRange.SDR","p":"documentation/ScreenCaptureKit/SCCaptureDynamicRange/SDR","r":"Case","a":"Specifies that the system captures the screen in standard dynamic range.","v":{"iOS":"27.0","iPadOS":"27.0","Mac Catalyst":"18.2","macOS":"15.0"},"beta":true},{"t":"SCCaptureDynamicRange.hdrCanonicalDisplay","p":"documentation/ScreenCaptureKit/SCCaptureDynamicRange/hdrCanonicalDisplay","r":"Case","a":"Specifies that the system captures the screen in high dynamic range with attributes of the canonical display.","v":{"iOS":"27.0","iPadOS":"27.0","Mac Catalyst":"18.2","macOS":"15.0"},"beta":true},{"t":"SCCaptureDynamicRange.hdrLocalDisplay","p":"documentation/ScreenCaptureKit/SCCaptureDynamicRange/hdrLocalDisplay","r":"Case","a":"Specifies that the system captures the screen in high dynamic range with attributes of the local display.","v":{"Mac Catalyst":"18.2","macOS":"15.0"}},{"t":"SCCaptureResolutionType","p":"documentation/ScreenCaptureKit/SCCaptureResolutionType","r":"Enumeration","a":"Available resolutions for content capture.","v":{"Mac Catalyst":"18.2","macOS":"12.3"}},{"t":"SCCaptureResolutionType.automatic","p":"documentation/ScreenCaptureKit/SCCaptureResolutionType/automatic","r":"Case","a":"Allow ScreenCaptureKit to automatically select the quality of content depending on factors such as network connection.","v":{"Mac Catalyst":"18.2","macOS":"12.3"}},{"t":"SCCaptureResolutionType.best","p":"documentation/ScreenCaptureKit/SCCaptureResolutionType/best","r":"Case","a":"Capture streaming content at the best available resolution.","v":{"Mac Catalyst":"18.2","macOS":"12.3"}},{"t":"SCCaptureResolutionType.nominal","p":"documentation/ScreenCaptureKit/SCCaptureResolutionType/nominal","r":"Case","a":"Capture streaming content with a one point to one pixel conversion factor.","v":{"Mac Catalyst":"18.2","macOS":"12.3"}},{"t":"SCClipBufferingOutput","p":"documentation/ScreenCaptureKit/SCClipBufferingOutput","r":"Class","v":{"iOS":"27.0","iPadOS":"27.0","Mac Catalyst":"27.0","macOS":"27.0","tvOS":"27.0","visionOS":"27.0"},"beta":true},{"t":"SCClipBufferingOutputDelegate","p":"documentation/ScreenCaptureKit/SCClipBufferingOutputDelegate","r":"Protocol","v":{"iOS":"27.0","iPadOS":"27.0","Mac Catalyst":"27.0","macOS":"27.0","tvOS":"27.0","visionOS":"27.0"},"beta":true},{"t":"SCContentFilter","p":"documentation/ScreenCaptureKit/SCContentFilter","r":"Class","a":"An instance that filters the content a stream captures.","v":{"iOS":"27.0","iPadOS":"27.0","Mac Catalyst":"18.2","macOS":"12.3","tvOS":"27.0","visionOS":"27.0"},"beta":true},{"t":"SCContentSharingPicker","p":"documentation/ScreenCaptureKit/SCContentSharingPicker","r":"Class","a":"An instance of a picker presented by the operating system for managing frame-capture streams.","v":{"iOS":"27.0","iPadOS":"27.0","Mac Catalyst":"18.2","macOS":"14.0","tvOS":"27.0","visionOS":"27.0"},"beta":true},{"t":"SCContentSharingPickerConfiguration","p":"documentation/ScreenCaptureKit/SCContentSharingPickerConfiguration-swift.struct","r":"Structure","a":"An instance for configuring the system content-sharing picker.","v":{"iOS":"27.0","iPadOS":"27.0","Mac Catalyst":"18.2","macOS":"14.0","tvOS":"27.0","visionOS":"27.0"},"beta":true},{"t":"SCContentSharingPickerConfiguration","p":"documentation/ScreenCaptureKit/SCContentSharingPickerConfiguration-c.class","r":"Class","a":"An instance for configuring the system content-sharing picker.","v":{"iOS":"27.0","iPadOS":"27.0","Mac Catalyst":"18.2","macOS":"14.0","tvOS":"27.0","visionOS":"27.0"},"beta":true},{"t":"SCContentSharingPickerMode","p":"documentation/ScreenCaptureKit/SCContentSharingPickerMode","r":"Structure","a":"Available modes for selecting streaming content from a picker presented by the operating system.","v":{"Mac Catalyst":"18.2","macOS":"14.0"}},{"t":"SCContentSharingPickerObserver","p":"documentation/ScreenCaptureKit/SCContentSharingPickerObserver","r":"Protocol","a":"An observer protocol your app implements to receive messages from the operating system\u2019s content picker.","v":{"iOS":"27.0","iPadOS":"27.0","Mac Catalyst":"18.2","macOS":"14.0","tvOS":"27.0","visionOS":"27.0"},"beta":true},{"t":"SCDisplay","p":"documentation/ScreenCaptureKit/SCDisplay","r":"Class","a":"An instance that represents a display device.","v":{"Mac Catalyst":"18.2","macOS":"12.3"}},{"t":"SCFrameStatus","p":"documentation/ScreenCaptureKit/SCFrameStatus","r":"Enumeration","a":"Status values for a frame from a stream.","v":{"iOS":"27.0","iPadOS":"27.0","Mac Catalyst":"18.2","macOS":"12.3","tvOS":"27.0","visionOS":"27.0"},"beta":true},{"t":"SCFrameStatus.blank","p":"documentation/ScreenCaptureKit/SCFrameStatus/blank","r":"Case","a":"A status that indicates the system didn\u2019t generate a new frame because the display is blank.","v":{"iOS":"27.0","iPadOS":"27.0","Mac Catalyst":"18.2","macOS":"12.3","tvOS":"27.0","visionOS":"27.0"},"beta":true},{"t":"SCFrameStatus.complete","p":"documentation/ScreenCaptureKit/SCFrameStatus/complete","r":"Case","a":"A status that indicates the system successfully generated a new frame.","v":{"iOS":"27.0","iPadOS":"27.0","Mac Catalyst":"18.2","macOS":"12.3","tvOS":"27.0","visionOS":"27.0"},"beta":true},{"t":"SCFrameStatus.idle","p":"documentation/ScreenCaptureKit/SCFrameStatus/idle","r":"Case","a":"A status that indicates the system didn\u2019t generate a new frame because the display didn\u2019t change.","v":{"iOS":"27.0","iPadOS":"27.0","Mac Catalyst":"18.2","macOS":"12.3","tvOS":"27.0","visionOS":"27.0"},"beta":true},{"t":"SCFrameStatus.started","p":"documentation/ScreenCaptureKit/SCFrameStatus/started","r":"Case","a":"A status that indicates the frame is the first one sent after the stream starts.","v":{"iOS":"27.0","iPadOS":"27.0","Mac Catalyst":"18.2","macOS":"12.3","tvOS":"27.0","visionOS":"27.0"},"beta":true},{"t":"SCFrameStatus.stopped","p":"documentation/ScreenCaptureKit/SCFrameStatus/stopped","r":"Case","a":"A status that indicates the frame is in a stopped state.","v":{"iOS":"27.0","iPadOS":"27.0","Mac Catalyst":"18.2","macOS":"12.3","tvOS":"27.0","visionOS":"27.0"},"beta":true},{"t":"SCFrameStatus.suspended","p":"documentation/ScreenCaptureKit/SCFrameStatus/suspended","r":"Case","a":"A status that indicates the system didn\u2019t generate a new frame because you suspended updates.","v":{"iOS":"27.0","iPadOS":"27.0","Mac Catalyst":"18.2","macOS":"12.3","tvOS":"27.0","visionOS":"27.0"},"beta":true},{"t":"SCPresenterOverlayAlertSetting","p":"documentation/ScreenCaptureKit/SCPresenterOverlayAlertSetting","r":"Enumeration","a":"Configures how to present streaming notifications to a streamer of Presenter Overlay.","v":{"Mac Catalyst":"18.2","macOS":"14.0"}},{"t":"SCPresenterOverlayAlertSetting.always","p":"documentation/ScreenCaptureKit/SCPresenterOverlayAlertSetting/always","r":"Case","a":"Always display an alert when using Presenter Overlay.","v":{"Mac Catalyst":"18.2","macOS":"14.0"}},{"t":"SCPresenterOverlayAlertSetting.never","p":"documentation/ScreenCaptureKit/SCPresenterOverlayAlertSetting/never","r":"Case","a":"Never display an alert when using Presenter Overlay.","v":{"Mac Catalyst":"18.2","macOS":"14.0"}},{"t":"SCPresenterOverlayAlertSetting.system","p":"documentation/ScreenCaptureKit/SCPresenterOverlayAlertSetting/system","r":"Case","a":"Displays an alert when using Presenter Overlay based on the System Settings.","v":{"Mac Catalyst":"18.2","macOS":"14.0"}},{"t":"SCRecordingEditor","p":"documentation/ScreenCaptureKit/SCRecordingEditor","r":"Class","v":{"iOS":"27.0","iPadOS":"27.0","Mac Catalyst":"27.0","macOS":"27.0","tvOS":"27.0","visionOS":"27.0"},"beta":true},{"t":"SCRecordingEditor.Mode","p":"documentation/ScreenCaptureKit/SCRecordingEditor/Mode","r":"Enumeration","v":{"tvOS":"27.0"},"beta":true},{"t":"SCRecordingEditor.Mode.preview","p":"documentation/ScreenCaptureKit/SCRecordingEditor/Mode/preview","r":"Case","v":{"tvOS":"27.0"},"beta":true},{"t":"SCRecordingEditor.Mode.share","p":"documentation/ScreenCaptureKit/SCRecordingEditor/Mode/share","r":"Case","v":{"tvOS":"27.0"},"beta":true},{"t":"SCRecordingEditorDelegate","p":"documentation/ScreenCaptureKit/SCRecordingEditorDelegate","r":"Protocol","v":{"iOS":"27.0","iPadOS":"27.0","Mac Catalyst":"27.0","macOS":"27.0","tvOS":"27.0","visionOS":"27.0"},"beta":true},{"t":"SCRecordingOutput","p":"documentation/ScreenCaptureKit/SCRecordingOutput","r":"Class","v":{"iOS":"27.0","iPadOS":"27.0","Mac Catalyst":"18.2","macOS":"15.0","tvOS":"27.0","visionOS":"27.0"},"beta":true},{"t":"SCRecordingOutputConfiguration","p":"documentation/ScreenCaptureKit/SCRecordingOutputConfiguration","r":"Class","v":{"iOS":"27.0","iPadOS":"27.0","Mac Catalyst":"18.2","macOS":"15.0","tvOS":"27.0","visionOS":"27.0"},"beta":true},{"t":"SCRecordingOutputDelegate","p":"documentation/ScreenCaptureKit/SCRecordingOutputDelegate","r":"Protocol","v":{"iOS":"27.0","iPadOS":"27.0","Mac Catalyst":"18.2","macOS":"15.0","tvOS":"27.0","visionOS":"27.0"},"beta":true},{"t":"SCRunningApplication","p":"documentation/ScreenCaptureKit/SCRunningApplication","r":"Class","a":"An instance that represents an app running on a device.","v":{"Mac Catalyst":"18.2","macOS":"12.3"}},{"t":"SCScreenshotConfiguration","p":"documentation/ScreenCaptureKit/SCScreenshotConfiguration","r":"Class","a":"An object that contains screenshot properties such as output width, height, and image quality specifications.","v":{"Mac Catalyst":"26.0","macOS":"26.0"}},{"t":"SCScreenshotConfiguration.DisplayIntent","p":"documentation/ScreenCaptureKit/SCScreenshotConfiguration/DisplayIntent-swift.enum","r":"Enumeration","a":"A value that specifies the type of display a screenshot rendering optimizes for."},{"t":"SCScreenshotConfiguration.DisplayIntent.canonical","p":"documentation/ScreenCaptureKit/SCScreenshotConfiguration/DisplayIntent-swift.enum/canonical","r":"Case","a":"Specifies that the screenshot renders with canonical display attributes optimizing output for presentation on a high dynamic range display."},{"t":"SCScreenshotConfiguration.DisplayIntent.local","p":"documentation/ScreenCaptureKit/SCScreenshotConfiguration/DisplayIntent-swift.enum/local","r":"Case","a":"Specifies that the screenshot renders with local display attributes optimizing output for presentation on the capture display."},{"t":"SCScreenshotConfiguration.DynamicRange","p":"documentation/ScreenCaptureKit/SCScreenshotConfiguration/DynamicRange-swift.enum","r":"Enumeration","a":"Specifies the type of images returned to the client; standard dynamic range, high dynamic range, or both."},{"t":"SCScreenshotConfiguration.DynamicRange.bothSDRAndHDR","p":"documentation/ScreenCaptureKit/SCScreenshotConfiguration/DynamicRange-swift.enum/bothSDRAndHDR","r":"Case","a":"Returns both standard dynamic range and high dynamic range image versions to the client."},{"t":"SCScreenshotConfiguration.DynamicRange.hdr","p":"documentation/ScreenCaptureKit/SCScreenshotConfiguration/DynamicRange-swift.enum/hdr","r":"Case","a":"Returns a high dynamic range image to the client."},{"t":"SCScreenshotConfiguration.DynamicRange.sdr","p":"documentation/ScreenCaptureKit/SCScreenshotConfiguration/DynamicRange-swift.enum/sdr","r":"Case","a":"Returns a standard dynamic range image to the client."},{"t":"SCScreenshotManager","p":"documentation/ScreenCaptureKit/SCScreenshotManager","r":"Class","a":"An instance for the capture of single frames from a stream.","v":{"Mac Catalyst":"18.2","macOS":"14.0"}},{"t":"SCScreenshotOutput","p":"documentation/ScreenCaptureKit/SCScreenshotOutput","r":"Class","a":"An object that contains all images requested by the client.","v":{"Mac Catalyst":"26.0","macOS":"26.0"}},{"t":"SCShareableContent","p":"documentation/ScreenCaptureKit/SCShareableContent","r":"Class","a":"An instance that represents a set of displays, apps, and windows that your app can capture.","v":{"Mac Catalyst":"18.2","macOS":"12.3"}},{"t":"SCShareableContentInfo","p":"documentation/ScreenCaptureKit/SCShareableContentInfo","r":"Class","a":"An instance that provides information for the content in a given stream.","v":{"Mac Catalyst":"18.2","macOS":"14.0"}},{"t":"SCShareableContentStyle","p":"documentation/ScreenCaptureKit/SCShareableContentStyle","r":"Enumeration","a":"The style of content presented in a stream.","v":{"iOS":"27.0","iPadOS":"27.0","Mac Catalyst":"18.2","macOS":"12.3","tvOS":"27.0","visionOS":"27.0"},"beta":true},{"t":"SCShareableContentStyle.application","p":"documentation/ScreenCaptureKit/SCShareableContentStyle/application","r":"Case","a":"The stream is currently presenting one or more applications.","v":{"Mac Catalyst":"18.2","macOS":"12.3"}},{"t":"SCShareableContentStyle.display","p":"documentation/ScreenCaptureKit/SCShareableContentStyle/display","r":"Case","a":"The stream is currently presenting a complete display.","v":{"iOS":"27.0","iPadOS":"27.0","Mac Catalyst":"18.2","macOS":"12.3","visionOS":"27.0"},"beta":true},{"t":"SCShareableContentStyle.none","p":"documentation/ScreenCaptureKit/SCShareableContentStyle/none","r":"Case","a":"The stream isn\u2019t currently presenting any content.","v":{"iOS":"27.0","iPadOS":"27.0","Mac Catalyst":"18.2","macOS":"12.3","tvOS":"27.0","visionOS":"27.0"},"beta":true},{"t":"SCShareableContentStyle.window","p":"documentation/ScreenCaptureKit/SCShareableContentStyle/window","r":"Case","a":"The stream is currently presenting one or more windows.","v":{"iOS":"27.0","iPadOS":"27.0","Mac Catalyst":"18.2","macOS":"12.3","tvOS":"27.0","visionOS":"27.0"},"beta":true},{"t":"SCStream","p":"documentation/ScreenCaptureKit/SCStream","r":"Class","a":"An instance that represents a stream of shareable content.","v":{"iOS":"27.0","iPadOS":"27.0","Mac Catalyst":"18.2","macOS":"12.3","tvOS":"27.0","visionOS":"27.0"},"beta":true},{"t":"SCStreamConfiguration","p":"documentation/ScreenCaptureKit/SCStreamConfiguration","r":"Class","a":"An instance that provides the output configuration for a stream.","v":{"iOS":"27.0","iPadOS":"27.0","Mac Catalyst":"18.2","macOS":"12.3","tvOS":"27.0","visionOS":"27.0"},"beta":true},{"t":"SCStreamConfiguration.Preset","p":"documentation/ScreenCaptureKit/SCStreamConfiguration/Preset","r":"Enumeration","v":{"iOS":"27.0","iPadOS":"27.0","Mac Catalyst":"18.2","macOS":"15.0"},"beta":true},{"t":"SCStreamConfiguration.Preset.captureHDRRecordingPreservedSDRHDR10","p":"documentation/ScreenCaptureKit/SCStreamConfiguration/Preset/captureHDRRecordingPreservedSDRHDR10","r":"Case","v":{"iOS":"27.0","iPadOS":"27.0","Mac Catalyst":"26.0","macOS":"26.0"},"beta":true},{"t":"SCStreamConfiguration.Preset.captureHDRScreenshotCanonicalDisplay","p":"documentation/ScreenCaptureKit/SCStreamConfiguration/Preset/captureHDRScreenshotCanonicalDisplay","r":"Case","v":{"Mac Catalyst":"18.2","macOS":"15.0"}},{"t":"SCStreamConfiguration.Preset.captureHDRScreenshotLocalDisplay","p":"documentation/ScreenCaptureKit/SCStreamConfiguration/Preset/captureHDRScreenshotLocalDisplay","r":"Case","v":{"Mac Catalyst":"18.2","macOS":"15.0"}},{"t":"SCStreamConfiguration.Preset.captureHDRStreamCanonicalDisplay","p":"documentation/ScreenCaptureKit/SCStreamConfiguration/Preset/captureHDRStreamCanonicalDisplay","r":"Case","v":{"Mac Catalyst":"18.2","macOS":"15.0"}},{"t":"SCStreamConfiguration.Preset.captureHDRStreamLocalDisplay","p":"documentation/ScreenCaptureKit/SCStreamConfiguration/Preset/captureHDRStreamLocalDisplay","r":"Case","v":{"Mac Catalyst":"18.2","macOS":"15.0"}},{"t":"SCStreamDelegate","p":"documentation/ScreenCaptureKit/SCStreamDelegate","r":"Protocol","a":"A delegate protocol your app implements to respond to stream events.","v":{"iOS":"27.0","iPadOS":"27.0","Mac Catalyst":"18.2","macOS":"12.3","tvOS":"27.0","visionOS":"27.0"},"beta":true},{"t":"SCStreamError","p":"documentation/ScreenCaptureKit/SCStreamError","r":"Structure","a":"An instance representing a ScreenCaptureKit framework error.","v":{"iOS":"27.0","iPadOS":"27.0","Mac Catalyst":"18.2","macOS":"12.3","tvOS":"27.0","visionOS":"27.0"},"beta":true},{"t":"SCStreamError.Code","p":"documentation/ScreenCaptureKit/SCStreamError/Code","r":"Enumeration","a":"Codes for user cancellation events and errors that can occur in ScreenCaptureKit.","v":{"iOS":"27.0","iPadOS":"27.0","Mac Catalyst":"18.2","macOS":"12.3","tvOS":"27.0","visionOS":"27.0"},"beta":true},{"t":"SCStreamError.Code.attemptToConfigState","p":"documentation/ScreenCaptureKit/SCStreamError/Code/attemptToConfigState","r":"Case","a":"An error message that indicates a stream couldn\u2019t update its configuration.","v":{"iOS":"27.0","iPadOS":"27.0","Mac Catalyst":"18.2","macOS":"12.3","tvOS":"27.0","visionOS":"27.0"},"beta":true},{"t":"SCStreamError.Code.attemptToStartStreamState","p":"documentation/ScreenCaptureKit/SCStreamError/Code/attemptToStartStreamState","r":"Case","a":"An error message that indicates a stream is already running or doesn\u2019t exist when trying to start a stream.","v":{"iOS":"27.0","iPadOS":"27.0","Mac Catalyst":"18.2","macOS":"12.3","tvOS":"27.0","visionOS":"27.0"},"beta":true},{"t":"SCStreamError.Code.attemptToStopStreamState","p":"documentation/ScreenCaptureKit/SCStreamError/Code/attemptToStopStreamState","r":"Case","a":"An error message that indicates a stream is already stopped or doesn\u2019t exist when trying to stop a stream.","v":{"iOS":"27.0","iPadOS":"27.0","Mac Catalyst":"18.2","macOS":"12.3","tvOS":"27.0","visionOS":"27.0"},"beta":true},{"t":"SCStreamError.Code.attemptToUpdateFilterState","p":"documentation/ScreenCaptureKit/SCStreamError/Code/attemptToUpdateFilterState","r":"Case","a":"An error message that indicates a stream couldn\u2019t update its content filter.","v":{"iOS":"27.0","iPadOS":"27.0","Mac Catalyst":"18.2","macOS":"12.3","tvOS":"27.0","visionOS":"27.0"},"beta":true},{"t":"SCStreamError.Code.failedApplicationConnectionInterrupted","p":"documentation/ScreenCaptureKit/SCStreamError/Code/failedApplicationConnectionInterrupted","r":"Case","a":"An error message that indicates there was an interruption in a connection to an app.","v":{"iOS":"27.0","iPadOS":"27.0","Mac Catalyst":"18.2","macOS":"12.3","tvOS":"27.0","visionOS":"27.0"},"beta":true},{"t":"SCStreamError.Code.failedApplicationConnectionInvalid","p":"documentation/ScreenCaptureKit/SCStreamError/Code/failedApplicationConnectionInvalid","r":"Case","a":"An error message that indicates the stream lost its connection to an app.","v":{"iOS":"27.0","iPadOS":"27.0","Mac Catalyst":"18.2","macOS":"12.3","tvOS":"27.0","visionOS":"27.0"},"beta":true},{"t":"SCStreamError.Code.failedNoMatchingApplicationContext","p":"documentation/ScreenCaptureKit/SCStreamError/Code/failedNoMatchingApplicationContext","r":"Case","a":"An error message that indicates there isn\u2019t a matching app context for streaming.","v":{"iOS":"27.0","iPadOS":"27.0","Mac Catalyst":"18.2","macOS":"12.3","tvOS":"27.0","visionOS":"27.0"},"beta":true},{"t":"SCStreamError.Code.failedToStart","p":"documentation/ScreenCaptureKit/SCStreamError/Code/failedToStart","r":"Case","a":"An error message that indicates a stream failed to start.","v":{"iOS":"27.0","iPadOS":"27.0","Mac Catalyst":"18.2","macOS":"12.3","tvOS":"27.0","visionOS":"27.0"},"beta":true},{"t":"SCStreamError.Code.failedToStartAudioCapture","p":"documentation/ScreenCaptureKit/SCStreamError/Code/failedToStartAudioCapture","r":"Case","a":"An error message that indicates an audio stream failed to start.","v":{"iOS":"27.0","iPadOS":"27.0","Mac Catalyst":"18.2","macOS":"13.0","tvOS":"27.0","visionOS":"27.0"},"beta":true},{"t":"SCStreamError.Code.failedToStartMicrophoneCapture","p":"documentation/ScreenCaptureKit/SCStreamError/Code/failedToStartMicrophoneCapture","r":"Case","a":"An error message that indicates microphone capture failed to start.","v":{"iOS":"27.0","iPadOS":"27.0","Mac Catalyst":"18.2","macOS":"15.0","tvOS":"27.0","visionOS":"27.0"},"beta":true},{"t":"SCStreamError.Code.failedToStopAudioCapture","p":"documentation/ScreenCaptureKit/SCStreamError/Code/failedToStopAudioCapture","r":"Case","a":"An error message that indicates an audio stream failed to stop.","v":{"iOS":"27.0","iPadOS":"27.0","Mac Catalyst":"18.2","macOS":"13.0","tvOS":"27.0","visionOS":"27.0"},"beta":true},{"t":"SCStreamError.Code.insufficientStorage","p":"documentation/ScreenCaptureKit/SCStreamError/Code/insufficientStorage","r":"Case","v":{"iOS":"27.0","iPadOS":"27.0","Mac Catalyst":"27.0","macOS":"27.0","tvOS":"27.0","visionOS":"27.0"},"beta":true},{"t":"SCStreamError.Code.internalError","p":"documentation/ScreenCaptureKit/SCStreamError/Code/internalError","r":"Case","a":"An error message that indicates a stream can\u2019t start due to a failure in ScreenCaptureKit\u2019s internals.","v":{"iOS":"27.0","iPadOS":"27.0","Mac Catalyst":"18.2","macOS":"12.3","tvOS":"27.0","visionOS":"27.0"},"beta":true},{"t":"SCStreamError.Code.invalidParameter","p":"documentation/ScreenCaptureKit/SCStreamError/Code/invalidParameter","r":"Case","a":"An error message that indicates an operation failed because of an invalid parameter value.","v":{"iOS":"27.0","iPadOS":"27.0","Mac Catalyst":"18.2","macOS":"12.3","tvOS":"27.0","visionOS":"27.0"},"beta":true},{"t":"SCStreamError.Code.missingBackgroundMode","p":"documentation/ScreenCaptureKit/SCStreamError/Code/missingBackgroundMode","r":"Case","v":{"iOS":"27.0","iPadOS":"27.0","Mac Catalyst":"27.0","macOS":"12.3","tvOS":"27.0","visionOS":"27.0"},"beta":true},{"t":"SCStreamError.Code.missingEntitlements","p":"documentation/ScreenCaptureKit/SCStreamError/Code/missingEntitlements","r":"Case","a":"An error message that indicates missing entitlements in your app.","v":{"iOS":"27.0","iPadOS":"27.0","Mac Catalyst":"18.2","macOS":"12.3","tvOS":"27.0","visionOS":"27.0"},"beta":true},{"t":"SCStreamError.Code.noCaptureSource","p":"documentation/ScreenCaptureKit/SCStreamError/Code/noCaptureSource","r":"Case","a":"An error message that indicates a stream doesn\u2019t have a source to capture.","v":{"iOS":"27.0","iPadOS":"27.0","Mac Catalyst":"18.2","macOS":"12.3","tvOS":"27.0","visionOS":"27.0"},"beta":true},{"t":"SCStreamError.Code.noDisplayList","p":"documentation/ScreenCaptureKit/SCStreamError/Code/noDisplayList","r":"Case","a":"An error message that indicates a stream doesn\u2019t have displays available.","v":{"iOS":"27.0","iPadOS":"27.0","Mac Catalyst":"18.2","macOS":"12.3","tvOS":"27.0","visionOS":"27.0"},"beta":true},{"t":"SCStreamError.Code.noWindowList","p":"documentation/ScreenCaptureKit/SCStreamError/Code/noWindowList","r":"Case","a":"An error message that indicates a stream doesn\u2019t have windows available.","v":{"iOS":"27.0","iPadOS":"27.0","Mac Catalyst":"18.2","macOS":"12.3","tvOS":"27.0","visionOS":"27.0"},"beta":true},{"t":"SCStreamError.Code.notSupported","p":"documentation/ScreenCaptureKit/SCStreamError/Code/notSupported","r":"Case","v":{"iOS":"27.0","iPadOS":"27.0","Mac Catalyst":"27.0","macOS":"27.0","tvOS":"27.0","visionOS":"27.0"},"beta":true},{"t":"SCStreamError.Code.removingStream","p":"documentation/ScreenCaptureKit/SCStreamError/Code/removingStream","r":"Case","a":"An error message that indicates a stream wasn\u2019t removed.","v":{"iOS":"27.0","iPadOS":"27.0","Mac Catalyst":"18.2","macOS":"12.3","tvOS":"27.0","visionOS":"27.0"},"beta":true},{"t":"SCStreamError.Code.systemStoppedStream","p":"documentation/ScreenCaptureKit/SCStreamError/Code/systemStoppedStream","r":"Case","a":"An error message that indicates the system stopped the stream.","v":{"iOS":"27.0","iPadOS":"27.0","Mac Catalyst":"18.2","macOS":"15.0","tvOS":"27.0","visionOS":"27.0"},"beta":true},{"t":"SCStreamError.Code.userDeclined","p":"documentation/ScreenCaptureKit/SCStreamError/Code/userDeclined","r":"Case","a":"An error message that indicates the user didn\u2019t grant Screen Recording permission to your app.","v":{"iOS":"27.0","iPadOS":"27.0","Mac Catalyst":"18.2","macOS":"12.3","tvOS":"27.0","visionOS":"27.0"},"beta":true},{"t":"SCStreamError.Code.userStopped","p":"documentation/ScreenCaptureKit/SCStreamError/Code/userStopped","r":"Case","a":"An error message that indicates the user stopped the stream.","v":{"iOS":"27.0","iPadOS":"27.0","Mac Catalyst":"18.2","macOS":"12.3","tvOS":"27.0","visionOS":"27.0"},"beta":true},{"t":"SCStreamErrorDomain","p":"documentation/ScreenCaptureKit/SCStreamErrorDomain","r":"Global Variable","a":"A string representation of the error domain.","v":{"iOS":"27.0","iPadOS":"27.0","Mac Catalyst":"18.2","macOS":"12.3","tvOS":"27.0","visionOS":"27.0"},"beta":true},{"t":"SCStreamFrameInfo","p":"documentation/ScreenCaptureKit/SCStreamFrameInfo","r":"Structure","a":"An instance that defines metadata keys for a stream frame.","v":{"iOS":"27.0","iPadOS":"27.0","Mac Catalyst":"18.2","macOS":"12.3","tvOS":"27.0","visionOS":"27.0"},"beta":true},{"t":"SCStreamOutput","p":"documentation/ScreenCaptureKit/SCStreamOutput","r":"Protocol","a":"A delegate protocol your app implements to receive capture stream output events.","v":{"iOS":"27.0","iPadOS":"27.0","Mac Catalyst":"18.2","macOS":"12.3","tvOS":"27.0","visionOS":"27.0"},"beta":true},{"t":"SCStreamOutputType","p":"documentation/ScreenCaptureKit/SCStreamOutputType","r":"Enumeration","a":"Constants that represent output types for a stream frame.","v":{"iOS":"27.0","iPadOS":"27.0","Mac Catalyst":"18.2","macOS":"12.3","tvOS":"27.0","visionOS":"27.0"},"beta":true},{"t":"SCStreamOutputType.audio","p":"documentation/ScreenCaptureKit/SCStreamOutputType/audio","r":"Case","a":"An output type that represents an audio capture sample buffer.","v":{"iOS":"27.0","iPadOS":"27.0","Mac Catalyst":"18.2","macOS":"13.0","tvOS":"27.0","visionOS":"27.0"},"beta":true},{"t":"SCStreamOutputType.microphone","p":"documentation/ScreenCaptureKit/SCStreamOutputType/microphone","r":"Case","v":{"iOS":"27.0","iPadOS":"27.0","Mac Catalyst":"18.2","macOS":"15.0","visionOS":"27.0"},"beta":true},{"t":"SCStreamOutputType.screen","p":"documentation/ScreenCaptureKit/SCStreamOutputType/screen","r":"Case","a":"An output type that represents a screen capture sample buffer.","v":{"iOS":"27.0","iPadOS":"27.0","Mac Catalyst":"18.2","macOS":"12.3","tvOS":"27.0","visionOS":"27.0"},"beta":true},{"t":"SCStreamType","p":"documentation/ScreenCaptureKit/SCStreamType","r":"Enumeration","a":"The display type of the presented stream.","v":{"Mac Catalyst":"18.2","macOS":"14.0"}},{"t":"SCStreamType.display","p":"documentation/ScreenCaptureKit/SCStreamType/display","r":"Case","a":"The stream is currently on a complete display.","v":{"Mac Catalyst":"18.2","macOS":"14.0"}},{"t":"SCStreamType.window","p":"documentation/ScreenCaptureKit/SCStreamType/window","r":"Case","a":"The stream is currently presented as a window.","v":{"Mac Catalyst":"18.2","macOS":"14.0"}},{"t":"SCVideoEffectOutput","p":"documentation/ScreenCaptureKit/SCVideoEffectOutput","r":"Class","v":{"iOS":"27.0","iPadOS":"27.0","Mac Catalyst":"27.0"},"beta":true},{"t":"SCWindow","p":"documentation/ScreenCaptureKit/SCWindow","r":"Class","a":"An instance that represents an onscreen window.","v":{"Mac Catalyst":"18.2","macOS":"12.3"}},{"t":"ScreenCaptureKit","p":"documentation/ScreenCaptureKit","r":"Framework","a":"Stream screen content and audio to your app with fine-grained control over what you capture.","v":{"iOS":"27.0","iPadOS":"27.0","Mac Catalyst":"18.2","macOS":"12.3","tvOS":"27.0","visionOS":"27.0"},"beta":true},{"t":"add(_:)","p":"documentation/ScreenCaptureKit/SCContentSharingPicker/add(_:)","r":"Instance Method","a":"Adds an observer instance to notify of changes in the content-sharing picker."},{"t":"addClipBufferingOutput(_:)","p":"documentation/ScreenCaptureKit/SCStream/addClipBufferingOutput(_:)","r":"Instance Method"},{"t":"addRecordingOutput(_:)","p":"documentation/ScreenCaptureKit/SCStream/addRecordingOutput(_:)","r":"Instance Method"},{"t":"addStreamOutput(_:type:sampleHandlerQueue:)","p":"documentation/ScreenCaptureKit/SCStream/addStreamOutput(_:type:sampleHandlerQueue:)","r":"Instance Method","a":"Adds a destination that receives the stream output."},{"t":"addVideoEffectOutput(_:)","p":"documentation/ScreenCaptureKit/SCStream/addVideoEffectOutput(_:)","r":"Instance Method"},{"t":"allowedPickerModes","p":"documentation/ScreenCaptureKit/SCContentSharingPickerConfiguration-swift.struct/allowedPickerModes","r":"Instance Property","a":"The content-selection modes supported by the picker.","v":{"Mac Catalyst":"18.2","macOS":"14.0"}},{"t":"allowedPickerModes","p":"documentation/ScreenCaptureKit/SCContentSharingPickerConfiguration-c.class/allowedPickerModes","r":"Instance Property","a":"The content-selection modes supported by the picker.","v":{"Mac Catalyst":"18.2","macOS":"14.0"}},{"t":"allowsChangingSelectedContent","p":"documentation/ScreenCaptureKit/SCContentSharingPickerConfiguration-swift.struct/allowsChangingSelectedContent","r":"Instance Property","a":"A Boolean value that indicates if the present stream can change to a different source.","v":{"Mac Catalyst":"18.2","macOS":"14.0"}},{"t":"allowsChangingSelectedContent","p":"documentation/ScreenCaptureKit/SCContentSharingPickerConfiguration-c.class/allowsChangingSelectedContent","r":"Instance Property","a":"A Boolean value that indicates if the present stream can change to a different source.","v":{"Mac Catalyst":"18.2","macOS":"14.0"}},{"t":"applicationName","p":"documentation/ScreenCaptureKit/SCRunningApplication/applicationName","r":"Instance Property","a":"The display name of the app.","v":{"Mac Catalyst":"18.2","macOS":"12.3"}},{"t":"applications","p":"documentation/ScreenCaptureKit/SCShareableContent/applications","r":"Instance Property","a":"The apps available for capture.","v":{"Mac Catalyst":"18.2","macOS":"12.3"}},{"t":"attemptToConfigState","p":"documentation/ScreenCaptureKit/SCStreamError/attemptToConfigState","r":"Type Property","a":"An error message that indicates a stream couldn\u2019t update its configuration.","v":{"iOS":"27.0","iPadOS":"27.0","Mac Catalyst":"18.2","macOS":"12.3","tvOS":"27.0","visionOS":"27.0"},"beta":true},{"t":"attemptToStartStreamState","p":"documentation/ScreenCaptureKit/SCStreamError/attemptToStartStreamState","r":"Type Property","a":"An error message that indicates a stream is already running or doesn\u2019t exist when trying to start a stream.","v":{"iOS":"27.0","iPadOS":"27.0","Mac Catalyst":"18.2","macOS":"12.3","tvOS":"27.0","visionOS":"27.0"},"beta":true},{"t":"attemptToStopStreamState","p":"documentation/ScreenCaptureKit/SCStreamError/attemptToStopStreamState","r":"Type Property","a":"An error message that indicates a stream is already stopped or doesn\u2019t exist when trying to stop a stream.","v":{"iOS":"27.0","iPadOS":"27.0","Mac Catalyst":"18.2","macOS":"12.3","tvOS":"27.0","visionOS":"27.0"},"beta":true},{"t":"attemptToUpdateFilterState","p":"documentation/ScreenCaptureKit/SCStreamError/attemptToUpdateFilterState","r":"Type Property","a":"An error message that indicates a stream couldn\u2019t update its content filter.","v":{"iOS":"27.0","iPadOS":"27.0","Mac Catalyst":"18.2","macOS":"12.3","tvOS":"27.0","visionOS":"27.0"},"beta":true},{"t":"availableOutputFileTypes","p":"documentation/ScreenCaptureKit/SCRecordingOutputConfiguration/availableOutputFileTypes","r":"Instance Property","v":{"iOS":"27.0","iPadOS":"27.0","Mac Catalyst":"18.2","macOS":"15.0","tvOS":"27.0","visionOS":"27.0"},"beta":true},{"t":"availableVideoCodecTypes","p":"documentation/ScreenCaptureKit/SCRecordingOutputConfiguration/availableVideoCodecTypes","r":"Instance Property","v":{"iOS":"27.0","iPadOS":"27.0","Mac Catalyst":"18.2","macOS":"15.0","tvOS":"27.0","visionOS":"27.0"},"beta":true},{"t":"backgroundColor","p":"documentation/ScreenCaptureKit/SCStreamConfiguration/backgroundColor","r":"Instance Property","a":"A background color for the output.","v":{"Mac Catalyst":"18.2","macOS":"12.3"}},{"t":"boundingRect","p":"documentation/ScreenCaptureKit/SCStreamFrameInfo/boundingRect","r":"Type Property","a":"A key to retrieve the bounding rectangle for a video frame.","v":{"Mac Catalyst":"18.2","macOS":"14.0"}},{"t":"bundleIdentifier","p":"documentation/ScreenCaptureKit/SCRunningApplication/bundleIdentifier","r":"Instance Property","a":"The unique bundle identifier of the app.","v":{"Mac Catalyst":"18.2","macOS":"12.3"}},{"t":"cameraDevice","p":"documentation/ScreenCaptureKit/SCVideoEffectOutput/cameraDevice","r":"Instance Property","v":{"iOS":"27.0","iPadOS":"27.0","Mac Catalyst":"27.0"},"beta":true},{"t":"captureDynamicRange","p":"documentation/ScreenCaptureKit/SCStreamConfiguration/captureDynamicRange","r":"Instance Property","v":{"iOS":"27.0","iPadOS":"27.0","Mac Catalyst":"18.2","macOS":"15.0"},"beta":true},{"t":"captureImage(contentFilter:configuration:completionHandler:)","p":"documentation/ScreenCaptureKit/SCScreenshotManager/captureImage(contentFilter:configuration:completionHandler:)","r":"Type Method","a":"Captures a single frame from a stream as an image, using a filter."},{"t":"captureImage(in:completionHandler:)","p":"documentation/ScreenCaptureKit/SCScreenshotManager/captureImage(in:completionHandler:)","r":"Type Method"},{"t":"captureMicrophone","p":"documentation/ScreenCaptureKit/SCStreamConfiguration/captureMicrophone","r":"Instance Property","v":{"Mac Catalyst":"18.2","macOS":"15.0"}},{"t":"captureResolution","p":"documentation/ScreenCaptureKit/SCStreamConfiguration/captureResolution","r":"Instance Property","a":"The resolution at which to capture source content.","v":{"Mac Catalyst":"18.2","macOS":"14.0"}},{"t":"captureSampleBuffer(contentFilter:configuration:completionHandler:)","p":"documentation/ScreenCaptureKit/SCScreenshotManager/captureSampleBuffer(contentFilter:configuration:completionHandler:)","r":"Type Method","a":"Captures a single frame directly from a stream\u2019s buffer, using a filter."},{"t":"captureScreenshot(contentFilter:configuration:completionHandler:)","p":"documentation/ScreenCaptureKit/SCScreenshotManager/captureScreenshot(contentFilter:configuration:completionHandler:)","r":"Type Method"},{"t":"captureScreenshot(rect:configuration:completionHandler:)","p":"documentation/ScreenCaptureKit/SCScreenshotManager/captureScreenshot(rect:configuration:completionHandler:)","r":"Type Method"},{"t":"capturesAudio","p":"documentation/ScreenCaptureKit/SCStreamConfiguration/capturesAudio","r":"Instance Property","a":"A Boolean value that indicates whether to capture audio.","v":{"iOS":"27.0","iPadOS":"27.0","Mac Catalyst":"18.2","macOS":"13.0","tvOS":"27.0","visionOS":"27.0"},"beta":true},{"t":"capturesShadowsOnly","p":"documentation/ScreenCaptureKit/SCStreamConfiguration/capturesShadowsOnly","r":"Instance Property","a":"A Boolean value that indicates if the stream only captures shadows.","v":{"Mac Catalyst":"18.2","macOS":"14.0"}},{"t":"channelCount","p":"documentation/ScreenCaptureKit/SCStreamConfiguration/channelCount","r":"Instance Property","a":"The number of audio channels to capture.","v":{"iOS":"27.0","iPadOS":"27.0","Mac Catalyst":"18.2","macOS":"13.0","tvOS":"27.0","visionOS":"27.0"},"beta":true},{"t":"clipBufferingOutput(_:didFailWithError:)","p":"documentation/ScreenCaptureKit/SCClipBufferingOutputDelegate/clipBufferingOutput(_:didFailWithError:)","r":"Instance Method"},{"t":"clipBufferingOutputDidStartBuffering(_:)","p":"documentation/ScreenCaptureKit/SCClipBufferingOutputDelegate/clipBufferingOutputDidStartBuffering(_:)","r":"Instance Method"},{"t":"clipBufferingOutputDidStopBuffering(_:)","p":"documentation/ScreenCaptureKit/SCClipBufferingOutputDelegate/clipBufferingOutputDidStopBuffering(_:)","r":"Instance Method"},{"t":"colorMatrix","p":"documentation/ScreenCaptureKit/SCStreamConfiguration/colorMatrix","r":"Instance Property","a":"A color matrix to apply to the output surface.","v":{"Mac Catalyst":"18.2","macOS":"12.3"}},{"t":"colorSpaceName","p":"documentation/ScreenCaptureKit/SCStreamConfiguration/colorSpaceName","r":"Instance Property","a":"A color space to use for the output buffer.","v":{"Mac Catalyst":"18.2","macOS":"12.3"}},{"t":"configuration","p":"documentation/ScreenCaptureKit/SCContentSharingPicker/configuration","r":"Instance Property","a":"Sets the configuration for the content capture picker for all streams, providing allowed selection modes and content excluded from selection.","v":{"iOS":"27.0","iPadOS":"27.0","Mac Catalyst":"18.2","macOS":"14.0","tvOS":"27.0","visionOS":"27.0"},"beta":true},{"t":"contentRect","p":"documentation/ScreenCaptureKit/SCStreamFrameInfo/contentRect","r":"Type Property","a":"A key to retrieve the content rectangle of a video frame.","v":{"iOS":"27.0","iPadOS":"27.0","Mac Catalyst":"18.2","macOS":"12.3","tvOS":"27.0","visionOS":"27.0"},"beta":true},{"t":"contentRect","p":"documentation/ScreenCaptureKit/SCShareableContentInfo/contentRect","r":"Instance Property","a":"The size and location of content for the stream.","v":{"Mac Catalyst":"18.2","macOS":"14.0"}},{"t":"contentRect","p":"documentation/ScreenCaptureKit/SCContentFilter/contentRect","r":"Instance Property","a":"The size and location of the content to filter, in screen points.","v":{"iOS":"27.0","iPadOS":"27.0","Mac Catalyst":"18.2","macOS":"14.0","tvOS":"27.0","visionOS":"27.0"},"beta":true},{"t":"contentScale","p":"documentation/ScreenCaptureKit/SCStreamFrameInfo/contentScale","r":"Type Property","a":"A key to retrieve the content scale of a video frame.","v":{"iOS":"27.0","iPadOS":"27.0","Mac Catalyst":"18.2","macOS":"12.3","tvOS":"27.0","visionOS":"27.0"},"beta":true},{"t":"contentSharingPicker(_:didCancelFor:)","p":"documentation/ScreenCaptureKit/SCContentSharingPickerObserver/contentSharingPicker(_:didCancelFor:)","r":"Instance Method","a":"Tells the observer that a sharing picker canceled selection for a stream."},{"t":"contentSharingPicker(_:didUpdateWith:for:)","p":"documentation/ScreenCaptureKit/SCContentSharingPickerObserver/contentSharingPicker(_:didUpdateWith:for:)","r":"Instance Method","a":"Tells the observer that a sharing picker updated the content filter for a stream."},{"t":"contentSharingPickerStartDidFailWithError(_:)","p":"documentation/ScreenCaptureKit/SCContentSharingPickerObserver/contentSharingPickerStartDidFailWithError(_:)","r":"Instance Method","a":"Tells the observer that a sharing picker was unable to start."},{"t":"contentType","p":"documentation/ScreenCaptureKit/SCScreenshotConfiguration/contentType","r":"Instance Property","a":"A uniform type identifier that specifies the screenshot\u2019s file format; HEIC, JPEG, or PNG.","v":{"Mac Catalyst":"26.0","macOS":"26.0"}},{"t":"defaultConfiguration","p":"documentation/ScreenCaptureKit/SCContentSharingPicker/defaultConfiguration-94q2b","r":"Instance Property","a":"The default configuration to use for the content capture picker.","v":{"iOS":"27.0","iPadOS":"27.0","Mac Catalyst":"18.2","macOS":"14.0","tvOS":"27.0","visionOS":"27.0"},"beta":true},{"t":"defaultConfiguration","p":"documentation/ScreenCaptureKit/SCContentSharingPicker/defaultConfiguration-9v5sa","r":"Instance Property","a":"The default configuration to use for the content capture picker.","v":{"iOS":"27.0","iPadOS":"27.0","Mac Catalyst":"18.2","macOS":"14.0","tvOS":"27.0","visionOS":"27.0"},"beta":true},{"t":"delegate","p":"documentation/ScreenCaptureKit/SCRecordingEditor/delegate","r":"Instance Property","v":{"iOS":"27.0","iPadOS":"27.0","Mac Catalyst":"27.0","macOS":"27.0","tvOS":"27.0","visionOS":"27.0"},"beta":true},{"t":"destinationRect","p":"documentation/ScreenCaptureKit/SCStreamConfiguration/destinationRect","r":"Instance Property","a":"A rectangle that specifies a destination into which to write the output.","v":{"Mac Catalyst":"18.2","macOS":"12.3"}},{"t":"destinationRect","p":"documentation/ScreenCaptureKit/SCScreenshotConfiguration/destinationRect","r":"Instance Property","a":"A rectangle that specifies whether to output screenshots in a subset of the output image.","v":{"Mac Catalyst":"26.0","macOS":"26.0"}},{"t":"dirtyRects","p":"documentation/ScreenCaptureKit/SCStreamFrameInfo/dirtyRects","r":"Type Property","a":"A key to retrieve the areas of a video frame that contain changes.","v":{"Mac Catalyst":"18.2","macOS":"12.3"}},{"t":"displayID","p":"documentation/ScreenCaptureKit/SCDisplay/displayID","r":"Instance Property","a":"The Core Graphics display identifier.","v":{"Mac Catalyst":"18.2","macOS":"12.3"}},{"t":"displayIntent","p":"documentation/ScreenCaptureKit/SCScreenshotConfiguration/displayIntent-swift.property","r":"Instance Property","a":"Specifies whether the screen capture uses attributes of the local or canonical display.","v":{"Mac Catalyst":"26.0","macOS":"26.0"}},{"t":"displayTime","p":"documentation/ScreenCaptureKit/SCStreamFrameInfo/displayTime","r":"Type Property","a":"A key to retrieve the display time of a video frame.","v":{"iOS":"27.0","iPadOS":"27.0","Mac Catalyst":"18.2","macOS":"12.3","tvOS":"27.0","visionOS":"27.0"},"beta":true},{"t":"displays","p":"documentation/ScreenCaptureKit/SCShareableContent/displays","r":"Instance Property","a":"The displays available for capture.","v":{"Mac Catalyst":"18.2","macOS":"12.3"}},{"t":"dynamicRange","p":"documentation/ScreenCaptureKit/SCScreenshotConfiguration/dynamicRange-swift.property","r":"Instance Property","a":"Specifies the type of image returned to the client; standard dynamic range, high dynamic range, or both.","v":{"Mac Catalyst":"26.0","macOS":"26.0"}},{"t":"errorDomain","p":"documentation/ScreenCaptureKit/SCStreamError/errorDomain","r":"Type Property","v":{"iOS":"27.0","iPadOS":"27.0","Mac Catalyst":"18.2","macOS":"12.3","tvOS":"27.0","visionOS":"27.0"},"beta":true},{"t":"excludedBundleIDs","p":"documentation/ScreenCaptureKit/SCContentSharingPickerConfiguration-swift.struct/excludedBundleIDs","r":"Instance Property","a":"A list of bundle IDs to exclude from the sharing picker.","v":{"Mac Catalyst":"18.2","macOS":"14.0"}},{"t":"excludedBundleIDs","p":"documentation/ScreenCaptureKit/SCContentSharingPickerConfiguration-c.class/excludedBundleIDs","r":"Instance Property","a":"A list of bundle IDs to exclude from the sharing picker.","v":{"Mac Catalyst":"18.2","macOS":"14.0"}},{"t":"excludedWindowIDs","p":"documentation/ScreenCaptureKit/SCContentSharingPickerConfiguration-c.class/excludedWindowIDs","r":"Instance Property","a":"A list of window IDs to exclude from the sharing picker.","v":{"Mac Catalyst":"18.2","macOS":"14.0"}},{"t":"excludedWindowIDs","p":"documentation/ScreenCaptureKit/SCContentSharingPickerConfiguration-swift.struct/excludedWindowIDs","r":"Instance Property","a":"A list of window IDs to exclude from the sharing picker.","v":{"Mac Catalyst":"18.2","macOS":"14.0"}},{"t":"excludesCurrentProcessAudio","p":"documentation/ScreenCaptureKit/SCStreamConfiguration/excludesCurrentProcessAudio","r":"Instance Property","a":"A Boolean value that indicates whether to exclude audio from your app during capture.","v":{"iOS":"27.0","iPadOS":"27.0","Mac Catalyst":"18.2","macOS":"13.0","tvOS":"27.0","visionOS":"27.0"},"beta":true},{"t":"exportClip(to:duration:completionHandler:)","p":"documentation/ScreenCaptureKit/SCClipBufferingOutput/exportClip(to:duration:completionHandler:)","r":"Instance Method"},{"t":"failedApplicationConnectionInterrupted","p":"documentation/ScreenCaptureKit/SCStreamError/failedApplicationConnectionInterrupted","r":"Type Property","a":"An error message that indicates there was an interruption in a connection to an app.","v":{"iOS":"27.0","iPadOS":"27.0","Mac Catalyst":"18.2","macOS":"12.3","tvOS":"27.0","visionOS":"27.0"},"beta":true},{"t":"failedApplicationConnectionInvalid","p":"documentation/ScreenCaptureKit/SCStreamError/failedApplicationConnectionInvalid","r":"Type Property","a":"An error message that indicates the stream lost its connection to an app.","v":{"iOS":"27.0","iPadOS":"27.0","Mac Catalyst":"18.2","macOS":"12.3","tvOS":"27.0","visionOS":"27.0"},"beta":true},{"t":"failedNoMatchingApplicationContext","p":"documentation/ScreenCaptureKit/SCStreamError/failedNoMatchingApplicationContext","r":"Type Property","a":"An error message that indicates there isn\u2019t a matching app context for streaming.","v":{"iOS":"27.0","iPadOS":"27.0","Mac Catalyst":"18.2","macOS":"12.3","tvOS":"27.0","visionOS":"27.0"},"beta":true},{"t":"failedToStart","p":"documentation/ScreenCaptureKit/SCStreamError/failedToStart","r":"Type Property","a":"An error message that indicates a stream failed to start.","v":{"iOS":"27.0","iPadOS":"27.0","Mac Catalyst":"18.2","macOS":"12.3","tvOS":"27.0","visionOS":"27.0"},"beta":true},{"t":"failedToStartAudioCapture","p":"documentation/ScreenCaptureKit/SCStreamError/failedToStartAudioCapture","r":"Type Property","a":"An error message that indicates an audio stream failed to start.","v":{"iOS":"27.0","iPadOS":"27.0","Mac Catalyst":"18.2","macOS":"13.0","tvOS":"27.0","visionOS":"27.0"},"beta":true},{"t":"failedToStartMicrophoneCapture","p":"documentation/ScreenCaptureKit/SCStreamError/failedToStartMicrophoneCapture","r":"Type Property","a":"An error message that indicates microphone capture failed to start.","v":{"iOS":"27.0","iPadOS":"27.0","Mac Catalyst":"18.2","macOS":"15.0","tvOS":"27.0","visionOS":"27.0"},"beta":true},{"t":"failedToStopAudioCapture","p":"documentation/ScreenCaptureKit/SCStreamError/failedToStopAudioCapture","r":"Type Property","a":"An error message that indicates an audio stream failed to stop.","v":{"iOS":"27.0","iPadOS":"27.0","Mac Catalyst":"18.2","macOS":"13.0","tvOS":"27.0","visionOS":"27.0"},"beta":true},{"t":"fileURL","p":"documentation/ScreenCaptureKit/SCScreenshotConfiguration/fileURL","r":"Instance Property","a":"Specifies the URL where the screenshot process saves the output.","v":{"Mac Catalyst":"26.0","macOS":"26.0"}},{"t":"fileURL","p":"documentation/ScreenCaptureKit/SCScreenshotOutput/fileURL","r":"Instance Property","a":"A URL property that specifies the location of the saved image.","v":{"Mac Catalyst":"26.0","macOS":"26.0"}},{"t":"frame","p":"documentation/ScreenCaptureKit/SCWindow/frame","r":"Instance Property","a":"A rectangle the represents the frame of the window within a display.","v":{"Mac Catalyst":"18.2","macOS":"12.3"}},{"t":"frame","p":"documentation/ScreenCaptureKit/SCDisplay/frame","r":"Instance Property","a":"The frame of the display.","v":{"Mac Catalyst":"18.2","macOS":"12.3"}},{"t":"getCurrentProcessShareableContent(completionHandler:)","p":"documentation/ScreenCaptureKit/SCShareableContent/getCurrentProcessShareableContent(completionHandler:)","r":"Type Method"},{"t":"getExcludingDesktopWindows(_:onScreenWindowsOnly:completionHandler:)","p":"documentation/ScreenCaptureKit/SCShareableContent/getExcludingDesktopWindows(_:onScreenWindowsOnly:completionHandler:)","r":"Type Method","a":"Retrieves the displays, apps, and windows that match your criteria."},{"t":"getExcludingDesktopWindows(_:onScreenWindowsOnlyAbove:completionHandler:)","p":"documentation/ScreenCaptureKit/SCShareableContent/getExcludingDesktopWindows(_:onScreenWindowsOnlyAbove:completionHandler:)","r":"Type Method","a":"Retrieves the displays, apps, and windows that are in front of the specified window."},{"t":"getExcludingDesktopWindows(_:onScreenWindowsOnlyBelow:completionHandler:)","p":"documentation/ScreenCaptureKit/SCShareableContent/getExcludingDesktopWindows(_:onScreenWindowsOnlyBelow:completionHandler:)","r":"Type Method","a":"Retrieves the displays, apps, and windows that are behind the specified window."},{"t":"getWithCompletionHandler(_:)","p":"documentation/ScreenCaptureKit/SCShareableContent/getWithCompletionHandler(_:)","r":"Type Method","a":"Retrieves the displays, apps, and windows that your app can capture."},{"t":"hdrImage","p":"documentation/ScreenCaptureKit/SCScreenshotOutput/hdrImage","r":"Instance Property","a":"An output property that specifies the high dynamic range version of the screenshot.","v":{"Mac Catalyst":"26.0","macOS":"26.0"}},{"t":"height","p":"documentation/ScreenCaptureKit/SCStreamConfiguration/height","r":"Instance Property","a":"The height of the output.","v":{"iOS":"27.0","iPadOS":"27.0","Mac Catalyst":"18.2","macOS":"12.3","tvOS":"27.0"},"beta":true},{"t":"height","p":"documentation/ScreenCaptureKit/SCScreenshotConfiguration/height","r":"Instance Property","a":"An integer value that specifies the output height, measured in pixels.","v":{"Mac Catalyst":"26.0","macOS":"26.0"}},{"t":"height","p":"documentation/ScreenCaptureKit/SCDisplay/height","r":"Instance Property","a":"The height of the display in points.","v":{"Mac Catalyst":"18.2","macOS":"12.3"}},{"t":"ignoreClipping","p":"documentation/ScreenCaptureKit/SCScreenshotConfiguration/ignoreClipping","r":"Instance Property","a":"A Boolean value that specifies whether to ignore framing on windows when using content filters.","v":{"Mac Catalyst":"26.0","macOS":"26.0"}},{"t":"ignoreGlobalClipDisplay","p":"documentation/ScreenCaptureKit/SCStreamConfiguration/ignoreGlobalClipDisplay","r":"Instance Property","a":"A Boolean value that indicates if the stream ignores content clipped past the edge of a display, when streaming in display style.","v":{"Mac Catalyst":"18.2","macOS":"14.0"}},{"t":"ignoreGlobalClipSingleWindow","p":"documentation/ScreenCaptureKit/SCStreamConfiguration/ignoreGlobalClipSingleWindow","r":"Instance Property","a":"A Boolean value that indicates if the stream ignores content clipped past the edge of a display, when streaming in window style.","v":{"Mac Catalyst":"18.2","macOS":"14.0"}},{"t":"ignoreShadows","p":"documentation/ScreenCaptureKit/SCScreenshotConfiguration/ignoreShadows","r":"Instance Property","a":"A Boolean value that specifies whether to ignore framing on windows.","v":{"Mac Catalyst":"26.0","macOS":"26.0"}},{"t":"ignoreShadowsDisplay","p":"documentation/ScreenCaptureKit/SCStreamConfiguration/ignoreShadowsDisplay","r":"Instance Property","a":"A Boolean value that indicates if the stream ignores the capturing of window shadows when streaming in display style.","v":{"Mac Catalyst":"18.2","macOS":"14.0"}},{"t":"ignoreShadowsSingleWindow","p":"documentation/ScreenCaptureKit/SCStreamConfiguration/ignoreShadowsSingleWindow","r":"Instance Property","a":"A Boolean value that indicates if the stream ignores the capturing of window shadows when streaming in window style.","v":{"Mac Catalyst":"18.2","macOS":"14.0"}},{"t":"includeChildWindows","p":"documentation/ScreenCaptureKit/SCStreamConfiguration/includeChildWindows","r":"Instance Property","v":{"Mac Catalyst":"18.2","macOS":"14.2"}},{"t":"includeChildWindows","p":"documentation/ScreenCaptureKit/SCScreenshotConfiguration/includeChildWindows","r":"Instance Property","a":"A Boolean that specifies whether the screenshot captures subwindows of the included apps and windows.","v":{"Mac Catalyst":"26.0","macOS":"26.0"}},{"t":"includeMenuBar","p":"documentation/ScreenCaptureKit/SCContentFilter/includeMenuBar","r":"Instance Property","v":{"Mac Catalyst":"18.2","macOS":"14.2"}},{"t":"includedApplications","p":"documentation/ScreenCaptureKit/SCContentFilter/includedApplications","r":"Instance Property","v":{"Mac Catalyst":"18.2","macOS":"15.2"}},{"t":"includedDisplays","p":"documentation/ScreenCaptureKit/SCContentFilter/includedDisplays","r":"Instance Property","v":{"Mac Catalyst":"18.2","macOS":"15.2"}},{"t":"includedWindows","p":"documentation/ScreenCaptureKit/SCContentFilter/includedWindows","r":"Instance Property","v":{"Mac Catalyst":"18.2","macOS":"15.2"}},{"t":"info(for:)","p":"documentation/ScreenCaptureKit/SCShareableContent/info(for:)","r":"Type Method","a":"Retrieves any available sharable content information that matches the provided filter."},{"t":"init()","p":"documentation/ScreenCaptureKit/SCContentSharingPickerConfiguration-swift.struct/init()","r":"Initializer","a":"Initializes a picker configuration with default values.","v":{"iOS":"27.0","iPadOS":"27.0","Mac Catalyst":"18.2","macOS":"14.0","tvOS":"27.0","visionOS":"27.0"},"beta":true},{"t":"init(URL:)","p":"documentation/ScreenCaptureKit/SCRecordingEditor/init(URL:)-1k2cv","r":"Initializer"},{"t":"init(cameraDevice:)","p":"documentation/ScreenCaptureKit/SCVideoEffectOutput/init(cameraDevice:)","r":"Initializer"},{"t":"init(configuration:delegate:)","p":"documentation/ScreenCaptureKit/SCRecordingOutput/init(configuration:delegate:)","r":"Initializer"},{"t":"init(delegate:)","p":"documentation/ScreenCaptureKit/SCClipBufferingOutput/init(delegate:)","r":"Initializer"},{"t":"init(desktopIndependentWindow:)","p":"documentation/ScreenCaptureKit/SCContentFilter/init(desktopIndependentWindow:)","r":"Initializer","a":"Creates a filter that captures only the specified window."},{"t":"init(display:excludingApplications:exceptingWindows:)","p":"documentation/ScreenCaptureKit/SCContentFilter/init(display:excludingApplications:exceptingWindows:)","r":"Initializer","a":"Creates a filter that captures a display, excluding windows of the specified apps."},{"t":"init(display:excludingWindows:)","p":"documentation/ScreenCaptureKit/SCContentFilter/init(display:excludingWindows:)","r":"Initializer","a":"Creates a filter that captures the contents of a display, excluding the specified windows."},{"t":"init(display:including:)","p":"documentation/ScreenCaptureKit/SCContentFilter/init(display:including:)","r":"Initializer","a":"Creates a filter that captures only specific windows from a display."},{"t":"init(display:including:exceptingWindows:)","p":"documentation/ScreenCaptureKit/SCContentFilter/init(display:including:exceptingWindows:)","r":"Initializer","a":"Creates a filter that captures a display, including only windows of the specified apps."},{"t":"init(display:includingApplications:exceptingWindows:)","p":"documentation/ScreenCaptureKit/SCContentFilter/init(display:includingApplications:exceptingWindows:)","r":"Initializer"},{"t":"init(display:includingWindows:)","p":"documentation/ScreenCaptureKit/SCContentFilter/init(display:includingWindows:)","r":"Initializer"},{"t":"init(filter:configuration:delegate:)","p":"documentation/ScreenCaptureKit/SCStream/init(filter:configuration:delegate:)","r":"Initializer","a":"Creates a stream with a content filter and configuration."},{"t":"init(preset:)","p":"documentation/ScreenCaptureKit/SCStreamConfiguration/init(preset:)","r":"Initializer"},{"t":"init(rawValue:)","p":"documentation/ScreenCaptureKit/SCStreamOutputType/init(rawValue:)","r":"Initializer"},{"t":"init(rawValue:)","p":"documentation/ScreenCaptureKit/SCStreamFrameInfo/init(rawValue:)","r":"Initializer","a":"Creates a new instance with a raw value."},{"t":"init(rawValue:)","p":"documentation/ScreenCaptureKit/SCScreenshotConfiguration/DynamicRange-swift.enum/init(rawValue:)","r":"Initializer","a":"Creates a dynamic range object from the specified raw value."},{"t":"init(rawValue:)","p":"documentation/ScreenCaptureKit/SCContentSharingPickerMode/init(rawValue:)","r":"Initializer","a":"Initializes a sharing-picker mode."},{"t":"init(rawValue:)","p":"documentation/ScreenCaptureKit/SCRecordingEditor/Mode/init(rawValue:)","r":"Initializer"},{"t":"init(rawValue:)","p":"documentation/ScreenCaptureKit/SCFrameStatus/init(rawValue:)","r":"Initializer"},{"t":"init(rawValue:)","p":"documentation/ScreenCaptureKit/SCStreamError/Code/init(rawValue:)","r":"Initializer"},{"t":"init(rawValue:)","p":"documentation/ScreenCaptureKit/SCScreenshotConfiguration/DisplayIntent-swift.enum/init(rawValue:)","r":"Initializer","a":"Creates a display intent object from the specified raw value."},{"t":"init(rawValue:)","p":"documentation/ScreenCaptureKit/SCShareableContentStyle/init(rawValue:)","r":"Initializer"},{"t":"init(rawValue:)","p":"documentation/ScreenCaptureKit/SCStreamType/init(rawValue:)","r":"Initializer"},{"t":"init(rawValue:)","p":"documentation/ScreenCaptureKit/SCPresenterOverlayAlertSetting/init(rawValue:)","r":"Initializer"},{"t":"init(rawValue:)","p":"documentation/ScreenCaptureKit/SCCaptureResolutionType/init(rawValue:)","r":"Initializer"},{"t":"init(rawValue:)","p":"documentation/ScreenCaptureKit/SCCaptureDynamicRange/init(rawValue:)","r":"Initializer"},{"t":"init(rawValue:)","p":"documentation/ScreenCaptureKit/SCStreamConfiguration/Preset/init(rawValue:)","r":"Initializer"},{"t":"init(url:)","p":"documentation/ScreenCaptureKit/SCRecordingEditor/init(url:)-ead5","r":"Initializer"},{"t":"insufficientStorage","p":"documentation/ScreenCaptureKit/SCStreamError/insufficientStorage","r":"Type Property","v":{"iOS":"27.0","iPadOS":"27.0","Mac Catalyst":"27.0","macOS":"27.0","tvOS":"27.0","visionOS":"27.0"},"beta":true},{"t":"internalError","p":"documentation/ScreenCaptureKit/SCStreamError/internalError","r":"Type Property","a":"An error message that indicates a stream can\u2019t start due to a failure in ScreenCaptureKit\u2019s internals.","v":{"iOS":"27.0","iPadOS":"27.0","Mac Catalyst":"18.2","macOS":"12.3","tvOS":"27.0","visionOS":"27.0"},"beta":true},{"t":"invalidParameter","p":"documentation/ScreenCaptureKit/SCStreamError/invalidParameter","r":"Type Property","a":"An error message that indicates an operation failed because of an invalid parameter value.","v":{"iOS":"27.0","iPadOS":"27.0","Mac Catalyst":"18.2","macOS":"12.3","tvOS":"27.0","visionOS":"27.0"},"beta":true},{"t":"isActive","p":"documentation/ScreenCaptureKit/SCWindow/isActive","r":"Instance Property","a":"A Boolean value that indicates if the window is currently streaming.","v":{"Mac Catalyst":"18.2","macOS":"13.1"}},{"t":"isActive","p":"documentation/ScreenCaptureKit/SCContentSharingPicker/isActive","r":"Instance Property","a":"A Boolean value that indicates if the picker is active.","v":{"iOS":"27.0","iPadOS":"27.0","Mac Catalyst":"18.2","macOS":"14.0","tvOS":"27.0","visionOS":"27.0"},"beta":true},{"t":"isAvailable","p":"documentation/ScreenCaptureKit/SCContentSharingPicker/isAvailable","r":"Instance Property","v":{"iOS":"27.0","iPadOS":"27.0","Mac Catalyst":"27.0","macOS":"27.0","tvOS":"27.0","visionOS":"27.0"},"beta":true},{"t":"isCameraEnabled","p":"documentation/ScreenCaptureKit/SCContentFilter/isCameraEnabled","r":"Instance Property","v":{"iOS":"27.0","iPadOS":"27.0","Mac Catalyst":"27.0"},"beta":true},{"t":"isCapturing","p":"documentation/ScreenCaptureKit/SCStream/isCapturing","r":"Instance Property","v":{"iOS":"27.0","iPadOS":"27.0","Mac Catalyst":"27.0","macOS":"27.0","tvOS":"27.0","visionOS":"27.0"},"beta":true},{"t":"isMicrophoneEnabled","p":"documentation/ScreenCaptureKit/SCContentFilter/isMicrophoneEnabled","r":"Instance Property","v":{"iOS":"27.0","iPadOS":"27.0","Mac Catalyst":"27.0","macOS":"27.0","visionOS":"27.0"},"beta":true},{"t":"isOnScreen","p":"documentation/ScreenCaptureKit/SCWindow/isOnScreen","r":"Instance Property","a":"A Boolean value that indicates whether the window is on screen.","v":{"Mac Catalyst":"18.2","macOS":"12.3"}},{"t":"maximumStreamCount","p":"documentation/ScreenCaptureKit/SCContentSharingPicker/maximumStreamCount-66khx","r":"Instance Property","a":"The maximum number of streams the content capture picker allows.","v":{"Mac Catalyst":"18.2","macOS":"14.0"}},{"t":"maximumStreamCount","p":"documentation/ScreenCaptureKit/SCContentSharingPicker/maximumStreamCount-2kuaa","r":"Instance Property","a":"The maximum number of streams the content capture picker allows.","v":{"Mac Catalyst":"18.2","macOS":"14.0"}},{"t":"microphoneCaptureDeviceID","p":"documentation/ScreenCaptureKit/SCStreamConfiguration/microphoneCaptureDeviceID","r":"Instance Property","v":{"macOS":"15.0"}},{"t":"minimumFrameInterval","p":"documentation/ScreenCaptureKit/SCStreamConfiguration/minimumFrameInterval","r":"Instance Property","a":"The desired minimum time between frame updates, in seconds.","v":{"Mac Catalyst":"18.2","macOS":"12.3"}},{"t":"missingBackgroundMode","p":"documentation/ScreenCaptureKit/SCStreamError/missingBackgroundMode","r":"Type Property","v":{"iOS":"27.0","iPadOS":"27.0","Mac Catalyst":"27.0","macOS":"12.3","tvOS":"27.0","visionOS":"27.0"},"beta":true},{"t":"missingEntitlements","p":"documentation/ScreenCaptureKit/SCStreamError/missingEntitlements","r":"Type Property","a":"An error message that indicates missing entitlements in your app.","v":{"iOS":"27.0","iPadOS":"27.0","Mac Catalyst":"18.2","macOS":"12.3","tvOS":"27.0","visionOS":"27.0"},"beta":true},{"t":"mixesAudioWithMicrophone","p":"documentation/ScreenCaptureKit/SCRecordingOutputConfiguration/mixesAudioWithMicrophone","r":"Instance Property","v":{"iOS":"27.0","iPadOS":"27.0","Mac Catalyst":"27.0","macOS":"27.0","tvOS":"27.0","visionOS":"27.0"},"beta":true},{"t":"multipleApplications","p":"documentation/ScreenCaptureKit/SCContentSharingPickerMode/multipleApplications","r":"Type Property","a":"The mode allowing the selection of multiple applications through the presented picker.","v":{"Mac Catalyst":"18.2","macOS":"14.0"}},{"t":"multipleWindows","p":"documentation/ScreenCaptureKit/SCContentSharingPickerMode/multipleWindows","r":"Type Property","a":"The mode allowing the selection of multiple windows through the presented picker.","v":{"Mac Catalyst":"18.2","macOS":"14.0"}},{"t":"noCaptureSource","p":"documentation/ScreenCaptureKit/SCStreamError/noCaptureSource","r":"Type Property","a":"An error message that indicates a stream doesn\u2019t have a source to capture.","v":{"iOS":"27.0","iPadOS":"27.0","Mac Catalyst":"18.2","macOS":"12.3","tvOS":"27.0","visionOS":"27.0"},"beta":true},{"t":"noDisplayList","p":"documentation/ScreenCaptureKit/SCStreamError/noDisplayList","r":"Type Property","a":"An error message that indicates a stream doesn\u2019t have displays available.","v":{"iOS":"27.0","iPadOS":"27.0","Mac Catalyst":"18.2","macOS":"12.3","tvOS":"27.0","visionOS":"27.0"},"beta":true},{"t":"noWindowList","p":"documentation/ScreenCaptureKit/SCStreamError/noWindowList","r":"Type Property","a":"An error message that indicates a stream doesn\u2019t have windows available.","v":{"iOS":"27.0","iPadOS":"27.0","Mac Catalyst":"18.2","macOS":"12.3","tvOS":"27.0","visionOS":"27.0"},"beta":true},{"t":"notSupported","p":"documentation/ScreenCaptureKit/SCStreamError/notSupported","r":"Type Property","v":{"iOS":"27.0","iPadOS":"27.0","Mac Catalyst":"27.0","macOS":"27.0","tvOS":"27.0","visionOS":"27.0"},"beta":true},{"t":"outputFileType","p":"documentation/ScreenCaptureKit/SCRecordingOutputConfiguration/outputFileType","r":"Instance Property","v":{"iOS":"27.0","iPadOS":"27.0","Mac Catalyst":"18.2","macOS":"15.0","tvOS":"27.0","visionOS":"27.0"},"beta":true},{"t":"outputURL","p":"documentation/ScreenCaptureKit/SCRecordingOutputConfiguration/outputURL","r":"Instance Property","v":{"iOS":"27.0","iPadOS":"27.0","Mac Catalyst":"18.2","macOS":"15.0","tvOS":"27.0","visionOS":"27.0"},"beta":true},{"t":"outputVideoEffectDidFail(for:withError:)","p":"documentation/ScreenCaptureKit/SCStreamDelegate/outputVideoEffectDidFail(for:withError:)","r":"Instance Method"},{"t":"outputVideoEffectDidStart(for:)","p":"documentation/ScreenCaptureKit/SCStreamDelegate/outputVideoEffectDidStart(for:)","r":"Instance Method","a":"Tells the delegate that Presenter Overlay started."},{"t":"outputVideoEffectDidStop(for:)","p":"documentation/ScreenCaptureKit/SCStreamDelegate/outputVideoEffectDidStop(for:)","r":"Instance Method","a":"Tells the delegate that Presenter Overlay stopped."},{"t":"owningApplication","p":"documentation/ScreenCaptureKit/SCWindow/owningApplication","r":"Instance Property","a":"The app that owns the window.","v":{"Mac Catalyst":"18.2","macOS":"12.3"}},{"t":"pixelFormat","p":"documentation/ScreenCaptureKit/SCStreamConfiguration/pixelFormat","r":"Instance Property","a":"A pixel format for sample buffers that a stream outputs.","v":{"Mac Catalyst":"18.2","macOS":"12.3"}},{"t":"pointPixelScale","p":"documentation/ScreenCaptureKit/SCShareableContentInfo/pointPixelScale","r":"Instance Property","a":"The scaling from points to output pixel resolution for the stream.","v":{"Mac Catalyst":"18.2","macOS":"14.0"}},{"t":"pointPixelScale","p":"documentation/ScreenCaptureKit/SCContentFilter/pointPixelScale","r":"Instance Property","a":"The scaling factor used to translate screen points into pixels.","v":{"iOS":"27.0","iPadOS":"27.0","Mac Catalyst":"18.2","macOS":"14.0","tvOS":"27.0","visionOS":"27.0"},"beta":true},{"t":"present()","p":"documentation/ScreenCaptureKit/SCContentSharingPicker/present()","r":"Instance Method","a":"Displays the picker with no active selection for capture.","v":{"iOS":"27.0","iPadOS":"27.0","Mac Catalyst":"18.2","macOS":"14.0","visionOS":"27.0"},"beta":true},{"t":"present(for:)","p":"documentation/ScreenCaptureKit/SCContentSharingPicker/present(for:)","r":"Instance Method","a":"Displays the picker with an already running capture stream."},{"t":"present(for:using:)","p":"documentation/ScreenCaptureKit/SCContentSharingPicker/present(for:using:)","r":"Instance Method","a":"Displays the picker with an existing capture stream, allowing for a single type of capture selection."},{"t":"present(from:completionHandler:)","p":"documentation/ScreenCaptureKit/SCRecordingEditor/present(from:completionHandler:)-2atpt","r":"Instance Method"},{"t":"present(from:completionHandler:)","p":"documentation/ScreenCaptureKit/SCRecordingEditor/present(from:completionHandler:)-1nvxe","r":"Instance Method"},{"t":"present(from:mode:completionHandler:)","p":"documentation/ScreenCaptureKit/SCRecordingEditor/present(from:mode:completionHandler:)","r":"Instance Method"},{"t":"present(using:)","p":"documentation/ScreenCaptureKit/SCContentSharingPicker/present(using:)","r":"Instance Method","a":"Displays the picker for a single type of capture selection."},{"t":"presentForCurrentApplication()","p":"documentation/ScreenCaptureKit/SCContentSharingPicker/presentForCurrentApplication()","r":"Instance Method","v":{"iOS":"27.0","iPadOS":"27.0","Mac Catalyst":"27.0","tvOS":"27.0","visionOS":"27.0"},"beta":true},{"t":"presenterOverlayContentRect","p":"documentation/ScreenCaptureKit/SCStreamFrameInfo/presenterOverlayContentRect","r":"Type Property","v":{"Mac Catalyst":"18.2","macOS":"14.2"}},{"t":"presenterOverlayPrivacyAlertSetting","p":"documentation/ScreenCaptureKit/SCStreamConfiguration/presenterOverlayPrivacyAlertSetting","r":"Instance Property","a":"A value indicating if alerts appear to presenters while using Presenter Overlay.","v":{"Mac Catalyst":"18.2","macOS":"14.0"}},{"t":"preservesAspectRatio","p":"documentation/ScreenCaptureKit/SCStreamConfiguration/preservesAspectRatio","r":"Instance Property","a":"A Boolean value that determines if the stream preserves aspect ratio.","v":{"Mac Catalyst":"18.2","macOS":"14.0"}},{"t":"processID","p":"documentation/ScreenCaptureKit/SCRunningApplication/processID","r":"Instance Property","a":"The system process identifier of the app.","v":{"Mac Catalyst":"18.2","macOS":"12.3"}},{"t":"queueDepth","p":"documentation/ScreenCaptureKit/SCStreamConfiguration/queueDepth","r":"Instance Property","a":"The maximum number of frames for the queue to store.","v":{"Mac Catalyst":"18.2","macOS":"12.3"}},{"t":"recordedDuration","p":"documentation/ScreenCaptureKit/SCRecordingOutput/recordedDuration","r":"Instance Property","v":{"iOS":"27.0","iPadOS":"27.0","Mac Catalyst":"18.2","macOS":"15.0","tvOS":"27.0","visionOS":"27.0"},"beta":true},{"t":"recordedFileSize","p":"documentation/ScreenCaptureKit/SCRecordingOutput/recordedFileSize","r":"Instance Property","v":{"iOS":"27.0","iPadOS":"27.0","Mac Catalyst":"18.2","macOS":"15.0","tvOS":"27.0","visionOS":"27.0"},"beta":true},{"t":"recordingEditor(_:didFailWithError:)","p":"documentation/ScreenCaptureKit/SCRecordingEditorDelegate/recordingEditor(_:didFailWithError:)","r":"Instance Method"},{"t":"recordingEditorDidDismiss(_:)","p":"documentation/ScreenCaptureKit/SCRecordingEditorDelegate/recordingEditorDidDismiss(_:)","r":"Instance Method"},{"t":"recordingOutput(_:didFailWithError:)","p":"documentation/ScreenCaptureKit/SCRecordingOutputDelegate/recordingOutput(_:didFailWithError:)","r":"Instance Method"},{"t":"recordingOutputDidFinishRecording(_:)","p":"documentation/ScreenCaptureKit/SCRecordingOutputDelegate/recordingOutputDidFinishRecording(_:)","r":"Instance Method"},{"t":"recordingOutputDidStartRecording(_:)","p":"documentation/ScreenCaptureKit/SCRecordingOutputDelegate/recordingOutputDidStartRecording(_:)","r":"Instance Method"},{"t":"remove(_:)","p":"documentation/ScreenCaptureKit/SCContentSharingPicker/remove(_:)","r":"Instance Method","a":"Removes an observer instance from the content-sharing picker."},{"t":"removeClipBufferingOutput(_:)","p":"documentation/ScreenCaptureKit/SCStream/removeClipBufferingOutput(_:)","r":"Instance Method"},{"t":"removeRecordingOutput(_:)","p":"documentation/ScreenCaptureKit/SCStream/removeRecordingOutput(_:)","r":"Instance Method"},{"t":"removeStreamOutput(_:type:)","p":"documentation/ScreenCaptureKit/SCStream/removeStreamOutput(_:type:)","r":"Instance Method","a":"Removes a destination from receiving stream output."},{"t":"removeVideoEffectOutput(_:)","p":"documentation/ScreenCaptureKit/SCStream/removeVideoEffectOutput(_:)","r":"Instance Method"},{"t":"removingStream","p":"documentation/ScreenCaptureKit/SCStreamError/removingStream","r":"Type Property","a":"An error message that indicates a stream wasn\u2019t removed.","v":{"iOS":"27.0","iPadOS":"27.0","Mac Catalyst":"18.2","macOS":"12.3","tvOS":"27.0","visionOS":"27.0"},"beta":true},{"t":"sampleRate","p":"documentation/ScreenCaptureKit/SCStreamConfiguration/sampleRate","r":"Instance Property","a":"The sample rate for audio capture.","v":{"iOS":"27.0","iPadOS":"27.0","Mac Catalyst":"18.2","macOS":"13.0","tvOS":"27.0","visionOS":"27.0"},"beta":true},{"t":"scaleFactor","p":"documentation/ScreenCaptureKit/SCStreamFrameInfo/scaleFactor","r":"Type Property","a":"A key to retrieve the scale factor of a video frame.","v":{"iOS":"27.0","iPadOS":"27.0","Mac Catalyst":"18.2","macOS":"12.3","tvOS":"27.0","visionOS":"27.0"},"beta":true},{"t":"scalesToFit","p":"documentation/ScreenCaptureKit/SCStreamConfiguration/scalesToFit","r":"Instance Property","a":"A Boolean value that indicates whether to scale the output to fit the configured width and height.","v":{"Mac Catalyst":"18.2","macOS":"12.3"}},{"t":"screenRect","p":"documentation/ScreenCaptureKit/SCStreamFrameInfo/screenRect","r":"Type Property","a":"A key to retrieve the onscreen location of captured content.","v":{"iOS":"27.0","iPadOS":"27.0","Mac Catalyst":"18.2","macOS":"13.1","tvOS":"27.0","visionOS":"27.0"},"beta":true},{"t":"sdrImage","p":"documentation/ScreenCaptureKit/SCScreenshotOutput/sdrImage","r":"Instance Property","a":"An output property that specifies the standard dynamic range version of the screenshot.","v":{"Mac Catalyst":"26.0","macOS":"26.0"}},{"t":"setConfiguration(_:for:)","p":"documentation/ScreenCaptureKit/SCContentSharingPicker/setConfiguration(_:for:)","r":"Instance Method","a":"Sets the configuration for the content capture picker for a capture stream, providing allowed selection modes and content excluded from selection."},{"t":"setConfiguration:forStream:","p":"documentation/ScreenCaptureKit/SCContentSharingPicker/setConfiguration:forStream:","r":"Instance Method","a":"Sets the configuration for the content capture picker for a capture stream, providing allowed selection modes and content excluded from selection."},{"t":"shared","p":"documentation/ScreenCaptureKit/SCContentSharingPicker/shared","r":"Type Property","a":"The system-provided picker UI instance for capturing display and audio content from someone\u2019s Mac.","v":{"iOS":"27.0","iPadOS":"27.0","Mac Catalyst":"18.2","macOS":"14.0","tvOS":"27.0","visionOS":"27.0"},"beta":true},{"t":"shouldBeOpaque","p":"documentation/ScreenCaptureKit/SCStreamConfiguration/shouldBeOpaque","r":"Instance Property","a":"A Boolean value that indicates if semitransparent content presents as opaque.","v":{"Mac Catalyst":"18.2","macOS":"14.0"}},{"t":"showMouseClicks","p":"documentation/ScreenCaptureKit/SCStreamConfiguration/showMouseClicks","r":"Instance Property","v":{"Mac Catalyst":"18.2","macOS":"15.0"}},{"t":"showsCameraControl","p":"documentation/ScreenCaptureKit/SCContentSharingPickerConfiguration-swift.struct/showsCameraControl","r":"Instance Property","v":{"iOS":"27.0","iPadOS":"27.0","Mac Catalyst":"27.0","tvOS":"27.0"},"beta":true},{"t":"showsCameraControl","p":"documentation/ScreenCaptureKit/SCContentSharingPickerConfiguration-c.class/showsCameraControl","r":"Instance Property","v":{"iOS":"27.0","iPadOS":"27.0"},"beta":true},{"t":"showsCursor","p":"documentation/ScreenCaptureKit/SCStreamConfiguration/showsCursor","r":"Instance Property","a":"A Boolean value that determines whether the cursor is visible in the stream.","v":{"Mac Catalyst":"18.2","macOS":"12.3"}},{"t":"showsCursor","p":"documentation/ScreenCaptureKit/SCScreenshotConfiguration/showsCursor","r":"Instance Property","a":"A Boolean value that specifies whether the pointer appears in the screenshot.","v":{"Mac Catalyst":"26.0","macOS":"26.0"}},{"t":"showsMicrophoneControl","p":"documentation/ScreenCaptureKit/SCContentSharingPickerConfiguration-swift.struct/showsMicrophoneControl","r":"Instance Property","v":{"iOS":"27.0","iPadOS":"27.0","Mac Catalyst":"27.0","visionOS":"27.0"},"beta":true},{"t":"showsMicrophoneControl","p":"documentation/ScreenCaptureKit/SCContentSharingPickerConfiguration-c.class/showsMicrophoneControl","r":"Instance Property","v":{"iOS":"27.0","iPadOS":"27.0","visionOS":"27.0"},"beta":true},{"t":"singleApplication","p":"documentation/ScreenCaptureKit/SCContentSharingPickerMode/singleApplication","r":"Type Property","a":"The mode allowing the selection of a single application through the presented picker.","v":{"Mac Catalyst":"18.2","macOS":"14.0"}},{"t":"singleDisplay","p":"documentation/ScreenCaptureKit/SCContentSharingPickerMode/singleDisplay","r":"Type Property","a":"The mode allowing the selection of a single display through the presented picker.","v":{"Mac Catalyst":"18.2","macOS":"14.0"}},{"t":"singleWindow","p":"documentation/ScreenCaptureKit/SCContentSharingPickerMode/singleWindow","r":"Type Property","a":"The mode allowing the selection of a single window through the presented picker.","v":{"Mac Catalyst":"18.2","macOS":"14.0"}},{"t":"sourceRect","p":"documentation/ScreenCaptureKit/SCStreamConfiguration/sourceRect","r":"Instance Property","a":"A rectangle that specifies the source area to capture.","v":{"Mac Catalyst":"18.2","macOS":"12.3"}},{"t":"sourceRect","p":"documentation/ScreenCaptureKit/SCScreenshotConfiguration/sourceRect","r":"Instance Property","a":"A rectangle that specifies that the screenshot only samples a subset of the frame input.","v":{"Mac Catalyst":"26.0","macOS":"26.0"}},{"t":"startCapture(completionHandler:)","p":"documentation/ScreenCaptureKit/SCStream/startCapture(completionHandler:)","r":"Instance Method","a":"Starts the stream with a callback to indicate whether it successfully starts."},{"t":"status","p":"documentation/ScreenCaptureKit/SCStreamFrameInfo/status","r":"Type Property","a":"A key to retrieve the status of a video frame.","v":{"iOS":"27.0","iPadOS":"27.0","Mac Catalyst":"18.2","macOS":"12.3","tvOS":"27.0","visionOS":"27.0"},"beta":true},{"t":"stopCapture(completionHandler:)","p":"documentation/ScreenCaptureKit/SCStream/stopCapture(completionHandler:)","r":"Instance Method","a":"Stops the stream."},{"t":"stream(_:didOutputSampleBuffer:of:)","p":"documentation/ScreenCaptureKit/SCStreamOutput/stream(_:didOutputSampleBuffer:of:)","r":"Instance Method","a":"Tells the delegate that a capture stream produced a frame."},{"t":"stream(_:didStopWithError:)","p":"documentation/ScreenCaptureKit/SCStreamDelegate/stream(_:didStopWithError:)","r":"Instance Method","a":"Tells the delegate that the stream stopped with an error."},{"t":"streamDidBecomeActive(_:)","p":"documentation/ScreenCaptureKit/SCStreamDelegate/streamDidBecomeActive(_:)","r":"Instance Method"},{"t":"streamDidBecomeInactive(_:)","p":"documentation/ScreenCaptureKit/SCStreamDelegate/streamDidBecomeInactive(_:)","r":"Instance Method"},{"t":"streamName","p":"documentation/ScreenCaptureKit/SCStreamConfiguration/streamName","r":"Instance Property","a":"A name that you provide for identifying the stream.","v":{"Mac Catalyst":"18.2","macOS":"14.0"}},{"t":"streamType","p":"documentation/ScreenCaptureKit/SCContentFilter/streamType","r":"Instance Property","a":"The type of the streaming content.","v":{"Mac Catalyst":"18.2","macOS":"14.0"}},{"t":"style","p":"documentation/ScreenCaptureKit/SCShareableContentInfo/style","r":"Instance Property","a":"The current presentation style of the stream.","v":{"Mac Catalyst":"18.2","macOS":"14.0"}},{"t":"style","p":"documentation/ScreenCaptureKit/SCContentFilter/style","r":"Instance Property","a":"The display style of the sharable content.","v":{"iOS":"27.0","iPadOS":"27.0","Mac Catalyst":"18.2","macOS":"14.0","tvOS":"27.0","visionOS":"27.0"},"beta":true},{"t":"supportedContentTypes","p":"documentation/ScreenCaptureKit/SCScreenshotConfiguration/supportedContentTypes","r":"Type Property","a":"An array of uniform type identifiers that correspond to file formats the output image supports.","v":{"Mac Catalyst":"26.0","macOS":"26.0"}},{"t":"synchronizationClock","p":"documentation/ScreenCaptureKit/SCStream/synchronizationClock","r":"Instance Property","a":"A clock to use for output synchronization.","v":{"iOS":"27.0","iPadOS":"27.0","Mac Catalyst":"18.2","macOS":"13.0","tvOS":"27.0","visionOS":"27.0"},"beta":true},{"t":"systemStoppedStream","p":"documentation/ScreenCaptureKit/SCStreamError/systemStoppedStream","r":"Type Property","a":"An error message that indicates the system stopped the stream.","v":{"iOS":"27.0","iPadOS":"27.0","Mac Catalyst":"18.2","macOS":"15.0","tvOS":"27.0","visionOS":"27.0"},"beta":true},{"t":"title","p":"documentation/ScreenCaptureKit/SCWindow/title","r":"Instance Property","a":"The string that displays in a window\u2019s title bar.","v":{"Mac Catalyst":"18.2","macOS":"12.3"}},{"t":"updateConfiguration(_:completionHandler:)","p":"documentation/ScreenCaptureKit/SCStream/updateConfiguration(_:completionHandler:)","r":"Instance Method","a":"Updates the stream with a new configuration."},{"t":"updateContentFilter(_:completionHandler:)","p":"documentation/ScreenCaptureKit/SCStream/updateContentFilter(_:completionHandler:)","r":"Instance Method","a":"Updates the stream by applying a new content filter."},{"t":"userDeclined","p":"documentation/ScreenCaptureKit/SCStreamError/userDeclined","r":"Type Property","a":"An error message that indicates the user didn\u2019t grant Screen Recording permission to your app.","v":{"iOS":"27.0","iPadOS":"27.0","Mac Catalyst":"18.2","macOS":"12.3","tvOS":"27.0","visionOS":"27.0"},"beta":true},{"t":"userStopped","p":"documentation/ScreenCaptureKit/SCStreamError/userStopped","r":"Type Property","a":"An error message that indicates the user stopped the stream.","v":{"iOS":"27.0","iPadOS":"27.0","Mac Catalyst":"18.2","macOS":"12.3","tvOS":"27.0","visionOS":"27.0"},"beta":true},{"t":"videoCodecType","p":"documentation/ScreenCaptureKit/SCRecordingOutputConfiguration/videoCodecType","r":"Instance Property","v":{"iOS":"27.0","iPadOS":"27.0","Mac Catalyst":"18.2","macOS":"15.0","tvOS":"27.0","visionOS":"27.0"},"beta":true},{"t":"videoOrientation","p":"documentation/ScreenCaptureKit/SCStreamFrameInfo/videoOrientation","r":"Type Property","v":{"iOS":"27.0","iPadOS":"27.0","Mac Catalyst":"27.0","macOS":"27.0","visionOS":"27.0"},"beta":true},{"t":"width","p":"documentation/ScreenCaptureKit/SCStreamConfiguration/width","r":"Instance Property","a":"The width of the output.","v":{"iOS":"27.0","iPadOS":"27.0","Mac Catalyst":"18.2","macOS":"12.3","tvOS":"27.0"},"beta":true},{"t":"width","p":"documentation/ScreenCaptureKit/SCScreenshotConfiguration/width","r":"Instance Property","a":"An integer value that specifies the output width in pixels.","v":{"Mac Catalyst":"26.0","macOS":"26.0"}},{"t":"width","p":"documentation/ScreenCaptureKit/SCDisplay/width","r":"Instance Property","a":"The width of the display in points.","v":{"Mac Catalyst":"18.2","macOS":"12.3"}},{"t":"windowID","p":"documentation/ScreenCaptureKit/SCWindow/windowID","r":"Instance Property","a":"The Core Graphics window identifier.","v":{"Mac Catalyst":"18.2","macOS":"12.3"}},{"t":"windowLayer","p":"documentation/ScreenCaptureKit/SCWindow/windowLayer","r":"Instance Property","a":"The layer of the window relative to other windows.","v":{"Mac Catalyst":"18.2","macOS":"12.3"}},{"t":"windows","p":"documentation/ScreenCaptureKit/SCShareableContent/windows","r":"Instance Property","a":"The windows available for capture.","v":{"Mac Catalyst":"18.2","macOS":"12.3"}}]